Workbook

Sheet 기준가격대장(결산후)
A1: Column4 | B1: Column1 | C1: Column2 | D1: Column3 | E1: Column5 | F1: Column6 | G1: Column7 | H1: Column8
C2: 차변 | G2: 대변
A3: 코드 | B3: 당일잔액 | C3: 당일증감액 | D3: 전일잔액 | E3: 계정명 | F3: 전일잔액 | G3: 당일증감액 | H3: 당일잔액
A4: 100000 | B4: 153189360965 | C4: 35100224209 | D4: 153187595708 | E4: 자산합계 | F4: 0 | G4: 35098458952 | H4: 0
A5: 101010 | B5: 7196301321 | C5: 0 | D5: 7196301321 | E5: 예금 | F5: 0 | G5: 0 | H5: 0
A6: 111010 | B6: 106485058475 | C6: 33658782896 | D6: 73217869377 | E6: 상장주식 | F6: 0 | G6: 391593798 | H6: 0
A7: 113010 | B7: 5368673944 | C7: 1765255 | D7: 5366908689 | E7: 국채 | F7: 0 | G7: 0 | H7: 0
A8: 115010 | B8: 24463760580 | C8: 1046317003 | D8: 23417443577 | E8: 상장펀드 | F8: 0 | G8: 0 | H8: 0
A9: 139310 | B9: 8837106649 | C9: 0 | D9: 8837106649 | E9: 상장펀드미수입금 | F9: 0 | G9: 0 | H9: 0
A10: 139410 | B10: 584987500 | C10: 0 | D10: 584987500 | E10: 선물미수입금 | F10: 0 | G10: 0 | H10: 0
A11: 139810 | B11: 455343 | C11: 0 | D11: 455343 | E11: 대차거래미수입금 | F11: 0 | G11: 0 | H11: 0
A12: 147010 | B12: 221852625 | C12: 0 | D12: 221852625 | E12: 주식미수배당금 | F12: 0 | G12: 0 | H12: 0
A13: 149010 | B13: 661948 | C13: 0 | D13: 661948 | E13: 채권미수이자 | F13: 0 | G13: 0 | H13: 0
A14: 149110 | B14: 6231172 | C14: 0 | D14: 6231172 | E14: 예금미수이자 | F14: 0 | G14: 0 | H14: 0
A15: 151010 | B15: 24271408 | C15: 0 | D15: 24271408 | E15: 채권기경과이자 | F15: 0 | G15: 0 | H15: 0
... A78: 531012 | B78: 0 | C78: 33658782896 | D78: 0 | E78: 상장주식평가이익(비과세) | F78: 33658782896 | G78: 0 | H78: 0
A79: 533011 | B79: 0 | C79: 1765255 | D79: 0 | E79: 채권평가이익(과세) | F79: 1765255 | G79: 0 | H79: 0 | L79: 167470000000
A80: 537011 | B80: 0 | C80: 29549335 | D80: 0 | E80: 상장펀드평가이익(과세) | F80: 29549335 | G80: 0 | H80: 0
A81: 537012 | B81: 0 | C81: 1016767668 | D81: 0 | E81: 상장펀드평가이익(비과세) | F81: 1016767668 | G81: 0 | H81: 0
A82: 555011 | B82: 0 | C82: 831697 | D82: 0 | E82: 채권상환이익(과세) | F82: 831697 | G82: 0 | H82: 0
A83: 557011 | B83: 0 | C83: 928953970 | D83: 0 | E83: 주식수입배당금(과세) | F83: 928953970 | G83: 0 | H83: 0
A84: 557012 | B84: 0 | C84: 19589055 | D84: 0 | E84: 주식수입배당금(비과세) | F84: 19589055 | G84: 0 | H84: 0
A85: 557051 | B85: 0 | C85: 312007724 | D85: 0 | E85: 상장펀드수입배당금(과세) | F85: 312007724 | G85: 0 | H85: 0
A86: 557052 | B86: 0 | C86: 28135256 | D86: 0 | E86: 상장펀드수입배당금(비과세) | F86: 28135256 | G86: 0 | H86: 0 | L86: 24645700000000
A87: 559011 | B87: 0 | C87: 3000 | D87: 0 | E87: 주식배당액(과세) | F87: 3000 | G87: 0 | H87: 0
A88: 561011 | B88: 0 | C88: 661948 | D88: 0 | E88: 채권수입이자(과세) | F88: 661948 | G88: 0 | H88: 0
A89: 561111 | B89: 0 | C89: 87439722 | D89: 0 | E89: 예금수입이자(과세) | F89: 87439722 | G89: 0 | H89: 0
A90: 561211 | B90: 0 | C90: 1842187 | D90: 0 | E90: REPO수입이자(과세) | F90: 1842187 | G90: 0 | H90: 0
A91: 561231 | B91: 0 | C91: 3137321 | D91: 0 | E91: 위탁증거금수입이자(과세) | F91: 3137321 | G91: 0 | H91: 0
A92: 565031 | B92: 0 | C92: 5121934 | D92: 0 | E92: 대차거래수입수수료(과세) | F92: 5121934 | G92: 0 | H92: 0
A93: 567011 | B93: 0 | C93: 5890881 | D93: 0 | E93: 단주대금수령액(과세) | F93: 5890881 | G93: 0 | H93: 0
A94: 567012 | B94: 0 | C94: 643877 | D94: 0 | E94: 단주대금수령액(비과세) | F94: 643877 | G94: 0 | H94: 0
A95: 567111 | B95: 0 | C95: 3557 | D95: 0 | E95: 기타이익(과세) | F95: 3557 | G95: 0 | H95: 0
A96: 600000 | B96: 153189360965 | C96: 789450783835 | D96: 232508639335 | E96: 총합계 | F96: 232508639335 | G96: 789450783835 | H96: 153189360965
A97: 700001 | B97: 0 | C97: 0 | D97: 0 | E97: 순자산총액 | F97: 137368956901 | G97: 0 | H97: 137368956901
A98: 700002 | B98: 0 | C98: 0 | D98: 0 | E98: 과세순자산총액 | F98: 37354536107 | G98: 0 | H98: 37354536107
... A125: 700039 | B125: 0 | C125: 0 | D125: 0 | E125: 발행 CU수량 | F125: 29 | G125: 0 | H125: 29

Sheet 통합기준가격대장(결산후)
B2: 자산검증 | C2: =SUM(B7:B91)=B6 -> TRUE | D2: 부채검증 | E2: =SUM(I93:I146)=I92 -> TRUE | F2: 자본검증 | G2: =SUM(I148:I159)=I147 -> TRUE
B3: 비용검증 | C3: =SUM(D161:D262)=D160 -> TRUE | D3: 수익검증 | E3: =SUM(G264:G366)=G263 -> TRUE
B5: 당일잔액 | C5: 당일증감액 | D5: 전일잔액 | E5: 코드 | F5: 계정명 | G5: 전일잔액 | H5: 당일증감액 | I5: 당일잔액
B6: =IFERROR(VLOOKUP(E6,'기준가격대장(결산후)'!$A$4:$H$500,2,0),0) -> 153189360965 | C6: =IFERROR(VLOOKUP(E6,'기준가격대장(결산후)'!$A$4:$H$500,3,0),0) -> 35100224209 | D6: =IFERROR(VLOOKUP(E6,'기준가격대장(결산후)'!$A$4:$H$500,4,0),0) -> 153187595708 | E6: 100000 | F6: 자산합계 | G6: =IFERROR(VLOOKUP(E6,'기준가격대장(결산후)'!$A$4:$H$500,6,0),0) -> 0 | H6: =IFERROR(VLOOKUP(E6,'기준가격대장(결산후)'!$A$4:$H$500,7,0),0) -> 35098458952 | I6: =IFERROR(VLOOKUP(E6,'기준가격대장(결산후)'!$A$4:$H$500,8,0),0) -> 0
B7: =IFERROR(VLOOKUP(E7,'기준가격대장(결산후)'!$A$4:$H$500,2,0),0) -> 7196301321 | C7: =IFERROR(VLOOKUP(E7,'기준가격대장(결산후)'!$A$4:$H$500,3,0),0) -> 0 | D7: =IFERROR(VLOOKUP(E7,'기준가격대장(결산후)'!$A$4:$H$500,4,0),0) -> 7196301321 | E7: 101010 | F7: 예금 | G7: =IFERROR(VLOOKUP(E7,'기준가격대장(결산후)'!$A$4:$H$500,6,0),0) -> 0 | H7: =IFERROR(VLOOKUP(E7,'기준가격대장(결산후)'!$A$4:$H$500,7,0),0) -> 0 | I7: =IFERROR(VLOOKUP(E7,'기준가격대장(결산후)'!$A$4:$H$500,8,0),0) -> 0 | K7: 자산검증 | L7: =SUM(B7:B91)=B6 -> TRUE | M7: =SUM(B7:B91)-B6 -> 0
B8: =IFERROR(VLOOKUP(E8,'기준가격대장(결산후)'!$A$4:$H$500,2,0),0) -> 0 | C8: =IFERROR(VLOOKUP(E8,'기준가격대장(결산후)'!$A$4:$H$500,3,0),0) -> 0 | D8: =IFERROR(VLOOKUP(E8,'기준가격대장(결산후)'!$A$4:$H$500,4,0),0) -> 0 | E8: 101050 | F8: 외화예금 | G8: =IFERROR(VLOOKUP(E8,'기준가격대장(결산후)'!$A$4:$H$500,6,0),0) -> 0 | H8: =IFERROR(VLOOKUP(E8,'기준가격대장(결산후)'!$A$4:$H$500,7,0),0) -> 0 | I8: =IFERROR(VLOOKUP(E8,'기준가격대장(결산후)'!$A$4:$H$500,8,0),0) -> 0 | L8: <<FALSE 나오면 조서에 없는 계정이 해당펀드 기준가격대장에 있으므로 추가해야함
B9: =IFERROR(VLOOKUP(E9,'기준가격대장(결산후)'!$A$4:$H$500,2,0),0) -> 0 | C9: =IFERROR(VLOOKUP(E9,'기준가격대장(결산후)'!$A$4:$H$500,3,0),0) -> 0 | D9: =IFERROR(VLOOKUP(E9,'기준가격대장(결산후)'!$A$4:$H$500,4,0),0) -> 0 | E9: 103010 | F9: 콜론 | G9: =IFERROR(VLOOKUP(E9,'기준가격대장(결산후)'!$A$4:$H$500,6,0),0) -> 0 | H9: =IFERROR(VLOOKUP(E9,'기준가격대장(결산후)'!$A$4:$H$500,7,0),0) -> 0 | I9: =IFERROR(VLOOKUP(E9,'기준가격대장(결산후)'!$A$4:$H$500,8,0),0) -> 0
B10: =IFERROR(VLOOKUP(E10,'기준가격대장(결산후)'!$A$4:$H$500,2,0),0) -> 0 | C10: =IFERROR(VLOOKUP(E10,'기준가격대장(결산후)'!$A$4:$H$500,3,0),0) -> 0 | D10: =IFERROR(VLOOKUP(E10,'기준가격대장(결산후)'!$A$4:$H$500,4,0),0) -> 0 | E10: 105010 | F10: CP/전단채 | G10: =IFERROR(VLOOKUP(E10,'기준가격대장(결산후)'!$A$4:$H$500,6,0),0) -> 0 | H10: =IFERROR(VLOOKUP(E10,'기준가격대장(결산후)'!$A$4:$H$500,7,0),0) -> 0 | I10: =IFERROR(VLOOKUP(E10,'기준가격대장(결산후)'!$A$4:$H$500,8,0),0) -> 0 | K10: VLOOKUP 참조 절대값 잘걸기
B11: =IFERROR(VLOOKUP(E11,'기준가격대장(결산후)'!$A$4:$H$500,2,0),0) -> 0 | C11: =IFERROR(VLOOKUP(E11,'기준가격대장(결산후)'!$A$4:$H$500,3,0),0) -> 0 | D11: =IFERROR(VLOOKUP(E11,'기준가격대장(결산후)'!$A$4:$H$500,4,0),0) -> 0 | E11: 107010 | F11: CD | G11: =IFERROR(VLOOKUP(E11,'기준가격대장(결산후)'!$A$4:$H$500,6,0),0) -> 0 | H11: =IFERROR(VLOOKUP(E11,'기준가격대장(결산후)'!$A$4:$H$500,7,0),0) -> 0 | I11: =IFERROR(VLOOKUP(E11,'기준가격대장(결산후)'!$A$4:$H$500,8,0),0) -> 0
B12: =IFERROR(VLOOKUP(E12,'기준가격대장(결산후)'!$A$4:$H$500,2,0),0) -> 0 | C12: =IFERROR(VLOOKUP(E12,'기준가격대장(결산후)'!$A$4:$H$500,3,0),0) -> 0 | D12: =IFERROR(VLOOKUP(E12,'기준가격대장(결산후)'!$A$4:$H$500,4,0),0) -> 0 | E12: 107030 | F12: 정기예금 | G12: =IFERROR(VLOOKUP(E12,'기준가격대장(결산후)'!$A$4:$H$500,6,0),0) -> 0 | H12: =IFERROR(VLOOKUP(E12,'기준가격대장(결산후)'!$A$4:$H$500,7,0),0) -> 0 | I12: =IFERROR(VLOOKUP(E12,'기준가격대장(결산후)'!$A$4:$H$500,8,0),0) -> 0
B13: =IFERROR(VLOOKUP(E13,'기준가격대장(결산후)'!$A$4:$H$500,2,0),0) -> 0 | C13: =IFERROR(VLOOKUP(E13,'기준가격대장(결산후)'!$A$4:$H$500,3,0),0) -> 0 | D13: =IFERROR(VLOOKUP(E13,'기준가격대장(결산후)'!$A$4:$H$500,4,0),0) -> 0 | E13: 109030 | F13: REPO | G13: =IFERROR(VLOOKUP(E13,'기준가격대장(결산후)'!$A$4:$H$500,6,0),0) -> 0 | H13: =IFERROR(VLOOKUP(E13,'기준가격대장(결산후)'!$A$4:$H$500,7,0),0) -> 0 | I13: =IFERROR(VLOOKUP(E13,'기준가격대장(결산후)'!$A$4:$H$500,8,0),0) -> 0
B14: =IFERROR(VLOOKUP(E14,'기준가격대장(결산후)'!$A$4:$H$500,2,0),0) -> 106485058475 | C14: =IFERROR(VLOOKUP(E14,'기준가격대장(결산후)'!$A$4:$H$500,3,0),0) -> 33658782896 | D14: =IFERROR(VLOOKUP(E14,'기준가격대장(결산후)'!$A$4:$H$500,4,0),0) -> 73217869377 | E14: 111010 | F14: 상장주식 | G14: =IFERROR(VLOOKUP(E14,'기준가격대장(결산후)'!$A$4:$H$500,6,0),0) -> 0 | H14: =IFERROR(VLOOKUP(E14,'기준가격대장(결산후)'!$A$4:$H$500,7,0),0) -> 391593798 | I14: =IFERROR(VLOOKUP(E14,'기준가격대장(결산후)'!$A$4:$H$500,8,0),0) -> 0
B15: =IFERROR(VLOOKUP(E15,'기준가격대장(결산후)'!$A$4:$H$500,2,0),0) -> 0 | C15: =IFERROR(VLOOKUP(E15,'기준가격대장(결산후)'!$A$4:$H$500,3,0),0) -> 0 | D15: =IFERROR(VLOOKUP(E15,'기준가격대장(결산후)'!$A$4:$H$500,4,0),0) -> 0 | E15: 111030 | F15: 코스닥주식 | G15: =IFERROR(VLOOKUP(E15,'기준가격대장(결산후)'!$A$4:$H$500,6,0),0) -> 0 | H15: =IFERROR(VLOOKUP(E15,'기준가격대장(결산후)'!$A$4:$H$500,7,0),0) -> 0 | I15: =IFERROR(VLOOKUP(E15,'기준가격대장(결산후)'!$A$4:$H$500,8,0),0) -> 0
B16: =IFERROR(VLOOKUP(E16,'기준가격대장(결산후)'!$A$4:$H$500,2,0),0) -> 0 | C16: =IFERROR(VLOOKUP(E16,'기준가격대장(결산후)'!$A$4:$H$500,3,0),0) -> 0 | D16: =IFERROR(VLOOKUP(E16,'기준가격대장(결산후)'!$A$4:$H$500,4,0),0) -> 0 | E16: 111040 | F16: 코넥스주식 | G16: =IFERROR(VLOOKUP(E16,'기준가격대장(결산후)'!$A$4:$H$500,6,0),0) -> 0 | H16: =IFERROR(VLOOKUP(E16,'기준가격대장(결산후)'!$A$4:$H$500,7,0),0) -> 0 | I16: =IFERROR(VLOOKUP(E16,'기준가격대장(결산후)'!$A$4:$H$500,8,0),0) -> 0
B17: =IFERROR(VLOOKUP(E17,'기준가격대장(결산후)'!$A$4:$H$500,2,0),0) -> 0 | C17: =IFERROR(VLOOKUP(E17,'기준가격대장(결산후)'!$A$4:$H$500,3,0),0) -> 0 | D17: =IFERROR(VLOOKUP(E17,'기준가격대장(결산후)'!$A$4:$H$500,4,0),0) -> 0 | E17: 111110 | F17: 외화주식 | G17: =IFERROR(VLOOKUP(E17,'기준가격대장(결산후)'!$A$4:$H$500,6,0),0) -> 0 | H17: =IFERROR(VLOOKUP(E17,'기준가격대장(결산후)'!$A$4:$H$500,7,0),0) -> 0 | I17: =IFERROR(VLOOKUP(E17,'기준가격대장(결산후)'!$A$4:$H$500,8,0),0) -> 0
B18: =IFERROR(VLOOKUP(E18,'기준가격대장(결산후)'!$A$4:$H$500,2,0),0) -> 5368673944 | C18: =IFERROR(VLOOKUP(E18,'기준가격대장(결산후)'!$A$4:$H$500,3,0),0) -> 1765255 | D18: =IFERROR(VLOOKUP(E18,'기준가격대장(결산후)'!$A$4:$H$500,4,0),0) -> 5366908689 | E18: 113010 | F18: 국채 | G18: =IFERROR(VLOOKUP(E18,'기준가격대장(결산후)'!$A$4:$H$500,6,0),0) -> 0 | H18: =IFERROR(VLOOKUP(E18,'기준가격대장(결산후)'!$A$4:$H$500,7,0),0) -> 0 | I18: =IFERROR(VLOOKUP(E18,'기준가격대장(결산후)'!$A$4:$H$500,8,0),0) -> 0
B19: =IFERROR(VLOOKUP(E19,'기준가격대장(결산후)'!$A$4:$H$500,2,0),0) -> 0 | C19: =IFERROR(VLOOKUP(E19,'기준가격대장(결산후)'!$A$4:$H$500,3,0),0) -> 0 | D19: =IFERROR(VLOOKUP(E19,'기준가격대장(결산후)'!$A$4:$H$500,4,0),0) -> 0 | E19: 113030 | F19: 지방채 | G19: =IFERROR(VLOOKUP(E19,'기준가격대장(결산후)'!$A$4:$H$500,6,0),0) -> 0 | H19: =IFERROR(VLOOKUP(E19,'기준가격대장(결산후)'!$A$4:$H$500,7,0),0) -> 0 | I19: =IFERROR(VLOOKUP(E19,'기준가격대장(결산후)'!$A$4:$H$500,8,0),0) -> 0
B20: =IFERROR(VLOOKUP(E20,'기준가격대장(결산후)'!$A$4:$H$500,2,0),0) -> 0 | C20: =IFERROR(VLOOKUP(E20,'기준가격대장(결산후)'!$A$4:$H$500,3,0),0) -> 0 | D20: =IFERROR(VLOOKUP(E20,'기준가격대장(결산후)'!$A$4:$H$500,4,0),0) -> 0 | E20: 113050 | F20: 특수채 | G20: =IFERROR(VLOOKUP(E20,'기준가격대장(결산후)'!$A$4:$H$500,6,0),0) -> 0 | H20: =IFERROR(VLOOKUP(E20,'기준가격대장(결산후)'!$A$4:$H$500,7,0),0) -> 0 | I20: =IFERROR(VLOOKUP(E20,'기준가격대장(결산후)'!$A$4:$H$500,8,0),0) -> 0
B21: =IFERROR(VLOOKUP(E21,'기준가격대장(결산후)'!$A$4:$H$500,2,0),0) -> 0 | C21: =IFERROR(VLOOKUP(E21,'기준가격대장(결산후)'!$A$4:$H$500,3,0),0) -> 0 | D21: =IFERROR(VLOOKUP(E21,'기준가격대장(결산후)'!$A$4:$H$500,4,0),0) -> 0 | E21: 113070 | F21: 통안채 | G21: =IFERROR(VLOOKUP(E21,'기준가격대장(결산후)'!$A$4:$H$500,6,0),0) -> 0 | H21: =IFERROR(VLOOKUP(E21,'기준가격대장(결산후)'!$A$4:$H$500,7,0),0) -> 0 | I21: =IFERROR(VLOOKUP(E21,'기준가격대장(결산후)'!$A$4:$H$500,8,0),0) -> 0
B22: =IFERROR(VLOOKUP(E22,'기준가격대장(결산후)'!$A$4:$H$500,2,0),0) -> 0 | C22: =IFERROR(VLOOKUP(E22,'기준가격대장(결산후)'!$A$4:$H$500,3,0),0) -> 0 | D22: =IFERROR(VLOOKUP(E22,'기준가격대장(결산후)'!$A$4:$H$500,4,0),0) -> 0 | E22: 113090 | F22: 금융채 | G22: =IFERROR(VLOOKUP(E22,'기준가격대장(결산후)'!$A$4:$H$500,6,0),0) -> 0 | H22: =IFERROR(VLOOKUP(E22,'기준가격대장(결산후)'!$A$4:$H$500,7,0),0) -> 0 | I22: =IFERROR(VLOOKUP(E22,'기준가격대장(결산후)'!$A$4:$H$500,8,0),0) -> 0
... B43: =IFERROR(VLOOKUP(E43,'기준가격대장(결산후)'!$A$4:$H$500,2,0),0) -> 584987500 | C43: =IFERROR(VLOOKUP(E43,'기준가격대장(결산후)'!$A$4:$H$500,3,0),0) -> 0 | D43: =IFERROR(VLOOKUP(E43,'기준가격대장(결산후)'!$A$4:$H$500,4,0),0) -> 584987500 | E43: 139410 | F43: 선물미수입금 | G43: =IFERROR(VLOOKUP(E43,'기준가격대장(결산후)'!$A$4:$H$500,6,0),0) -> 0 | H43: =IFERROR(VLOOKUP(E43,'기준가격대장(결산후)'!$A$4:$H$500,7,0),0) -> 0 | I43: =IFERROR(VLOOKUP(E43,'기준가격대장(결산후)'!$A$4:$H$500,8,0),0) -> 0
B44: =IFERROR(VLOOKUP(E44,'기준가격대장(결산후)'!$A$4:$H$500,2,0),0) -> 0 | C44: =IFERROR(VLOOKUP(E44,'기준가격대장(결산후)'!$A$4:$H$500,3,0),0) -> 0 | D44: =IFERROR(VLOOKUP(E44,'기준가격대장(결산후)'!$A$4:$H$500,4,0),0) -> 0 | E44: 139420 | F44: 옵션미수입금 | G44: =IFERROR(VLOOKUP(E44,'기준가격대장(결산후)'!$A$4:$H$500,6,0),0) -> 0 | H44: =IFERROR(VLOOKUP(E44,'기준가격대장(결산후)'!$A$4:$H$500,7,0),0) -> 0 | I44: =IFERROR(VLOOKUP(E44,'기준가격대장(결산후)'!$A$4:$H$500,8,0),0) -> 0 | J44: 추가
B45: =IFERROR(VLOOKUP(E45,'기준가격대장(결산후)'!$A$4:$H$500,2,0),0) -> 0 | C45: =IFERROR(VLOOKUP(E45,'기준가격대장(결산후)'!$A$4:$H$500,3,0),0) -> 0 | D45: =IFERROR(VLOOKUP(E45,'기준가격대장(결산후)'!$A$4:$H$500,4,0),0) -> 0 | E45: 139450 | F45: 국채선물미수입금 | G45: =IFERROR(VLOOKUP(E45,'기준가격대장(결산후)'!$A$4:$H$500,6,0),0) -> 0 | H45: =IFERROR(VLOOKUP(E45,'기준가격대장(결산후)'!$A$4:$H$500,7,0),0) -> 0 | I45: =IFERROR(VLOOKUP(E45,'기준가격대장(결산후)'!$A$4:$H$500,8,0),0) -> 0
B46: =IFERROR(VLOOKUP(E46,'기준가격대장(결산후)'!$A$4:$H$500,2,0),0) -> 0 | C46: =IFERROR(VLOOKUP(E46,'기준가격대장(결산후)'!$A$4:$H$500,3,0),0) -> 0 | D46: =IFERROR(VLOOKUP(E46,'기준가격대장(결산후)'!$A$4:$H$500,4,0),0) -> 0 | E46: 139510 | F46: 달러선물미수입금 | G46: =IFERROR(VLOOKUP(E46,'기준가격대장(결산후)'!$A$4:$H$500,6,0),0) -> 0 | H46: =IFERROR(VLOOKUP(E46,'기준가격대장(결산후)'!$A$4:$H$500,7,0),0) -> 0 | I46: =IFERROR(VLOOKUP(E46,'기준가격대장(결산후)'!$A$4:$H$500,8,0),0) -> 0
B47: =IFERROR(VLOOKUP(E47,'기준가격대장(결산후)'!$A$4:$H$500,2,0),0) -> 455343 | C47: =IFERROR(VLOOKUP(E47,'기준가격대장(결산후)'!$A$4:$H$500,3,0),0) -> 0 | D47: =IFERROR(VLOOKUP(E47,'기준가격대장(결산후)'!$A$4:$H$500,4,0),0) -> 455343 | E47: 139810 | F47: 대차거래미수입금 | G47: =IFERROR(VLOOKUP(E47,'기준가격대장(결산후)'!$A$4:$H$500,6,0),0) -> 0 | H47: =IFERROR(VLOOKUP(E47,'기준가격대장(결산후)'!$A$4:$H$500,7,0),0) -> 0 | I47: =IFERROR(VLOOKUP(E47,'기준가격대장(결산후)'!$A$4:$H$500,8,0),0) -> 0
B48: =IFERROR(VLOOKUP(E48,'기준가격대장(결산후)'!$A$4:$H$500,2,0),0) -> 0 | C48: =IFERROR(VLOOKUP(E48,'기준가격대장(결산후)'!$A$4:$H$500,3,0),0) -> 0 | D48: =IFERROR(VLOOKUP(E48,'기준가격대장(결산후)'!$A$4:$H$500,4,0),0) -> 0 | E48: 139811 | F48: 대차거래미수입금(외화) | G48: =IFERROR(VLOOKUP(E48,'기준가격대장(결산후)'!$A$4:$H$500,6,0),0) -> 0 | H48: =IFERROR(VLOOKUP(E48,'기준가격대장(결산후)'!$A$4:$H$500,7,0),0) -> 0 | I48: =IFERROR(VLOOKUP(E48,'기준가격대장(결산후)'!$A$4:$H$500,8,0),0) -> 0
B49: =IFERROR(VLOOKUP(E49,'기준가격대장(결산후)'!$A$4:$H$500,2,0),0) -> 0 | C49: =IFERROR(VLOOKUP(E49,'기준가격대장(결산후)'!$A$4:$H$500,3,0),0) -> 0 | D49: =IFERROR(VLOOKUP(E49,'기준가격대장(결산후)'!$A$4:$H$500,4,0),0) -> 0 | E49: 139890 | F49: 기타미수입금 | G49: =IFERROR(VLOOKUP(E49,'기준가격대장(결산후)'!$A$4:$H$500,6,0),0) -> 0 | H49: =IFERROR(VLOOKUP(E49,'기준가격대장(결산후)'!$A$4:$H$500,7,0),0) -> 0 | I49: =IFERROR(VLOOKUP(E49,'기준가격대장(결산후)'!$A$4:$H$500,8,0),0) -> 0
B50: =IFERROR(VLOOKUP(E50,'기준가격대장(결산후)'!$A$4:$H$500,2,0),0) -> 221852625 | C50: =IFERROR(VLOOKUP(E50,'기준가격대장(결산후)'!$A$4:$H$500,3,0),0) -> 0 | D50: =IFERROR(VLOOKUP(E50,'기준가격대장(결산후)'!$A$4:$H$500,4,0),0) -> 221852625 | E50: 147010 | F50: 주식미수배당금 | G50: =IFERROR(VLOOKUP(E50,'기준가격대장(결산후)'!$A$4:$H$500,6,0),0) -> 0 | H50: =IFERROR(VLOOKUP(E50,'기준가격대장(결산후)'!$A$4:$H$500,7,0),0) -> 0 | I50: =IFERROR(VLOOKUP(E50,'기준가격대장(결산후)'!$A$4:$H$500,8,0),0) -> 0
B51: =IFERROR(VLOOKUP(E51,'기준가격대장(결산후)'!$A$4:$H$500,2,0),0) -> 0 | C51: =IFERROR(VLOOKUP(E51,'기준가격대장(결산후)'!$A$4:$H$500,3,0),0) -> 0 | D51: =IFERROR(VLOOKUP(E51,'기준가격대장(결산후)'!$A$4:$H$500,4,0),0) -> 0 | E51: 147030 | F51: 외화주식미수배당금 | G51: =IFERROR(VLOOKUP(E51,'기준가격대장(결산후)'!$A$4:$H$500,6,0),0) -> 0 | H51: =IFERROR(VLOOKUP(E51,'기준가격대장(결산후)'!$A$4:$H$500,7,0),0) -> 0 | I51: =IFERROR(VLOOKUP(E51,'기준가격대장(결산후)'!$A$4:$H$500,8,0),0) -> 0
B52: =IFERROR(VLOOKUP(E52,'기준가격대장(결산후)'!$A$4:$H$500,2,0),0) -> 0 | C52: =IFERROR(VLOOKUP(E52,'기준가격대장(결산후)'!$A$4:$H$500,3,0),0) -> 0 | D52: =IFERROR(VLOOKUP(E52,'기준가격대장(결산후)'!$A$4:$H$500,4,0),0) -> 0 | E52: 147050 | F52: 상장펀드미수배당금 | G52: =IFERROR(VLOOKUP(E52,'기준가격대장(결산후)'!$A$4:$H$500,6,0),0) -> 0 | H52: =IFERROR(VLOOKUP(E52,'기준가격대장(결산후)'!$A$4:$H$500,7,0),0) -> 0 | I52: =IFERROR(VLOOKUP(E52,'기준가격대장(결산후)'!$A$4:$H$500,8,0),0) -> 0
B53: =IFERROR(VLOOKUP(E53,'기준가격대장(결산후)'!$A$4:$H$500,2,0),0) -> 0 | C53: =IFERROR(VLOOKUP(E53,'기준가격대장(결산후)'!$A$4:$H$500,3,0),0) -> 0 | D53: =IFERROR(VLOOKUP(E53,'기준가격대장(결산후)'!$A$4:$H$500,4,0),0) -> 0 | E53: 147070 | F53: 수익증권미수배당금 | G53: =IFERROR(VLOOKUP(E53,'기준가격대장(결산후)'!$A$4:$H$500,6,0),0) -> 0 | H53: =IFERROR(VLOOKUP(E53,'기준가격대장(결산후)'!$A$4:$H$500,7,0),0) -> 0 | I53: =IFERROR(VLOOKUP(E53,'기준가격대장(결산후)'!$A$4:$H$500,8,0),0) -> 0
B54: =IFERROR(VLOOKUP(E54,'기준가격대장(결산후)'!$A$4:$H$500,2,0),0) -> 661948 | C54: =IFERROR(VLOOKUP(E54,'기준가격대장(결산후)'!$A$4:$H$500,3,0),0) -> 0 | D54: =IFERROR(VLOOKUP(E54,'기준가격대장(결산후)'!$A$4:$H$500,4,0),0) -> 661948 | E54: 149010 | F54: 채권미수이자 | G54: =IFERROR(VLOOKUP(E54,'기준가격대장(결산후)'!$A$4:$H$500,6,0),0) -> 0 | H54: =IFERROR(VLOOKUP(E54,'기준가격대장(결산후)'!$A$4:$H$500,7,0),0) -> 0 | I54: =IFERROR(VLOOKUP(E54,'기준가격대장(결산후)'!$A$4:$H$500,8,0),0) -> 0
B55: =IFERROR(VLOOKUP(E55,'기준가격대장(결산후)'!$A$4:$H$500,2,0),0) -> 0 | C55: =IFERROR(VLOOKUP(E55,'기준가격대장(결산후)'!$A$4:$H$500,3,0),0) -> 0 | D55: =IFERROR(VLOOKUP(E55,'기준가격대장(결산후)'!$A$4:$H$500,4,0),0) -> 0 | E55: 149030 | F55: 외화채권미수이자 | G55: =IFERROR(VLOOKUP(E55,'기준가격대장(결산후)'!$A$4:$H$500,6,0),0) -> 0 | H55: =IFERROR(VLOOKUP(E55,'기준가격대장(결산후)'!$A$4:$H$500,7,0),0) -> 0 | I55: =IFERROR(VLOOKUP(E55,'기준가격대장(결산후)'!$A$4:$H$500,8,0),0) -> 0
B56: =IFERROR(VLOOKUP(E56,'기준가격대장(결산후)'!$A$4:$H$500,2,0),0) -> 6231172 | C56: =IFERROR(VLOOKUP(E56,'기준가격대장(결산후)'!$A$4:$H$500,3,0),0) -> 0 | D56: =IFERROR(VLOOKUP(E56,'기준가격대장(결산후)'!$A$4:$H$500,4,0),0) -> 6231172 | E56: 149110 | F56: 예금미수이자 | G56: =IFERROR(VLOOKUP(E56,'기준가격대장(결산후)'!$A$4:$H$500,6,0),0) -> 0 | H56: =IFERROR(VLOOKUP(E56,'기준가격대장(결산후)'!$A$4:$H$500,7,0),0) -> 0 | I56: =IFERROR(VLOOKUP(E56,'기준가격대장(결산후)'!$A$4:$H$500,8,0),0) -> 0
... B91: =IFERROR(VLOOKUP(E91,'기준가격대장(결산후)'!$A$4:$H$500,2,0),0) -> 0 | C91: =IFERROR(VLOOKUP(E91,'기준가격대장(결산후)'!$A$4:$H$500,3,0),0) -> 0 | D91: =IFERROR(VLOOKUP(E91,'기준가격대장(결산후)'!$A$4:$H$500,4,0),0) -> 0 | E91: 183611 | F91: 선물평가손익조정(해외-전기) | G91: =IFERROR(VLOOKUP(E91,'기준가격대장(결산후)'!$A$4:$H$500,6,0),0) -> 0 | H91: =IFERROR(VLOOKUP(E91,'기준가격대장(결산후)'!$A$4:$H$500,7,0),0) -> 0 | I91: =IFERROR(VLOOKUP(E91,'기준가격대장(결산후)'!$A$4:$H$500,8,0),0) -> 0
B92: =IFERROR(VLOOKUP(E92,'기준가격대장(결산후)'!$A$4:$H$500,2,0),0) -> 0 | C92: =IFERROR(VLOOKUP(E92,'기준가격대장(결산후)'!$A$4:$H$500,3,0),0) -> 0 | D92: =IFERROR(VLOOKUP(E92,'기준가격대장(결산후)'!$A$4:$H$500,4,0),0) -> 0 | E92: 200000 | F92: 부채합계 | G92: =IFERROR(VLOOKUP(E92,'기준가격대장(결산후)'!$A$4:$H$500,6,0),0) -> 15818638807 | H92: =IFERROR(VLOOKUP(E92,'기준가격대장(결산후)'!$A$4:$H$500,7,0),0) -> 1765257 | I92: =IFERROR(VLOOKUP(E92,'기준가격대장(결산후)'!$A$4:$H$500,8,0),0) -> 15820404064 | K92: 부채검증 | L92: =SUM(I93:I146)=I92 -> TRUE | M92: =SUM(I93:I146)-I92 -> 0
B93: =IFERROR(VLOOKUP(E93,'기준가격대장(결산후)'!$A$4:$H$500,2,0),0) -> 0 | C93: =IFERROR(VLOOKUP(E93,'기준가격대장(결산후)'!$A$4:$H$500,3,0),0) -> 0 | D93: =IFERROR(VLOOKUP(E93,'기준가격대장(결산후)'!$A$4:$H$500,4,0),0) -> 0 | E93: 201050 | F93: 매도REPO | G93: =IFERROR(VLOOKUP(E93,'기준가격대장(결산후)'!$A$4:$H$500,6,0),0) -> 5000000000 | H93: =IFERROR(VLOOKUP(E93,'기준가격대장(결산후)'!$A$4:$H$500,7,0),0) -> 0 | I93: =IFERROR(VLOOKUP(E93,'기준가격대장(결산후)'!$A$4:$H$500,8,0),0) -> 5000000000
B94: =IFERROR(VLOOKUP(E94,'기준가격대장(결산후)'!$A$4:$H$500,2,0),0) -> 0 | C94: =IFERROR(VLOOKUP(E94,'기준가격대장(결산후)'!$A$4:$H$500,3,0),0) -> 0 | D94: =IFERROR(VLOOKUP(E94,'기준가격대장(결산후)'!$A$4:$H$500,4,0),0) -> 0 | E94: 211010 | F94: 미지급상장주식 | G94: =IFERROR(VLOOKUP(E94,'기준가격대장(결산후)'!$A$4:$H$500,6,0),0) -> 0 | H94: =IFERROR(VLOOKUP(E94,'기준가격대장(결산후)'!$A$4:$H$500,7,0),0) -> 0 | I94: =IFERROR(VLOOKUP(E94,'기준가격대장(결산후)'!$A$4:$H$500,8,0),0) -> 0
B95: =IFERROR(VLOOKUP(E95,'기준가격대장(결산후)'!$A$4:$H$500,2,0),0) -> 0 | C95: =IFERROR(VLOOKUP(E95,'기준가격대장(결산후)'!$A$4:$H$500,3,0),0) -> 0 | D95: =IFERROR(VLOOKUP(E95,'기준가격대장(결산후)'!$A$4:$H$500,4,0),0) -> 0 | E95: 213150 | F95: 미지급외화채권 | G95: =IFERROR(VLOOKUP(E95,'기준가격대장(결산후)'!$A$4:$H$500,6,0),0) -> 0 | H95: =IFERROR(VLOOKUP(E95,'기준가격대장(결산후)'!$A$4:$H$500,7,0),0) -> 0 | I95: =IFERROR(VLOOKUP(E95,'기준가격대장(결산후)'!$A$4:$H$500,8,0),0) -> 0
B96: =IFERROR(VLOOKUP(E96,'기준가격대장(결산후)'!$A$4:$H$500,2,0),0) -> 0 | C96: =IFERROR(VLOOKUP(E96,'기준가격대장(결산후)'!$A$4:$H$500,3,0),0) -> 0 | D96: =IFERROR(VLOOKUP(E96,'기준가격대장(결산후)'!$A$4:$H$500,4,0),0) -> 0 | E96: 213170 | F96: 미지급채권 | G96: =IFERROR(VLOOKUP(E96,'기준가격대장(결산후)'!$A$4:$H$500,6,0),0) -> 5366908687 | H96: =IFERROR(VLOOKUP(E96,'기준가격대장(결산후)'!$A$4:$H$500,7,0),0) -> 1765257 | I96: =IFERROR(VLOOKUP(E96,'기준가격대장(결산후)'!$A$4:$H$500,8,0),0) -> 5368673944
B97: =IFERROR(VLOOKUP(E97,'기준가격대장(결산후)'!$A$4:$H$500,2,0),0) -> 0 | C97: =IFERROR(VLOOKUP(E97,'기준가격대장(결산후)'!$A$4:$H$500,3,0),0) -> 0 | D97: =IFERROR(VLOOKUP(E97,'기준가격대장(결산후)'!$A$4:$H$500,4,0),0) -> 0 | E97: 215030 | F97: 미지급상장펀드증권 | G97: =IFERROR(VLOOKUP(E97,'기준가격대장(결산후)'!$A$4:$H$500,6,0),0) -> 0 | H97: =IFERROR(VLOOKUP(E97,'기준가격대장(결산후)'!$A$4:$H$500,7,0),0) -> 0 | I97: =IFERROR(VLOOKUP(E97,'기준가격대장(결산후)'!$A$4:$H$500,8,0),0) -> 0
B98: =IFERROR(VLOOKUP(E98,'기준가격대장(결산후)'!$A$4:$H$500,2,0),0) -> 0 | C98: =IFERROR(VLOOKUP(E98,'기준가격대장(결산후)'!$A$4:$H$500,3,0),0) -> 0 | D98: =IFERROR(VLOOKUP(E98,'기준가격대장(결산후)'!$A$4:$H$500,4,0),0) -> 0 | E98: 227010 | F98: 주식옵션매도 | G98: =IFERROR(VLOOKUP(E98,'기준가격대장(결산후)'!$A$4:$H$500,6,0),0) -> 0 | H98: =IFERROR(VLOOKUP(E98,'기준가격대장(결산후)'!$A$4:$H$500,7,0),0) -> 0 | I98: =IFERROR(VLOOKUP(E98,'기준가격대장(결산후)'!$A$4:$H$500,8,0),0) -> 0
B99: =IFERROR(VLOOKUP(E99,'기준가격대장(결산후)'!$A$4:$H$500,2,0),0) -> 0 | C99: =IFERROR(VLOOKUP(E99,'기준가격대장(결산후)'!$A$4:$H$500,3,0),0) -> 0 | D99: =IFERROR(VLOOKUP(E99,'기준가격대장(결산후)'!$A$4:$H$500,4,0),0) -> 0 | E99: 239010 | F99: 주식미지급금 | G99: =IFERROR(VLOOKUP(E99,'기준가격대장(결산후)'!$A$4:$H$500,6,0),0) -> 0 | H99: =IFERROR(VLOOKUP(E99,'기준가격대장(결산후)'!$A$4:$H$500,7,0),0) -> 0 | I99: =IFERROR(VLOOKUP(E99,'기준가격대장(결산후)'!$A$4:$H$500,8,0),0) -> 0
B100: =IFERROR(VLOOKUP(E100,'기준가격대장(결산후)'!$A$4:$H$500,2,0),0) -> 0 | C100: =IFERROR(VLOOKUP(E100,'기준가격대장(결산후)'!$A$4:$H$500,3,0),0) -> 0 | D100: =IFERROR(VLOOKUP(E100,'기준가격대장(결산후)'!$A$4:$H$500,4,0),0) -> 0 | E100: 239030 | F100: 외화주식미지급금 | G100: =IFERROR(VLOOKUP(E100,'기준가격대장(결산후)'!$A$4:$H$500,6,0),0) -> 0 | H100: =IFERROR(VLOOKUP(E100,'기준가격대장(결산후)'!$A$4:$H$500,7,0),0) -> 0 | I100: =IFERROR(VLOOKUP(E100,'기준가격대장(결산후)'!$A$4:$H$500,8,0),0) -> 0
B101: =IFERROR(VLOOKUP(E101,'기준가격대장(결산후)'!$A$4:$H$500,2,0),0) -> 0 | C101: =IFERROR(VLOOKUP(E101,'기준가격대장(결산후)'!$A$4:$H$500,3,0),0) -> 0 | D101: =IFERROR(VLOOKUP(E101,'기준가격대장(결산후)'!$A$4:$H$500,4,0),0) -> 0 | E101: 239110 | F101: 채권미지급금 | G101: =IFERROR(VLOOKUP(E101,'기준가격대장(결산후)'!$A$4:$H$500,6,0),0) -> 0 | H101: =IFERROR(VLOOKUP(E101,'기준가격대장(결산후)'!$A$4:$H$500,7,0),0) -> 0 | I101: =IFERROR(VLOOKUP(E101,'기준가격대장(결산후)'!$A$4:$H$500,8,0),0) -> 0
B102: =IFERROR(VLOOKUP(E102,'기준가격대장(결산후)'!$A$4:$H$500,2,0),0) -> 0 | C102: =IFERROR(VLOOKUP(E102,'기준가격대장(결산후)'!$A$4:$H$500,3,0),0) -> 0 | D102: =IFERROR(VLOOKUP(E102,'기준가격대장(결산후)'!$A$4:$H$500,4,0),0) -> 0 | E102: 239150 | F102: 외화채권미지급금 | G102: =IFERROR(VLOOKUP(E102,'기준가격대장(결산후)'!$A$4:$H$500,6,0),0) -> 0 | H102: =IFERROR(VLOOKUP(E102,'기준가격대장(결산후)'!$A$4:$H$500,7,0),0) -> 0 | I102: =IFERROR(VLOOKUP(E102,'기준가격대장(결산후)'!$A$4:$H$500,8,0),0) -> 0
B103: =IFERROR(VLOOKUP(E103,'기준가격대장(결산후)'!$A$4:$H$500,2,0),0) -> 0 | C103: =IFERROR(VLOOKUP(E103,'기준가격대장(결산후)'!$A$4:$H$500,3,0),0) -> 0 | D103: =IFERROR(VLOOKUP(E103,'기준가격대장(결산후)'!$A$4:$H$500,4,0),0) -> 0 | E103: 239210 | F103: 유동미지급금 | G103: =IFERROR(VLOOKUP(E103,'기준가격대장(결산후)'!$A$4:$H$500,6,0),0) -> 0 | H103: =IFERROR(VLOOKUP(E103,'기준가격대장(결산후)'!$A$4:$H$500,7,0),0) -> 0 | I103: =IFERROR(VLOOKUP(E103,'기준가격대장(결산후)'!$A$4:$H$500,8,0),0) -> 0
B104: =IFERROR(VLOOKUP(E104,'기준가격대장(결산후)'!$A$4:$H$500,2,0),0) -> 0 | C104: =IFERROR(VLOOKUP(E104,'기준가격대장(결산후)'!$A$4:$H$500,3,0),0) -> 0 | D104: =IFERROR(VLOOKUP(E104,'기준가격대장(결산후)'!$A$4:$H$500,4,0),0) -> 0 | E104: 239230 | F104: 외화유동미지급금 | G104: =IFERROR(VLOOKUP(E104,'기준가격대장(결산후)'!$A$4:$H$500,6,0),0) -> 0 | H104: =IFERROR(VLOOKUP(E104,'기준가격대장(결산후)'!$A$4:$H$500,7,0),0) -> 0 | I104: =IFERROR(VLOOKUP(E104,'기준가격대장(결산후)'!$A$4:$H$500,8,0),0) -> 0
... B106: =IFERROR(VLOOKUP(E106,'기준가격대장(결산후)'!$A$4:$H$500,2,0),0) -> 0 | C106: =IFERROR(VLOOKUP(E106,'기준가격대장(결산후)'!$A$4:$H$500,3,0),0) -> 0 | D106: =IFERROR(VLOOKUP(E106,'기준가격대장(결산후)'!$A$4:$H$500,4,0),0) -> 0 | E106: 239410 | F106: 선물미지급금 | G106: =IFERROR(VLOOKUP(E106,'기준가격대장(결산후)'!$A$4:$H$500,6,0),0) -> 0 | H106: =IFERROR(VLOOKUP(E106,'기준가격대장(결산후)'!$A$4:$H$500,7,0),0) -> 0 | I106: =IFERROR(VLOOKUP(E106,'기준가격대장(결산후)'!$A$4:$H$500,8,0),0) -> 0
B107: =IFERROR(VLOOKUP(#REF!,'기준가격대장(결산후)'!$A$4:$H$500,6,0),0) -> 0 | C107: =IFERROR(VLOOKUP(#REF!,'기준가격대장(결산후)'!$A$4:$H$500,7,0),0) -> 0 | D107: =IFERROR(VLOOKUP(#REF!,'기준가격대장(결산후)'!$A$4:$H$500,8,0),0) -> 0 | E107: 239420 | F107: 옵션미지급금 | G107: =IFERROR(VLOOKUP(E107,'기준가격대장(결산후)'!$A$4:$H$500,6,0),0) -> 0 | H107: =IFERROR(VLOOKUP(E107,'기준가격대장(결산후)'!$A$4:$H$500,7,0),0) -> 0 | I107: =IFERROR(VLOOKUP(E107,'기준가격대장(결산후)'!$A$4:$H$500,8,0),0) -> 0
B108: =IFERROR(VLOOKUP(E108,'기준가격대장(결산후)'!$A$4:$H$500,2,0),0) -> 0 | C108: =IFERROR(VLOOKUP(E108,'기준가격대장(결산후)'!$A$4:$H$500,3,0),0) -> 0 | D108: =IFERROR(VLOOKUP(E108,'기준가격대장(결산후)'!$A$4:$H$500,4,0),0) -> 0 | E108: 239450 | F108: 국채선물미지급금 | G108: =IFERROR(VLOOKUP(E108,'기준가격대장(결산후)'!$A$4:$H$500,6,0),0) -> 0 | H108: =IFERROR(VLOOKUP(E108,'기준가격대장(결산후)'!$A$4:$H$500,7,0),0) -> 0 | I108: =IFERROR(VLOOKUP(E108,'기준가격대장(결산후)'!$A$4:$H$500,8,0),0) -> 0
B109: =IFERROR(VLOOKUP(E109,'기준가격대장(결산후)'!$A$4:$H$500,2,0),0) -> 0 | C109: =IFERROR(VLOOKUP(E109,'기준가격대장(결산후)'!$A$4:$H$500,3,0),0) -> 0 | D109: =IFERROR(VLOOKUP(E109,'기준가격대장(결산후)'!$A$4:$H$500,4,0),0) -> 0 | E109: 239510 | F109: 달러선물미지급금 | G109: =IFERROR(VLOOKUP(E109,'기준가격대장(결산후)'!$A$4:$H$500,6,0),0) -> 0 | H109: =IFERROR(VLOOKUP(E109,'기준가격대장(결산후)'!$A$4:$H$500,7,0),0) -> 0 | I109: =IFERROR(VLOOKUP(E109,'기준가격대장(결산후)'!$A$4:$H$500,8,0),0) -> 0
B110: =IFERROR(VLOOKUP(E110,'기준가격대장(결산후)'!$A$4:$H$500,2,0),0) -> 0 | C110: =IFERROR(VLOOKUP(E110,'기준가격대장(결산후)'!$A$4:$H$500,3,0),0) -> 0 | D110: =IFERROR(VLOOKUP(E110,'기준가격대장(결산후)'!$A$4:$H$500,4,0),0) -> 0 | E110: 239540 | F110: 외화상품선물미지급금 | G110: =IFERROR(VLOOKUP(E110,'기준가격대장(결산후)'!$A$4:$H$500,6,0),0) -> 0 | H110: =IFERROR(VLOOKUP(E110,'기준가격대장(결산후)'!$A$4:$H$500,7,0),0) -> 0 | I110: =IFERROR(VLOOKUP(E110,'기준가격대장(결산후)'!$A$4:$H$500,8,0),0) -> 0
B111: =IFERROR(VLOOKUP(E111,'기준가격대장(결산후)'!$A$4:$H$500,2,0),0) -> 0 | C111: =IFERROR(VLOOKUP(E111,'기준가격대장(결산후)'!$A$4:$H$500,3,0),0) -> 0 | D111: =IFERROR(VLOOKUP(E111,'기준가격대장(결산후)'!$A$4:$H$500,4,0),0) -> 0 | E111: 239810 | F111: 대차거래미지급금 | G111: =IFERROR(VLOOKUP(E111,'기준가격대장(결산후)'!$A$4:$H$500,6,0),0) -> 26580 | H111: =IFERROR(VLOOKUP(E111,'기준가격대장(결산후)'!$A$4:$H$500,7,0),0) -> 0 | I111: =IFERROR(VLOOKUP(E111,'기준가격대장(결산후)'!$A$4:$H$500,8,0),0) -> 26580
B112: =IFERROR(VLOOKUP(E112,'기준가격대장(결산후)'!$A$4:$H$500,2,0),0) -> 0 | C112: =IFERROR(VLOOKUP(E112,'기준가격대장(결산후)'!$A$4:$H$500,3,0),0) -> 0 | D112: =IFERROR(VLOOKUP(E112,'기준가격대장(결산후)'!$A$4:$H$500,4,0),0) -> 0 | E112: 239890 | F112: 기타미지급금 | G112: =IFERROR(VLOOKUP(E112,'기준가격대장(결산후)'!$A$4:$H$500,6,0),0) -> 0 | H112: =IFERROR(VLOOKUP(E112,'기준가격대장(결산후)'!$A$4:$H$500,7,0),0) -> 0 | I112: =IFERROR(VLOOKUP(E112,'기준가격대장(결산후)'!$A$4:$H$500,8,0),0) -> 0
B113: =IFERROR(VLOOKUP(E113,'기준가격대장(결산후)'!$A$4:$H$500,2,0),0) -> 0 | C113: =IFERROR(VLOOKUP(E113,'기준가격대장(결산후)'!$A$4:$H$500,3,0),0) -> 0 | D113: =IFERROR(VLOOKUP(E113,'기준가격대장(결산후)'!$A$4:$H$500,4,0),0) -> 0 | E113: 241010 | F113: 미지급주식납입금 | G113: =IFERROR(VLOOKUP(E113,'기준가격대장(결산후)'!$A$4:$H$500,6,0),0) -> 0 | H113: =IFERROR(VLOOKUP(E113,'기준가격대장(결산후)'!$A$4:$H$500,7,0),0) -> 0 | I113: =IFERROR(VLOOKUP(E113,'기준가격대장(결산후)'!$A$4:$H$500,8,0),0) -> 0
B114: =IFERROR(VLOOKUP(E114,'기준가격대장(결산후)'!$A$4:$H$500,2,0),0) -> 0 | C114: =IFERROR(VLOOKUP(E114,'기준가격대장(결산후)'!$A$4:$H$500,3,0),0) -> 0 | D114: =IFERROR(VLOOKUP(E114,'기준가격대장(결산후)'!$A$4:$H$500,4,0),0) -> 0 | E114: 243010 | F114: 미지급해지금 | G114: =IFERROR(VLOOKUP(E114,'기준가격대장(결산후)'!$A$4:$H$500,6,0),0) -> 0 | H114: =IFERROR(VLOOKUP(E114,'기준가격대장(결산후)'!$A$4:$H$500,7,0),0) -> 0 | I114: =IFERROR(VLOOKUP(E114,'기준가격대장(결산후)'!$A$4:$H$500,8,0),0) -> 0
B115: =IFERROR(VLOOKUP(E115,'기준가격대장(결산후)'!$A$4:$H$500,2,0),0) -> 0 | C115: =IFERROR(VLOOKUP(E115,'기준가격대장(결산후)'!$A$4:$H$500,3,0),0) -> 0 | D115: =IFERROR(VLOOKUP(E115,'기준가격대장(결산후)'!$A$4:$H$500,4,0),0) -> 0 | E115: 243030 | F115: 미지급해지보수 | G115: =IFERROR(VLOOKUP(E115,'기준가격대장(결산후)'!$A$4:$H$500,6,0),0) -> 0 | H115: =IFERROR(VLOOKUP(E115,'기준가격대장(결산후)'!$A$4:$H$500,7,0),0) -> 0 | I115: =IFERROR(VLOOKUP(E115,'기준가격대장(결산후)'!$A$4:$H$500,8,0),0) -> 0
B116: =IFERROR(VLOOKUP(E116,'기준가격대장(결산후)'!$A$4:$H$500,2,0),0) -> 0 | C116: =IFERROR(VLOOKUP(E116,'기준가격대장(결산후)'!$A$4:$H$500,3,0),0) -> 0 | D116: =IFERROR(VLOOKUP(E116,'기준가격대장(결산후)'!$A$4:$H$500,4,0),0) -> 0 | E116: 245010 | F116: 미지급이익분배금 | G116: =IFERROR(VLOOKUP(E116,'기준가격대장(결산후)'!$A$4:$H$500,6,0),0) -> 0 | H116: =IFERROR(VLOOKUP(E116,'기준가격대장(결산후)'!$A$4:$H$500,7,0),0) -> 0 | I116: =IFERROR(VLOOKUP(E116,'기준가격대장(결산후)'!$A$4:$H$500,8,0),0) -> 0
B117: =IFERROR(VLOOKUP(E117,'기준가격대장(결산후)'!$A$4:$H$500,2,0),0) -> 0 | C117: =IFERROR(VLOOKUP(E117,'기준가격대장(결산후)'!$A$4:$H$500,3,0),0) -> 0 | D117: =IFERROR(VLOOKUP(E117,'기준가격대장(결산후)'!$A$4:$H$500,4,0),0) -> 0 | E117: 246010 | F117: 미지급분배금 | G117: =IFERROR(VLOOKUP(E117,'기준가격대장(결산후)'!$A$4:$H$500,6,0),0) -> 870000000 | H117: =IFERROR(VLOOKUP(E117,'기준가격대장(결산후)'!$A$4:$H$500,7,0),0) -> 0 | I117: =IFERROR(VLOOKUP(E117,'기준가격대장(결산후)'!$A$4:$H$500,8,0),0) -> 870000000
B118: =IFERROR(VLOOKUP(E118,'기준가격대장(결산후)'!$A$4:$H$500,2,0),0) -> 0 | C118: =IFERROR(VLOOKUP(E118,'기준가격대장(결산후)'!$A$4:$H$500,3,0),0) -> 0 | D118: =IFERROR(VLOOKUP(E118,'기준가격대장(결산후)'!$A$4:$H$500,4,0),0) -> 0 | E118: 247020 | F118: 미지급주식배당금 | G118: =IFERROR(VLOOKUP(E118,'기준가격대장(결산후)'!$A$4:$H$500,6,0),0) -> 0 | H118: =IFERROR(VLOOKUP(E118,'기준가격대장(결산후)'!$A$4:$H$500,7,0),0) -> 0 | I118: =IFERROR(VLOOKUP(E118,'기준가격대장(결산후)'!$A$4:$H$500,8,0),0) -> 0
B119: =IFERROR(VLOOKUP(E119,'기준가격대장(결산후)'!$A$4:$H$500,2,0),0) -> 0 | C119: =IFERROR(VLOOKUP(E119,'기준가격대장(결산후)'!$A$4:$H$500,3,0),0) -> 0 | D119: =IFERROR(VLOOKUP(E119,'기준가격대장(결산후)'!$A$4:$H$500,4,0),0) -> 0 | E119: 247060 | F119: 미지급상장펀드배당금 | G119: =IFERROR(VLOOKUP(E119,'기준가격대장(결산후)'!$A$4:$H$500,6,0),0) -> 0 | H119: =IFERROR(VLOOKUP(E119,'기준가격대장(결산후)'!$A$4:$H$500,7,0),0) -> 0 | I119: =IFERROR(VLOOKUP(E119,'기준가격대장(결산후)'!$A$4:$H$500,8,0),0) -> 0
... B146: =IFERROR(VLOOKUP(E146,'기준가격대장(결산후)'!$A$4:$H$500,2,0),0) -> 0 | C146: =IFERROR(VLOOKUP(E146,'기준가격대장(결산후)'!$A$4:$H$500,3,0),0) -> 0 | D146: =IFERROR(VLOOKUP(E146,'기준가격대장(결산후)'!$A$4:$H$500,4,0),0) -> 0 | E146: 295121 | F146: 미지급판매사후원기금(과세) | G146: =IFERROR(VLOOKUP(E146,'기준가격대장(결산후)'!$A$4:$H$500,6,0),0) -> 0 | H146: =IFERROR(VLOOKUP(E146,'기준가격대장(결산후)'!$A$4:$H$500,7,0),0) -> 0 | I146: =IFERROR(VLOOKUP(E146,'기준가격대장(결산후)'!$A$4:$H$500,8,0),0) -> 0
B147: =IFERROR(VLOOKUP(E147,'기준가격대장(결산후)'!$A$4:$H$500,2,0),0) -> 0 | C147: =IFERROR(VLOOKUP(E147,'기준가격대장(결산후)'!$A$4:$H$500,3,0),0) -> 586880529621 | D147: =IFERROR(VLOOKUP(E147,'기준가격대장(결산후)'!$A$4:$H$500,4,0),0) -> 0 | E147: 300000 | F147: 원본합계 | G147: =IFERROR(VLOOKUP(E147,'기준가격대장(결산후)'!$A$4:$H$500,6,0),0) -> 49219970523 | H147: =IFERROR(VLOOKUP(E147,'기준가격대장(결산후)'!$A$4:$H$500,7,0),0) -> 675029515999 | I147: =IFERROR(VLOOKUP(E147,'기준가격대장(결산후)'!$A$4:$H$500,8,0),0) -> 137368956901 | K147: 자본검증 | L147: =SUM(I148:I159)=I147 -> TRUE
B148: =IFERROR(VLOOKUP(E148,'기준가격대장(결산후)'!$A$4:$H$500,2,0),0) -> 0 | C148: =IFERROR(VLOOKUP(E148,'기준가격대장(결산후)'!$A$4:$H$500,3,0),0) -> 0 | D148: =IFERROR(VLOOKUP(E148,'기준가격대장(결산후)'!$A$4:$H$500,4,0),0) -> 0 | E148: 301010 | F148: 원본액 | G148: =IFERROR(VLOOKUP(E148,'기준가격대장(결산후)'!$A$4:$H$500,6,0),0) -> 29000000000 | H148: =IFERROR(VLOOKUP(E148,'기준가격대장(결산후)'!$A$4:$H$500,7,0),0) -> 0 | I148: =IFERROR(VLOOKUP(E148,'기준가격대장(결산후)'!$A$4:$H$500,8,0),0) -> 29000000000
B149: =IFERROR(VLOOKUP(E149,'기준가격대장(결산후)'!$A$4:$H$500,2,0),0) -> 0 | C149: =IFERROR(VLOOKUP(E149,'기준가격대장(결산후)'!$A$4:$H$500,3,0),0) -> 8853823181 | D149: =IFERROR(VLOOKUP(E149,'기준가격대장(결산후)'!$A$4:$H$500,4,0),0) -> 0 | E149: 311011 | F149: 이월이익잉여금(과세) | G149: =IFERROR(VLOOKUP(E149,'기준가격대장(결산후)'!$A$4:$H$500,6,0),0) -> 8853823181 | H149: =IFERROR(VLOOKUP(E149,'기준가격대장(결산후)'!$A$4:$H$500,7,0),0) -> 8354536107 | I149: =IFERROR(VLOOKUP(E149,'기준가격대장(결산후)'!$A$4:$H$500,8,0),0) -> 8354536107
B150: =IFERROR(VLOOKUP(E150,'기준가격대장(결산후)'!$A$4:$H$500,2,0),0) -> 0 | C150: =IFERROR(VLOOKUP(E150,'기준가격대장(결산후)'!$A$4:$H$500,3,0),0) -> 2578559132 | D150: =IFERROR(VLOOKUP(E150,'기준가격대장(결산후)'!$A$4:$H$500,4,0),0) -> 0 | E150: 311012 | F150: 이월이익잉여금(비과세) | G150: =IFERROR(VLOOKUP(E150,'기준가격대장(결산후)'!$A$4:$H$500,6,0),0) -> 2578559132 | H150: =IFERROR(VLOOKUP(E150,'기준가격대장(결산후)'!$A$4:$H$500,7,0),0) -> 100014420794 | I150: =IFERROR(VLOOKUP(E150,'기준가격대장(결산후)'!$A$4:$H$500,8,0),0) -> 100014420794
B151: =IFERROR(VLOOKUP(E151,'기준가격대장(결산후)'!$A$4:$H$500,2,0),0) -> 0 | C151: =IFERROR(VLOOKUP(E151,'기준가격대장(결산후)'!$A$4:$H$500,3,0),0) -> 0 | D151: =IFERROR(VLOOKUP(E151,'기준가격대장(결산후)'!$A$4:$H$500,4,0),0) -> 0 | E151: 311022 | F151: 이월이익잉여금2(비과세) | G151: =IFERROR(VLOOKUP(E151,'기준가격대장(결산후)'!$A$4:$H$500,6,0),0) -> 0 | H151: =IFERROR(VLOOKUP(E151,'기준가격대장(결산후)'!$A$4:$H$500,7,0),0) -> 0 | I151: =IFERROR(VLOOKUP(E151,'기준가격대장(결산후)'!$A$4:$H$500,8,0),0) -> 0
B152: =IFERROR(VLOOKUP(E152,'기준가격대장(결산후)'!$A$4:$H$500,2,0),0) -> 0 | C152: =IFERROR(VLOOKUP(E152,'기준가격대장(결산후)'!$A$4:$H$500,3,0),0) -> 109144656237 | D152: =IFERROR(VLOOKUP(E152,'기준가격대장(결산후)'!$A$4:$H$500,4,0),0) -> 0 | E152: 331011 | F152: 설정조정금(과세) | G152: =IFERROR(VLOOKUP(E152,'기준가격대장(결산후)'!$A$4:$H$500,6,0),0) -> 109144656237 | H152: =IFERROR(VLOOKUP(E152,'기준가격대장(결산후)'!$A$4:$H$500,7,0),0) -> 0 | I152: =IFERROR(VLOOKUP(E152,'기준가격대장(결산후)'!$A$4:$H$500,8,0),0) -> 0
B153: =IFERROR(VLOOKUP(E153,'기준가격대장(결산후)'!$A$4:$H$500,2,0),0) -> 0 | C153: =IFERROR(VLOOKUP(E153,'기준가격대장(결산후)'!$A$4:$H$500,3,0),0) -> 466303491071 | D153: =IFERROR(VLOOKUP(E153,'기준가격대장(결산후)'!$A$4:$H$500,4,0),0) -> 0 | E153: 331012 | F153: 설정조정금(비과세) | G153: =IFERROR(VLOOKUP(E153,'기준가격대장(결산후)'!$A$4:$H$500,6,0),0) -> 466303491071 | H153: =IFERROR(VLOOKUP(E153,'기준가격대장(결산후)'!$A$4:$H$500,7,0),0) -> 0 | I153: =IFERROR(VLOOKUP(E153,'기준가격대장(결산후)'!$A$4:$H$500,8,0),0) -> 0
B154: =IFERROR(VLOOKUP(E154,'기준가격대장(결산후)'!$A$4:$H$500,2,0),0) -> 0 | C154: =IFERROR(VLOOKUP(E154,'기준가격대장(결산후)'!$A$4:$H$500,3,0),0) -> 0 | D154: =IFERROR(VLOOKUP(E154,'기준가격대장(결산후)'!$A$4:$H$500,4,0),0) -> 0 | E154: 331022 | F154: 설정조정금2(비과세) | G154: =IFERROR(VLOOKUP(E154,'기준가격대장(결산후)'!$A$4:$H$500,6,0),0) -> 0 | H154: =IFERROR(VLOOKUP(E154,'기준가격대장(결산후)'!$A$4:$H$500,7,0),0) -> 0 | I154: =IFERROR(VLOOKUP(E154,'기준가격대장(결산후)'!$A$4:$H$500,8,0),0) -> 0
B155: =IFERROR(VLOOKUP(E155,'기준가격대장(결산후)'!$A$4:$H$500,2,0),0) -> 0 | C155: =IFERROR(VLOOKUP(E155,'기준가격대장(결산후)'!$A$4:$H$500,3,0),0) -> 0 | D155: =IFERROR(VLOOKUP(E155,'기준가격대장(결산후)'!$A$4:$H$500,4,0),0) -> 0 | E155: 331031 | F155: 해지조정금(과세) | G155: =IFERROR(VLOOKUP(E155,'기준가격대장(결산후)'!$A$4:$H$500,6,0),0) -> -109653470172 | H155: =IFERROR(VLOOKUP(E155,'기준가격대장(결산후)'!$A$4:$H$500,7,0),0) -> 109653470172 | I155: =IFERROR(VLOOKUP(E155,'기준가격대장(결산후)'!$A$4:$H$500,8,0),0) -> 0
B156: =IFERROR(VLOOKUP(E156,'기준가격대장(결산후)'!$A$4:$H$500,2,0),0) -> 0 | C156: =IFERROR(VLOOKUP(E156,'기준가격대장(결산후)'!$A$4:$H$500,3,0),0) -> 0 | D156: =IFERROR(VLOOKUP(E156,'기준가격대장(결산후)'!$A$4:$H$500,4,0),0) -> 0 | E156: 331032 | F156: 해지조정금(비과세) | G156: =IFERROR(VLOOKUP(E156,'기준가격대장(결산후)'!$A$4:$H$500,6,0),0) -> -456137088926 | H156: =IFERROR(VLOOKUP(E156,'기준가격대장(결산후)'!$A$4:$H$500,7,0),0) -> 456137088926 | I156: =IFERROR(VLOOKUP(E156,'기준가격대장(결산후)'!$A$4:$H$500,8,0),0) -> 0
B157: =IFERROR(VLOOKUP(E157,'기준가격대장(결산후)'!$A$4:$H$500,2,0),0) -> 0 | C157: =IFERROR(VLOOKUP(E157,'기준가격대장(결산후)'!$A$4:$H$500,3,0),0) -> 0 | D157: =IFERROR(VLOOKUP(E157,'기준가격대장(결산후)'!$A$4:$H$500,4,0),0) -> 0 | E157: 331042 | F157: 해지조정금2(비과세) | G157: =IFERROR(VLOOKUP(E157,'기준가격대장(결산후)'!$A$4:$H$500,6,0),0) -> 0 | H157: =IFERROR(VLOOKUP(E157,'기준가격대장(결산후)'!$A$4:$H$500,7,0),0) -> 0 | I157: =IFERROR(VLOOKUP(E157,'기준가격대장(결산후)'!$A$4:$H$500,8,0),0) -> 0
B158: =IFERROR(VLOOKUP(E158,'기준가격대장(결산후)'!$A$4:$H$500,2,0),0) -> 0 | C158: =IFERROR(VLOOKUP(E158,'기준가격대장(결산후)'!$A$4:$H$500,3,0),0) -> 0 | D158: =IFERROR(VLOOKUP(E158,'기준가격대장(결산후)'!$A$4:$H$500,4,0),0) -> 0 | E158: 341011 | F158: 기지급분배금(과세) | G158: =IFERROR(VLOOKUP(E158,'기준가격대장(결산후)'!$A$4:$H$500,6,0),0) -> -870000000 | H158: =IFERROR(VLOOKUP(E158,'기준가격대장(결산후)'!$A$4:$H$500,7,0),0) -> 870000000 | I158: =IFERROR(VLOOKUP(E158,'기준가격대장(결산후)'!$A$4:$H$500,8,0),0) -> 0
B159: =IFERROR(VLOOKUP(E159,'기준가격대장(결산후)'!$A$4:$H$500,2,0),0) -> 0 | C159: =IFERROR(VLOOKUP(E159,'기준가격대장(결산후)'!$A$4:$H$500,3,0),0) -> 0 | D159: =IFERROR(VLOOKUP(E159,'기준가격대장(결산후)'!$A$4:$H$500,4,0),0) -> 0 | E159: 341012 | F159: 기지급분배금(비과세) | G159: =IFERROR(VLOOKUP(E159,'기준가격대장(결산후)'!$A$4:$H$500,6,0),0) -> 0 | H159: =IFERROR(VLOOKUP(E159,'기준가격대장(결산후)'!$A$4:$H$500,7,0),0) -> 0 | I159: =IFERROR(VLOOKUP(E159,'기준가격대장(결산후)'!$A$4:$H$500,8,0),0) -> 0
B160: =IFERROR(VLOOKUP(E160,'기준가격대장(결산후)'!$A$4:$H$500,2,0),0) -> 0 | C160: =IFERROR(VLOOKUP(E160,'기준가격대장(결산후)'!$A$4:$H$500,3,0),0) -> 0 | D160: =IFERROR(VLOOKUP(E160,'기준가격대장(결산후)'!$A$4:$H$500,4,0),0) -> 79321043627 | E160: 400000 | F160: 비용합계 | G160: =IFERROR(VLOOKUP(E160,'기준가격대장(결산후)'!$A$4:$H$500,6,0),0) -> 0 | H160: =IFERROR(VLOOKUP(E160,'기준가격대장(결산후)'!$A$4:$H$500,7,0),0) -> 79321043627 | I160: =IFERROR(VLOOKUP(E160,'기준가격대장(결산후)'!$A$4:$H$500,8,0),0) -> 0 | K160: 비용검증 | L160: =SUM(D161:D262)=D160 -> TRUE | M160: =SUM(D161:D262)-D160 -> 0
B161: =IFERROR(VLOOKUP(E161,'기준가격대장(결산후)'!$A$4:$H$500,2,0),0) -> 0 | C161: =IFERROR(VLOOKUP(E161,'기준가격대장(결산후)'!$A$4:$H$500,3,0),0) -> 0 | D161: =IFERROR(VLOOKUP(E161,'기준가격대장(결산후)'!$A$4:$H$500,4,0),0) -> 44085416 | E161: 401012 | F161: 상장주식처분손실(비과세) | G161: =IFERROR(VLOOKUP(E161,'기준가격대장(결산후)'!$A$4:$H$500,6,0),0) -> 0 | H161: =IFERROR(VLOOKUP(E161,'기준가격대장(결산후)'!$A$4:$H$500,7,0),0) -> 44085416 | I161: =IFERROR(VLOOKUP(E161,'기준가격대장(결산후)'!$A$4:$H$500,8,0),0) -> 0
B162: =IFERROR(VLOOKUP(E162,'기준가격대장(결산후)'!$A$4:$H$500,2,0),0) -> 0 | C162: =IFERROR(VLOOKUP(E162,'기준가격대장(결산후)'!$A$4:$H$500,3,0),0) -> 0 | D162: =IFERROR(VLOOKUP(E162,'기준가격대장(결산후)'!$A$4:$H$500,4,0),0) -> 0 | E162: 401032 | F162: 코스닥주식처분손실(비과세) | G162: =IFERROR(VLOOKUP(E162,'기준가격대장(결산후)'!$A$4:$H$500,6,0),0) -> 0 | H162: =IFERROR(VLOOKUP(E162,'기준가격대장(결산후)'!$A$4:$H$500,7,0),0) -> 0 | I162: =IFERROR(VLOOKUP(E162,'기준가격대장(결산후)'!$A$4:$H$500,8,0),0) -> 0 | K162: 과세 | L162: =D160-L163 -> 521312022
B163: =IFERROR(VLOOKUP(E163,'기준가격대장(결산후)'!$A$4:$H$500,2,0),0) -> 0 | C163: =IFERROR(VLOOKUP(E163,'기준가격대장(결산후)'!$A$4:$H$500,3,0),0) -> 0 | D163: =IFERROR(VLOOKUP(E163,'기준가격대장(결산후)'!$A$4:$H$500,4,0),0) -> 0 | E163: 401071 | F163: 외화주식처분손실(과세) | G163: =IFERROR(VLOOKUP(E163,'기준가격대장(결산후)'!$A$4:$H$500,6,0),0) -> 0 | H163: =IFERROR(VLOOKUP(E163,'기준가격대장(결산후)'!$A$4:$H$500,7,0),0) -> 0 | I163: =IFERROR(VLOOKUP(E163,'기준가격대장(결산후)'!$A$4:$H$500,8,0),0) -> 0 | K163: 비과세 | L163: =SUM(D161,D162,D173,D175,D177,D178,D200,D201,D209,D211,D212,D214,D215,D252,D337,D180,D187,D197,D233,D165,D205,D195,D250,D218) -> 78799731605
B164: =IFERROR(VLOOKUP(E164,'기준가격대장(결산후)'!$A$4:$H$500,2,0),0) -> 0 | C164: =IFERROR(VLOOKUP(E164,'기준가격대장(결산후)'!$A$4:$H$500,3,0),0) -> 0 | D164: =IFERROR(VLOOKUP(E164,'기준가격대장(결산후)'!$A$4:$H$500,4,0),0) -> 0 | E164: 403011 | F164: 채권처분손실(과세) | G164: =IFERROR(VLOOKUP(E164,'기준가격대장(결산후)'!$A$4:$H$500,6,0),0) -> 0 | H164: =IFERROR(VLOOKUP(E164,'기준가격대장(결산후)'!$A$4:$H$500,7,0),0) -> 0 | I164: =IFERROR(VLOOKUP(E164,'기준가격대장(결산후)'!$A$4:$H$500,8,0),0) -> 0
B165: =IFERROR(VLOOKUP(E165,'기준가격대장(결산후)'!$A$4:$H$500,2,0),0) -> 0 | C165: =IFERROR(VLOOKUP(E165,'기준가격대장(결산후)'!$A$4:$H$500,3,0),0) -> 0 | D165: =IFERROR(VLOOKUP(E165,'기준가격대장(결산후)'!$A$4:$H$500,4,0),0) -> 0 | E165: 401022 | F165: 차입상장주식처분손실(비과세) | G165: =IFERROR(VLOOKUP(E165,'기준가격대장(결산후)'!$A$4:$H$500,6,0),0) -> 0 | H165: =IFERROR(VLOOKUP(E165,'기준가격대장(결산후)'!$A$4:$H$500,7,0),0) -> 0 | I165: =IFERROR(VLOOKUP(E165,'기준가격대장(결산후)'!$A$4:$H$500,8,0),0) -> 0 | J165: 추가 | K165: NI | L165: =G263-D160 -> 88148986378
B166: =IFERROR(VLOOKUP(E166,'기준가격대장(결산후)'!$A$4:$H$500,2,0),0) -> 0 | C166: =IFERROR(VLOOKUP(E166,'기준가격대장(결산후)'!$A$4:$H$500,3,0),0) -> 0 | D166: =IFERROR(VLOOKUP(E166,'기준가격대장(결산후)'!$A$4:$H$500,4,0),0) -> 0 | E166: 403041 | F166: 차입채권매매손실(과세) | G166: =IFERROR(VLOOKUP(E166,'기준가격대장(결산후)'!$A$4:$H$500,6,0),0) -> 0 | H166: =IFERROR(VLOOKUP(E166,'기준가격대장(결산후)'!$A$4:$H$500,7,0),0) -> 0 | I166: =IFERROR(VLOOKUP(E166,'기준가격대장(결산후)'!$A$4:$H$500,8,0),0) -> 0
B167: =IFERROR(VLOOKUP(E167,'기준가격대장(결산후)'!$A$4:$H$500,2,0),0) -> 0 | C167: =IFERROR(VLOOKUP(E167,'기준가격대장(결산후)'!$A$4:$H$500,3,0),0) -> 0 | D167: =IFERROR(VLOOKUP(E167,'기준가격대장(결산후)'!$A$4:$H$500,4,0),0) -> 0 | E167: 403051 | F167: 외화채권처분손실(과세) | G167: =IFERROR(VLOOKUP(E167,'기준가격대장(결산후)'!$A$4:$H$500,6,0),0) -> 0 | H167: =IFERROR(VLOOKUP(E167,'기준가격대장(결산후)'!$A$4:$H$500,7,0),0) -> 0 | I167: =IFERROR(VLOOKUP(E167,'기준가격대장(결산후)'!$A$4:$H$500,8,0),0) -> 0
B168: =IFERROR(VLOOKUP(E168,'기준가격대장(결산후)'!$A$4:$H$500,2,0),0) -> 0 | C168: =IFERROR(VLOOKUP(E168,'기준가격대장(결산후)'!$A$4:$H$500,3,0),0) -> 0 | D168: =IFERROR(VLOOKUP(E168,'기준가격대장(결산후)'!$A$4:$H$500,4,0),0) -> 0 | E168: 405011 | F168: CP처분손실(과세) | G168: =IFERROR(VLOOKUP(E168,'기준가격대장(결산후)'!$A$4:$H$500,6,0),0) -> 0 | H168: =IFERROR(VLOOKUP(E168,'기준가격대장(결산후)'!$A$4:$H$500,7,0),0) -> 0 | I168: =IFERROR(VLOOKUP(E168,'기준가격대장(결산후)'!$A$4:$H$500,8,0),0) -> 0
B169: =IFERROR(VLOOKUP(E169,'기준가격대장(결산후)'!$A$4:$H$500,2,0),0) -> 0 | C169: =IFERROR(VLOOKUP(E169,'기준가격대장(결산후)'!$A$4:$H$500,3,0),0) -> 0 | D169: =IFERROR(VLOOKUP(E169,'기준가격대장(결산후)'!$A$4:$H$500,4,0),0) -> 0 | E169: 405031 | F169: CD처분손실(과세) | G169: =IFERROR(VLOOKUP(E169,'기준가격대장(결산후)'!$A$4:$H$500,6,0),0) -> 0 | H169: =IFERROR(VLOOKUP(E169,'기준가격대장(결산후)'!$A$4:$H$500,7,0),0) -> 0 | I169: =IFERROR(VLOOKUP(E169,'기준가격대장(결산후)'!$A$4:$H$500,8,0),0) -> 0
B170: =IFERROR(VLOOKUP(E170,'기준가격대장(결산후)'!$A$4:$H$500,2,0),0) -> 0 | C170: =IFERROR(VLOOKUP(E170,'기준가격대장(결산후)'!$A$4:$H$500,3,0),0) -> 0 | D170: =IFERROR(VLOOKUP(E170,'기준가격대장(결산후)'!$A$4:$H$500,4,0),0) -> 0 | E170: 405051 | F170: 기타유동처분손실(과세) | G170: =IFERROR(VLOOKUP(E170,'기준가격대장(결산후)'!$A$4:$H$500,6,0),0) -> 0 | H170: =IFERROR(VLOOKUP(E170,'기준가격대장(결산후)'!$A$4:$H$500,7,0),0) -> 0 | I170: =IFERROR(VLOOKUP(E170,'기준가격대장(결산후)'!$A$4:$H$500,8,0),0) -> 0
B171: =IFERROR(VLOOKUP(E171,'기준가격대장(결산후)'!$A$4:$H$500,2,0),0) -> 0 | C171: =IFERROR(VLOOKUP(E171,'기준가격대장(결산후)'!$A$4:$H$500,3,0),0) -> 0 | D171: =IFERROR(VLOOKUP(E171,'기준가격대장(결산후)'!$A$4:$H$500,4,0),0) -> 0 | E171: 405911 | F171: 유동처분손실(과세) | G171: =IFERROR(VLOOKUP(E171,'기준가격대장(결산후)'!$A$4:$H$500,6,0),0) -> 0 | H171: =IFERROR(VLOOKUP(E171,'기준가격대장(결산후)'!$A$4:$H$500,7,0),0) -> 0 | I171: =IFERROR(VLOOKUP(E171,'기준가격대장(결산후)'!$A$4:$H$500,8,0),0) -> 0
B172: =IFERROR(VLOOKUP(E172,'기준가격대장(결산후)'!$A$4:$H$500,2,0),0) -> 0 | C172: =IFERROR(VLOOKUP(E172,'기준가격대장(결산후)'!$A$4:$H$500,3,0),0) -> 0 | D172: =IFERROR(VLOOKUP(E172,'기준가격대장(결산후)'!$A$4:$H$500,4,0),0) -> 484877828 | E172: 407011 | F172: 상장펀드처분손실(과세) | G172: =IFERROR(VLOOKUP(E172,'기준가격대장(결산후)'!$A$4:$H$500,6,0),0) -> 0 | H172: =IFERROR(VLOOKUP(E172,'기준가격대장(결산후)'!$A$4:$H$500,7,0),0) -> 484877828 | I172: =IFERROR(VLOOKUP(E172,'기준가격대장(결산후)'!$A$4:$H$500,8,0),0) -> 0
B173: =IFERROR(VLOOKUP(E173,'기준가격대장(결산후)'!$A$4:$H$500,2,0),0) -> 0 | C173: =IFERROR(VLOOKUP(E173,'기준가격대장(결산후)'!$A$4:$H$500,3,0),0) -> 0 | D173: =IFERROR(VLOOKUP(E173,'기준가격대장(결산후)'!$A$4:$H$500,4,0),0) -> 484142055 | E173: 407012 | F173: 상장펀드처분손실(비과세) | G173: =IFERROR(VLOOKUP(E173,'기준가격대장(결산후)'!$A$4:$H$500,6,0),0) -> 0 | H173: =IFERROR(VLOOKUP(E173,'기준가격대장(결산후)'!$A$4:$H$500,7,0),0) -> 484142055 | I173: =IFERROR(VLOOKUP(E173,'기준가격대장(결산후)'!$A$4:$H$500,8,0),0) -> 0
B174: =IFERROR(VLOOKUP(E174,'기준가격대장(결산후)'!$A$4:$H$500,2,0),0) -> 0 | C174: =IFERROR(VLOOKUP(E174,'기준가격대장(결산후)'!$A$4:$H$500,3,0),0) -> 0 | D174: =IFERROR(VLOOKUP(E174,'기준가격대장(결산후)'!$A$4:$H$500,4,0),0) -> 0 | E174: 407021 | F174: 차입상장펀드처분손실(과세) | G174: =IFERROR(VLOOKUP(E174,'기준가격대장(결산후)'!$A$4:$H$500,6,0),0) -> 0 | H174: =IFERROR(VLOOKUP(E174,'기준가격대장(결산후)'!$A$4:$H$500,7,0),0) -> 0 | I174: =IFERROR(VLOOKUP(E174,'기준가격대장(결산후)'!$A$4:$H$500,8,0),0) -> 0
B175: =IFERROR(VLOOKUP(E175,'기준가격대장(결산후)'!$A$4:$H$500,2,0),0) -> 0 | C175: =IFERROR(VLOOKUP(E175,'기준가격대장(결산후)'!$A$4:$H$500,3,0),0) -> 0 | D175: =IFERROR(VLOOKUP(E175,'기준가격대장(결산후)'!$A$4:$H$500,4,0),0) -> 0 | E175: 407032 | F175: 상장펀드처분손실2(비과세) | G175: =IFERROR(VLOOKUP(E175,'기준가격대장(결산후)'!$A$4:$H$500,6,0),0) -> 0 | H175: =IFERROR(VLOOKUP(E175,'기준가격대장(결산후)'!$A$4:$H$500,7,0),0) -> 0 | I175: =IFERROR(VLOOKUP(E175,'기준가격대장(결산후)'!$A$4:$H$500,8,0),0) -> 0
B176: =IFERROR(VLOOKUP(E176,'기준가격대장(결산후)'!$A$4:$H$500,2,0),0) -> 0 | C176: =IFERROR(VLOOKUP(E176,'기준가격대장(결산후)'!$A$4:$H$500,3,0),0) -> 0 | D176: =IFERROR(VLOOKUP(E176,'기준가격대장(결산후)'!$A$4:$H$500,4,0),0) -> 0 | E176: 409011 | F176: 수익증권처분손실(과세) | G176: =IFERROR(VLOOKUP(E176,'기준가격대장(결산후)'!$A$4:$H$500,6,0),0) -> 0 | H176: =IFERROR(VLOOKUP(E176,'기준가격대장(결산후)'!$A$4:$H$500,7,0),0) -> 0 | I176: =IFERROR(VLOOKUP(E176,'기준가격대장(결산후)'!$A$4:$H$500,8,0),0) -> 0
B177: =IFERROR(VLOOKUP(E177,'기준가격대장(결산후)'!$A$4:$H$500,2,0),0) -> 0 | C177: =IFERROR(VLOOKUP(E177,'기준가격대장(결산후)'!$A$4:$H$500,3,0),0) -> 0 | D177: =IFERROR(VLOOKUP(E177,'기준가격대장(결산후)'!$A$4:$H$500,4,0),0) -> 0 | E177: 409012 | F177: 수익증권처분손실(비과세) | G177: =IFERROR(VLOOKUP(E177,'기준가격대장(결산후)'!$A$4:$H$500,6,0),0) -> 0 | H177: =IFERROR(VLOOKUP(E177,'기준가격대장(결산후)'!$A$4:$H$500,7,0),0) -> 0 | I177: =IFERROR(VLOOKUP(E177,'기준가격대장(결산후)'!$A$4:$H$500,8,0),0) -> 0
... B194: =IFERROR(VLOOKUP(E194,'기준가격대장(결산후)'!$A$4:$H$500,2,0),0) -> 0 | C194: =IFERROR(VLOOKUP(E194,'기준가격대장(결산후)'!$A$4:$H$500,3,0),0) -> 0 | D194: =IFERROR(VLOOKUP(E194,'기준가격대장(결산후)'!$A$4:$H$500,4,0),0) -> 0 | E194: 416131 | F194: 통화스왑처분손실(과세) | G194: =IFERROR(VLOOKUP(E194,'기준가격대장(결산후)'!$A$4:$H$500,6,0),0) -> 0 | H194: =IFERROR(VLOOKUP(E194,'기준가격대장(결산후)'!$A$4:$H$500,7,0),0) -> 0 | I194: =IFERROR(VLOOKUP(E194,'기준가격대장(결산후)'!$A$4:$H$500,8,0),0) -> 0
B195: =IFERROR(VLOOKUP(E195,'기준가격대장(결산후)'!$A$4:$H$500,2,0),0) -> 0 | C195: =IFERROR(VLOOKUP(E195,'기준가격대장(결산후)'!$A$4:$H$500,3,0),0) -> 0 | D195: =IFERROR(VLOOKUP(E195,'기준가격대장(결산후)'!$A$4:$H$500,4,0),0) -> 0 | E195: 417012 | F195: 주식옵션처분손실(비과세) | G195: =IFERROR(VLOOKUP(E195,'기준가격대장(결산후)'!$A$4:$H$500,6,0),0) -> 0 | H195: =IFERROR(VLOOKUP(E195,'기준가격대장(결산후)'!$A$4:$H$500,7,0),0) -> 0 | I195: =IFERROR(VLOOKUP(E195,'기준가격대장(결산후)'!$A$4:$H$500,8,0),0) -> 0 | J195: 추가
B196: =IFERROR(VLOOKUP(E196,'기준가격대장(결산후)'!$A$4:$H$500,2,0),0) -> 0 | C196: =IFERROR(VLOOKUP(E196,'기준가격대장(결산후)'!$A$4:$H$500,3,0),0) -> 0 | D196: =IFERROR(VLOOKUP(E196,'기준가격대장(결산후)'!$A$4:$H$500,4,0),0) -> 0 | E196: 417061 | F196: 외화옵션처분손실(과세) | G196: =IFERROR(VLOOKUP(E196,'기준가격대장(결산후)'!$A$4:$H$500,6,0),0) -> 0 | H196: =IFERROR(VLOOKUP(E196,'기준가격대장(결산후)'!$A$4:$H$500,7,0),0) -> 0 | I196: =IFERROR(VLOOKUP(E196,'기준가격대장(결산후)'!$A$4:$H$500,8,0),0) -> 0
B197: =IFERROR(VLOOKUP(E197,'기준가격대장(결산후)'!$A$4:$H$500,2,0),0) -> 0 | C197: =IFERROR(VLOOKUP(E197,'기준가격대장(결산후)'!$A$4:$H$500,3,0),0) -> 0 | D197: =IFERROR(VLOOKUP(E197,'기준가격대장(결산후)'!$A$4:$H$500,4,0),0) -> 0 | E197: 419012 | F197: 신주인수권처분손실(비과세) | G197: =IFERROR(VLOOKUP(E197,'기준가격대장(결산후)'!$A$4:$H$500,6,0),0) -> 0 | H197: =IFERROR(VLOOKUP(E197,'기준가격대장(결산후)'!$A$4:$H$500,7,0),0) -> 0 | I197: =IFERROR(VLOOKUP(E197,'기준가격대장(결산후)'!$A$4:$H$500,8,0),0) -> 0
B198: =IFERROR(VLOOKUP(E198,'기준가격대장(결산후)'!$A$4:$H$500,2,0),0) -> 0 | C198: =IFERROR(VLOOKUP(E198,'기준가격대장(결산후)'!$A$4:$H$500,3,0),0) -> 0 | D198: =IFERROR(VLOOKUP(E198,'기준가격대장(결산후)'!$A$4:$H$500,4,0),0) -> 0 | E198: 419071 | F198: 통화스왑처분손실(과세) | G198: =IFERROR(VLOOKUP(E198,'기준가격대장(결산후)'!$A$4:$H$500,6,0),0) -> 0 | H198: =IFERROR(VLOOKUP(E198,'기준가격대장(결산후)'!$A$4:$H$500,7,0),0) -> 0 | I198: =IFERROR(VLOOKUP(E198,'기준가격대장(결산후)'!$A$4:$H$500,8,0),0) -> 0
B199: =IFERROR(VLOOKUP(E199,'기준가격대장(결산후)'!$A$4:$H$500,2,0),0) -> 0 | C199: =IFERROR(VLOOKUP(E199,'기준가격대장(결산후)'!$A$4:$H$500,3,0),0) -> 0 | D199: =IFERROR(VLOOKUP(E199,'기준가격대장(결산후)'!$A$4:$H$500,4,0),0) -> 0 | E199: 423011 | F199: 외환차손(과세) | G199: =IFERROR(VLOOKUP(E199,'기준가격대장(결산후)'!$A$4:$H$500,6,0),0) -> 0 | H199: =IFERROR(VLOOKUP(E199,'기준가격대장(결산후)'!$A$4:$H$500,7,0),0) -> 0 | I199: =IFERROR(VLOOKUP(E199,'기준가격대장(결산후)'!$A$4:$H$500,8,0),0) -> 0
...

Sheet C1_정산표
B1: 한빛코스피레버리지증권상장지수투자신탁(주식-파생형)
B2: 45657 | G2: Prepared by : | H2: SJ
B3: 정산표 재계산 | G3: Reviewed by : | H3: MK
J6: 전기보고서숫자 넣어야함
F7: <공고용 BS> | J7: 합계수식걸려있음
B8: 과목 | C8: 제 X (당)기 | E8: 공시여부 | F8: 과목 | G8: 제 X (당)기 | I8: 제 X (전)기 | K8: 주석 번호(자동) | L8: 과목순서(자동)
B9: =F9 -> 자산 | E9: 공시 | F9: 자산
B10: =F10 -> Ⅰ. 운용자산 | C10: =C11++C21+C16+C26 -> 143513794320 | E10: =IF(AND(G10=0,H10=0,I10=0,J10=0),"공시제외","공시") -> 공시 | F10: =L10&". 운용자산" -> Ⅰ. 운용자산 | H10: =G11+G21+G16+G26 -> 138145120376 | J10: 42400001063 | L10: Ⅰ
B11: =F11 -> 1. 현금및예치금 (주석3) | C11: =SUM(C12:C15) -> 7196301321 | E11: =IF(AND(G11=0,H11=0,I11=0,J11=0),"공시제외","공시") -> 공시 | F11: =L11&". 현금및예치금 (주석"&K11&")" -> 1. 현금및예치금 (주석3) | G11: =C11 -> 7196301321 | I11: 2337568068 | K11: =IF(OR(G11>0,I11>0),3,FALSE) -> 3 | L11: =IF(OR(G11>0,I11>0),1,0) -> 1
B12: =F12 -> (1) 현금및현금성자산 | C12: ='통합기준가격대장(결산후)'!B7+'통합기준가격대장(결산후)'!B8 -> 7196301321 | E12: =IF(AND(G12=0,H12=0,I12=0,J12=0),"공시제외","공시") -> 공시 | F12: ="("&L12&") 현금및현금성자산" -> (1) 현금및현금성자산 | G12: =C12 -> 7196301321 | I12: 2246153208 | L12: =IF(OR(G12>0,I12>0),1,0) -> 1
B13: =F13 -> (1) 예치금 | C13: ='통합기준가격대장(결산후)'!B12 -> 0 | E13: =IF(AND(G13=0,H13=0,I13=0,J13=0),"공시제외","공시") -> 공시제외 | F13: ="("&L13&") 예치금" -> (1) 예치금 | G13: =C13 -> 0 | I13: 0 | L13: =IF(OR(G13>0,I13>0),L12+1,L12) -> 1 | N13: (2) 증거금 | Q13: 118923050
B14: =F14 -> (1) 양도성예금증서 | C14: ='통합기준가격대장(결산후)'!B11 -> 0 | E14: =IF(AND(G14=0,H14=0,I14=0,J14=0),"공시제외","공시") -> 공시제외 | F14: ="("&L14&") 양도성예금증서" -> (1) 양도성예금증서 | G14: =C14 -> 0 | I14: 0 | L14: =IF(OR(G14>0,I14>0),L13+1,L13) -> 1 | N14: 2. 대출채권 (주4) | Q14: 1500000000
B15: =F15 -> (2) 증거금 | C15: =SUM('통합기준가격대장(결산후)'!B32:B34) -> 0 | E15: =IF(AND(G15=0,H15=0,I15=0,J15=0),"공시제외","공시") -> 공시 | F15: ="("&L15&") 증거금" -> (2) 증거금 | G15: =C15 -> 0 | I15: 91414860 | L15: =IF(OR(G15>0,I15>0),L14+1,L14) -> 2
B16: =F16 -> 1. 대출채권 (주석3) | C16: =SUM(C17:C20) -> 0 | E16: =IF(AND(G16=0,H16=0,I16=0,J16=0),"공시제외","공시") -> 공시제외 | F16: =L16&". 대출채권 (주석"&K16&")" -> 1. 대출채권 (주석3) | G16: =C16 -> 0 | I16: 0 | K16: =IF(OR(G16>0,I16>0),K11+1,K11) -> 3 | L16: =IF(OR(G16>0,I16>0),L11+1,L11) -> 1 | N16: 3. 유가증권
B17: =F17 -> (0) 콜론 | C17: ='통합기준가격대장(결산후)'!B9 -> 0 | E17: =IF(AND(G17=0,H17=0,I17=0,J17=0),"공시제외","공시") -> 공시제외 | F17: ="("&L17&") 콜론" -> (0) 콜론 | G17: =C17 -> 0 | I17: 0 | L17: =IF(OR(G17>0,I17>0),1,0) -> 0 | N17: (1) 지분증권 (주5)
B18: =F18 -> (0) 환매조건부채권 | C18: ='통합기준가격대장(결산후)'!B13 -> 0 | E18: =IF(AND(G18=0,H18=0,I18=0,J18=0),"공시제외","공시") -> 공시제외 | F18: ="("&L18&") 환매조건부채권" -> (0) 환매조건부채권 | G18: =C18 -> 0 | I18: 0 | L18: =IF(OR(G18>0,I18>0),L17+1,L17) -> 0 | N18: (2) 채무증권 (주6) | Q18: 5340535525
B19: =F19 -> (0) 매입어음 | C19: ='통합기준가격대장(결산후)'!B10 -> 0 | E19: =IF(AND(G19=0,H19=0,I19=0,J19=0),"공시제외","공시") -> 공시제외 | F19: ="("&L19&") 매입어음" -> (0) 매입어음 | G19: =C19 -> 0 | I19: 0 | L19: =IF(OR(G19>0,I19>0),L18+1,L18) -> 0 | N19: (3) 수익증권 (주7) | Q19: 25061088120
B20: =F20 -> (0) 전자단기사채 | E20: =IF(AND(G20=0,H20=0,I20=0,J20=0),"공시제외","공시") -> 공시제외 | F20: ="("&L20&") 전자단기사채" -> (0) 전자단기사채 | G20: =C20 -> 0 | I20: 0 | L20: =IF(OR(G20>0,I20>0),L19+1,L19) -> 0 | N20: II . 기타자산 | R20: 6341002778
B21: =F21 -> 2. 유가증권 | C21: =SUM(C22:C25) -> 136317492999 | E21: =IF(AND(G21=0,H21=0,I21=0,J21=0),"공시제외","공시") -> 공시 | F21: =L21&". 유가증권" -> 2. 유가증권 | G21: =SUM(G22:G25) -> 130948819055 | I21: 40062432995 | L21: =IF(OR(G21>0,I21>0),L16+1,L16) -> 2
B22: =F22 -> (1) 지분증권 (주석4) | C22: =SUM('통합기준가격대장(결산후)'!B14:B17)+'통합기준가격대장(결산후)'!B30 -> 106485058475 | E22: =IF(AND(G22=0,H22=0,I22=0,J22=0),"공시제외","공시") -> 공시 | F22: ="("&L22&") 지분증권 (주석"&K22&")" -> (1) 지분증권 (주석4) | G22: =C22 -> 106485058475 | I22: 28733636115 | K22: =IF(OR(G22>0,I22>0),K16+1,K16) -> 4 | L22: =IF(OR(G22>0,I22>0),1,0) -> 1
B23: =F23 -> (1) 채무증권 (주석4) | C23: =SUM('통합기준가격대장(결산후)'!B18:B24) -> 5368673944 | E23: =IF(AND(G23=0,H23=0,I23=0,J23=0),"공시제외","공시") -> 공시제외 | F23: ="("&L23&") 채무증권 (주석"&K23&")" -> (1) 채무증권 (주석4) | G23: 0 | I23: 0 | K23: =IF(OR(G23>0,I23>0),K22+1,K22) -> 4 | L23: =IF(OR(G23>0,I23>0),L22+1,L22) -> 1
B24: =F24 -> (2) 수익증권 (주석5) | C24: =SUM('통합기준가격대장(결산후)'!B25:B28) -> 24463760580 | E24: =IF(AND(G24=0,H24=0,I24=0,J24=0),"공시제외","공시") -> 공시 | F24: ="("&L24&") 수익증권 (주석"&K24&")" -> (2) 수익증권 (주석5) | G24: =C24 -> 24463760580 | I24: 11328796880 | K24: =IF(OR(G24>0,I24>0),K23+1,K23) -> 5 | L24: =IF(OR(G24>0,I24>0),L23+1,L23) -> 2
B25: (3) 기타유가증권 (주석6) | C25: 0 | E25: =IF(AND(G25=0,H25=0,I25=0,J25=0),"공시제외","공시") -> 공시제외 | F25: ="("&L25&") 기타유가증권 (주석"&K25&")" -> () 기타유가증권 (주석4) | G25: 0 | I25: 0 | K25: =K22 -> 4 | N25: 5. 기타자산 | Q25: 5473242
B26: =F26 -> 2. 파생상품자산 (주석6) | C26: =SUM(C27:C30) -> 0 | E26: =IF(AND(G26=0,H26=0,I26=0,J26=0),"공시제외","공시") -> 공시제외 | F26: =L26&". 파생상품자산 (주석"&K26&")" -> 2. 파생상품자산 (주석6) | G26: =C26 -> 0 | I26: 0 | K26: =IF(OR(G26>0,I26>0,G33>0,I33>0,G42>0,I42>0,G48>0,I48>0),K24+1,K24) -> 6 | L26: =IF(OR(G26>0,I26>0),L21+1,L21) -> 2 | N26: 자 산 총 계 | R26: 103993171846
B27: =F27 -> (0) 외환스왑 | C27: 0 | E27: =IF(AND(G27=0,H27=0,I27=0,J27=0),"공시제외","공시") -> 공시제외 | F27: ="("&L27&") 외환스왑" -> (0) 외환스왑 | G27: =C27 -> 0 | I27: 0 | L27: =IF(OR(G27>0,I27>0),1,0) -> 0 | N27: 부 채
B28: =F28 -> 외화선물 | C28: 0 | E28: =IF(AND(G28=0,H28=0,I28=0,J28=0),"공시제외","공시") -> 공시제외 | F28: 외화선물 | G28: =C28 -> 0 | I28: 0 | N28: Ⅰ. 운용부채 | R28: 10340535525
B29: =F29 -> 옵션매수 | C29: 0 | E29: =IF(AND(G29=0,H29=0,I29=0,J29=0),"공시제외","공시") -> 공시제외 | F29: 옵션매수 | G29: =C29 -> 0 | I29: 0 | N29: 1. 환매조건부매도 (주9) | Q29: 5000000000
B30: =F30 -> (0) 주식워런트증권 | C30: ='통합기준가격대장(결산후)'!B31 -> 0 | E30: =IF(AND(G30=0,H30=0,I30=0,J30=0),"공시제외","공시") -> 공시제외 | F30: ="("&L30&") 주식워런트증권" -> (0) 주식워런트증권 | G30: =C30 -> 0 | I30: 0 | L30: =IF(OR(G30>0,I30>0),L27+1,L27) -> 0 | N30: 2. 매도유가증권 (주10) | Q30: 5340535525
B31: =F31 -> Ⅱ. 기타자산 | C31: =SUM(C32:C36) -> 9675566645 | E31: =IF(AND(G31=0,H31=0,I31=0,J31=0),"공시제외","공시") -> 공시 | F31: =L31&". 기타자산" -> Ⅱ. 기타자산 | H31: =SUM(G32:G36) -> 9675566645 | J31: 128095470 | L31: =IF(OR(H10>0,J10>0),"Ⅱ","Ⅰ") -> Ⅱ
B32: =F32 -> 1. 매도유가증권미수금 | C32: =SUM('통합기준가격대장(결산후)'!B35:B38,'통합기준가격대장(결산후)'!B41:B42) -> 8837106649 | E32: =IF(AND(G32=0,H32=0,I32=0,J32=0),"공시제외","공시") -> 공시 | F32: =L32&". 매도유가증권미수금" -> 1. 매도유가증권미수금 | G32: =C32 -> 8837106649 | I32: 0 | L32: =IF(OR(G32>0,I32>0),1,0) -> 1
B33: =F33 -> 2. 정산미수금 (주석6) | C33: =SUM('통합기준가격대장(결산후)'!B43) -> 584987500 | D33: =C33-C48 -> 584987500 | E33: =IF(AND(G33=0,H33=0,I33=0,J33=0),"공시제외","공시") -> 공시 | F33: =L33&". 정산미수금 (주석"&K33&")" -> 2. 정산미수금 (주석6) | G33: =C33 -> 584987500 | I33: 0 | K33: =IF(OR(G26>0,I26>0,G33>0,I33>0,G42>0,I42>0,G48>0,I48>0),K24+1,K24) -> 6 | L33: =IF(OR(G33>0,I33>0),L32+1,L32) -> 2 | N33: 2 . 정산미지급금 (주8) | Q33: 118650000
B34: =F34 -> 3. 미수이자 | C34: =SUM('통합기준가격대장(결산후)'!B54:B64) -> 31164528 | E34: =IF(AND(G34=0,H34=0,I34=0,J34=0),"공시제외","공시") -> 공시 | F34: =L34&". 미수이자" -> 3. 미수이자 | G34: =C34 -> 31164528 | I34: 6521950 | L34: =IF(OR(G34>0,I34>0),L33+1,L33) -> 3
B35: =F35 -> 4. 미수배당금 | C35: =SUM('통합기준가격대장(결산후)'!B50:B53) -> 221852625 | E35: =IF(AND(G35=0,H35=0,I35=0,J35=0),"공시제외","공시") -> 공시 | F35: =L35&". 미수배당금" -> 4. 미수배당금 | G35: =C35 -> 221852625 | I35: 121342460 | L35: =IF(OR(G35>0,I35>0),L34+1,L34) -> 4
B36: =F36 -> 5. 기타자산 | C36: =SUM('통합기준가격대장(결산후)'!B39:B40,'통합기준가격대장(결산후)'!B47:B49,'통합기준가격대장(결산후)'!B65:B66,'통합기준가격대장(결산후)'!B44) -> 455343 | E36: =IF(AND(G36=0,H36=0,I36=0,J36=0),"공시제외","공시") -> 공시 | F36: =L36&". 기타자산" -> 5. 기타자산 | G36: =C36 -> 455343 | I36: 231060 | L36: =IF(OR(G36>0,I36>0),L35+1,L35) -> 5
B37: =F37 -> 자산 총계 | C37: =C10+C31 -> 153189360965 | D37: ='통합기준가격대장(결산후)'!B6=C37 -> TRUE | E37: 공시 | F37: 자산 총계 | H37: =SUM(H10,H31) -> 147820687021 | J37: 42528096533
B38: =F38 -> 부채 | E38: 공시 | F38: 부채
B39: =F39 -> Ⅰ. 운용부채 | C39: =SUM(C40:C45) -> 10368673944 | E39: =IF(AND(G39=0,H39=0,I39=0,J39=0),"공시제외","공시") -> 공시 | F39: =L39&". 운용부채" -> Ⅰ. 운용부채 | H39: =SUM(G40:G45) -> 5000000000 | J39: 0 | L39: Ⅰ
B40: =F40 -> 1. 환매조건부매도 (주석7) | C40: ='통합기준가격대장(결산후)'!I93 -> 5000000000 | E40: =IF(AND(G40=0,H40=0,I40=0,J40=0),"공시제외","공시") -> 공시 | F40: =L40&". 환매조건부매도 (주석"&K40&")" -> 1. 환매조건부매도 (주석7) | G40: =C40 -> 5000000000 | I40: 0 | K40: =IF(OR(G40>0,I40>0),K42+1,K42) -> 7 | L40: =IF(OR(G40>0,I40>0),1,0) -> 1 | N40: II . 이익잉여금 (주16) | R40: 2882053781
B41: =F41 -> 1. 매도유가증권 (주석7) | C41: =SUM('통합기준가격대장(결산후)'!I94:I97) -> 5368673944 | E41: =IF(AND(G41=0,H41=0,I41=0,J41=0),"공시제외","공시") -> 공시제외 | F41: =L41&". 매도유가증권 (주석"&K41&")" -> 1. 매도유가증권 (주석7) | G41: 0 | I41: 0 | K41: =IF(OR(G41>0,I41>0),K40+1,K40) -> 7 | L41: =IF(OR(G41>0,I41>0),L40+1,L40) -> 1
B42: =F42 -> 1. 파생상품부채 (주석6) | C42: =SUM(C43:C44) -> 0 | E42: =IF(AND(G42=0,H42=0,I42=0,J42=0),"공시제외","공시") -> 공시제외 | F42: =L42&". 파생상품부채 (주석"&K42&")" -> 1. 파생상품부채 (주석6) | G42: =SUM(G43:G45) -> 0 | I42: 0 | K42: =IF(OR(G26>0,I26>0,G33>0,I33>0,G42>0,I42>0,G48>0,I48>0),K24+1,K24) -> 6 | L42: =IF(OR(G42>0,I42>0),L41+1,L41) -> 1 | N42: 전기 : 8,800000좌)
B43: =F43 -> (0) 외환스왑 | C43: 0 | E43: =IF(AND(G43=0,H43=0,I43=0,J43=0),"공시제외","공시") -> 공시제외 | F43: ="("&L43&") 외환스왑" -> (0) 외환스왑 | G43: =C43 -> 0 | I43: 0 | L43: =IF(OR(G43>0,I43>0),1,0) -> 0 | N43: (좌당 기준 가격 : 당기 : 16,270.64원
B44: =F44 -> 외화선물 | C44: 0 | E44: =IF(AND(G44=0,H44=0,I44=0,J44=0),"공시제외","공시") -> 공시제외 | F44: 외화선물 | G44: =C44 -> 0 | I44: 0 | N44: 전기 : 10,327.51원)
B45: =F45 -> 옵션매도 | C45: ='통합기준가격대장(결산후)'!I98 -> 0 | E45: =IF(AND(G45=0,H45=0,I45=0,J45=0),"공시제외","공시") -> 공시제외 | F45: 옵션매도 | G45: =C45 -> 0 | I45: 0
B46: =F46 -> Ⅱ. 기타부채 | C46: =SUM(C47:C54) -> 5451730120 | E46: =IF(AND(G46=0,H46=0,I46=0,J46=0),"공시제외","공시") -> 공시 | F46: =L46&". 기타부채" -> Ⅱ. 기타부채 | H46: =SUM(G47:G54) -> 5451730120 | J46: 95714220 | L46: =IF(OR(H39>0,J39>0),"Ⅱ","Ⅰ") -> Ⅱ
B47: =F47 -> 1. 매수유가증권미지급금 | C47: =SUM('통합기준가격대장(결산후)'!I99:I102,'통합기준가격대장(결산후)'!I105) -> 4547096890 | E47: =IF(AND(G47=0,H47=0,I47=0,J47=0),"공시제외","공시") -> 공시 | F47: =L47&". 매수유가증권미지급금" -> 1. 매수유가증권미지급금 | G47: =C47 -> 4547096890 | I47: 0 | L47: =IF(OR(G47>0,I47>0),1,0) -> 1
B48: =F48 -> 2. 정산미지급금 (주석6) | C48: =SUM('통합기준가격대장(결산후)'!I106) -> 0 | E48: =IF(AND(G48=0,H48=0,I48=0,J48=0),"공시제외","공시") -> 공시 | F48: =L48&". 정산미지급금 (주석"&K48&")" -> 2. 정산미지급금 (주석6) | G48: =C48 -> 0 | I48: 91325000 | K48: =IF(OR(G26>0,I26>0,G33>0,I33>0,G42>0,I42>0,G48>0,I48>0),K24+1,K24) -> 6 | L48: =IF(OR(G48>0,I48>0),L47+1,L47) -> 2
B49: =F49 -> 2. 해지미지급금 | C49: ='통합기준가격대장(결산후)'!I114 -> 0 | E49: =IF(AND(G49=0,H49=0,I49=0,J49=0),"공시제외","공시") -> 공시제외 | F49: =L49&". 해지미지급금" -> 2. 해지미지급금 | G49: =C49 -> 0 | I49: 0 | L49: =IF(OR(G49>0,I49>0),L48+1,L48) -> 2
B50: =F50 -> 3. 보수미지급금 (주석8,13) | C50: =SUM('통합기준가격대장(결산후)'!I140:I143) -> 5525638 | E50: =IF(AND(G50=0,H50=0,I50=0,J50=0),"공시제외","공시") -> 공시 | F50: =L50&". 보수미지급금 (주석"&K50&","&K117+1&")" -> 3. 보수미지급금 (주석8,13) | G50: =C50 -> 5525638 | I50: 2264192 | K50: =IF(OR(G50>0,I50>0),K41+1,K41) -> 8 | L50: =IF(OR(G50>0,I50>0),L49+1,L49) -> 3
B51: =F51 -> 3. 미지급후원기금 (주석8) | C51: =SUM('통합기준가격대장(결산후)'!I145:I146) -> 0 | E51: =IF(AND(G51=0,H51=0,I51=0,J51=0),"공시제외","공시") -> 공시제외 | F51: =L51&". 미지급후원기금 (주석"&K51&")" -> 3. 미지급후원기금 (주석8) | G51: =C51 -> 0 | I51: 0 | K51: =IF(OR(G51>0,I51>0),K50+1,K50) -> 8 | L51: =IF(OR(G51>0,I51>0),L50+1,L50) -> 3
B52: =F52 -> 3. 미지급이익분배금 (주석8) | C52: ='통합기준가격대장(결산후)'!I116 -> 0 | E52: =IF(AND(G52=0,H52=0,I52=0,J52=0),"공시제외","공시") -> 공시제외 | F52: =L52&". 미지급이익분배금 (주석"&K52&")" -> 3. 미지급이익분배금 (주석8) | G52: =C52 -> 0 | I52: 0 | K52: =IF(OR(G52>0,I52>0),K51+1,K51) -> 8 | L52: =IF(OR(G52>0,I52>0),L51+1,L51) -> 3
B53: =F53 -> 4. 미지급분배금 (주석8) | C53: ='통합기준가격대장(결산후)'!I117 -> 870000000 | E53: =IF(AND(G53=0,H53=0,I53=0,J53=0),"공시제외","공시") -> 공시 | F53: =L53&". 미지급분배금 (주석"&K53&")" -> 4. 미지급분배금 (주석8) | G53: =C53 -> 870000000 | I53: 0 | K53: =K52 -> 8 | L53: =IF(OR(G53>0,I53>0),L52+1,L52) -> 4
B54: =F54 -> 5. 기타부채 | C54: =SUM('통합기준가격대장(결산후)'!I103:I104,'통합기준가격대장(결산후)'!I107,'통합기준가격대장(결산후)'!I111:I113,'통합기준가격대장(결산후)'!I115,'통합기준가격대장(결산후)'!I120:I139,'통합기준가격대장(결산후)'!I144,'통합기준가격대장(결산후)'!I118,'통합기준가격대장(결산후)'!I119) -> 29107592 | E54: =IF(AND(G54=0,H54=0,I54=0,J54=0),"공시제외","공시") -> 공시 | F54: =L54&". 기타부채" -> 5. 기타부채 | G54: =C54 -> 29107592 | I54: 2125028 | L54: =IF(OR(G54>0,I54>0),L53+1,L53) -> 5
B55: =F55 -> 부채 총계 | C55: =C46+C39 -> 15820404064 | D55: ='통합기준가격대장(결산후)'!I92=C55 -> TRUE | E55: 공시 | F55: 부채 총계 | H55: =H46+H39 -> 10451730120 | J55: 95714220 | N55: 당기 | O55: 전기
B56: =F56 -> 자본 | E56: 공시 | F56: 자본 | M56: 운용 미지급 | N56: ='통합기준가격대장(결산후)'!I141 -> 251130 | O56: 102877
B57: =F57 -> Ⅰ. 원본 (주석9) | C57: ='통합기준가격대장(결산후)'!I148 -> 29000000000 | E57: 공시 | F57: ="Ⅰ. 원본 (주석"&K57&")" -> Ⅰ. 원본 (주석9) | H57: =C57 -> 29000000000 | J57: 31000000000 | K57: =K53+1 -> 9 | M57: 판매 미지급 | N57: ='통합기준가격대장(결산후)'!I142 -> 251130 | O57: 102877
B58: =F58 -> Ⅱ. 이익잉여금 | C58: =SUM('통합기준가격대장(결산후)'!I149:I151) -> 108368956901 | E58: 공시 | F58: ="Ⅱ. "&L58 -> Ⅱ. 이익잉여금 | H58: =C58 -> 108368956901 | J58: 11432382313 | L58: =IF(AND(H58<0,J58<0),"결손금",IF(AND(H58>=0,J58>=0),"이익잉여금","이익잉여금(결손금)")) -> 이익잉여금 | M58: 수탁 미지급 | N58: ='통합기준가격대장(결산후)'!I140 -> 2511689 | O58: 1029219
B59: =C57/10000 -> 2900000 | E59: 공시 | F59: ="(총좌수 당기 : "&TEXT(B59,"#,###")&"좌" -> (총좌수 당기 : 2,900,000좌 | M59: 사무관리 미지급 | N59: ='통합기준가격대장(결산후)'!I143 -> 2511689 | O59: 1029219
B60: =J57/10000 -> 3100000 | E60: 공시 | F60: =" 전기 : "&TEXT(J57/10000,"#,###")&"좌)" -> 전기 : 3,100,000좌)
B61: =F61 -> (좌당 기준가격 | E61: 공시 | F61: (좌당 기준가격 | M61: 보수미지급금검증 | N61: =SUM(N56:N59)=G50 -> TRUE | O61: =SUM(O56:O59)=I50 -> TRUE
B62: =H68 -> 47368.606 | E62: 공시 | F62: ="당기 : "&TEXT(B62,"#,###.00")&"원" -> 당기 : 47,368.61원
B63: =J68 -> 13687.865 | E63: 공시 | F63: ="전기 : "&TEXT(B63,"#,###.00")&"원)" -> 전기 : 13,687.87원)
B64: =F64 -> (주석11) | E64: 공시 | F64: ="(주석"&K64&")" -> (주석11) | K64: =K57+2 -> 11
B65: =F65 -> 자본 총계 | C65: =SUM(C57:C63) -> 137368956901 | D65: ='통합기준가격대장(결산후)'!I147=C65 -> TRUE | E65: 공시 | F65: 자본 총계 | H65: =SUM(H57:H63) -> 137368956901 | J65: 42432382313
B66: =F66 -> 부채 및 자본 총계 | C66: =C55+C65 -> 153189360965 | E66: 공시 | F66: 부채 및 자본 총계 | H66: =H65+H55 -> 147820687021 | J66: 42528096533
B67: 차대검증 | C67: =C66=C37 -> TRUE | E67: .
E68: . | F68: 좌당 기준가격 | H68: =(H65/B59) -> 47368.606 | J68: =J65/(J57/10000) -> 13687.865
E69: . | F69: 차대검증 | G69: =H37=H66 -> TRUE | I69: =J37=J66 -> TRUE
E70: . | F70: 기지급분배금 | G70: =SUM('통합기준가격대장(결산후)'!H158:H159) -> 870000000 | I70: =J37-J66 -> 0
E71: .
E72: . | J72: 전기보고서숫자 넣어야함
E73: . | F73: <공고용 IS> | J73: 합계수식걸려있음
B74: 과목 | C74: 제 X (당)기 | E74: . | F74: 과목 | G74: 제 X (당)기 | I74: 제 X (전)기 | K74: 주석 번호(자동) | L74: 과목순서(자동)
B75: =F75 -> Ⅰ. 운용수익(손실) | C75: =C76+C80+C94 -> 88277940651 | E75: =IF(AND(G75=0,H75=0,I75=0,J75=0),"공시제외","공시") -> 공시 | F75: ="Ⅰ. "&L75 -> Ⅰ. 운용수익(손실) | H75: =C75 -> 88277940651 | J75: -7318285434 | L75: =IF(AND(H75<0,J75<0),"운용손실",IF(AND(H75>0,J75>0),"운용수익","운용수익(손실)")) -> 운용수익(손실)
B76: =F76 -> 1. 투자수익 | C76: =SUM(C77:C79) -> 1394262129 | E76: =IF(AND(G76=0,H76=0,I76=0,J76=0),"공시제외","공시") -> 공시 | F76: 1. 투자수익 | G76: =SUM(G77:G79) -> 1394262129 | I76: 929730733
B77: =F77 -> (1) 이자수익 | C77: =SUM('통합기준가격대장(결산후)'!G344:G354)+SUM('통합기준가격대장(결산후)'!G328:G332) -> 93912875 | E77: =IF(AND(G77=0,H77=0,I77=0,J77=0),"공시제외","공시") -> 공시 | F77: ="("&L77&") 이자수익" -> (1) 이자수익 | G77: =C77 -> 93912875 | I77: 120117662 | L77: =IF(OR(G77>0,I77>0),1,0) -> 1
B78: =F78 -> (2) 배당수익 | C78: =SUM('통합기준가격대장(결산후)'!G333:G343) -> 1288689005 | E78: =IF(AND(G78=0,H78=0,I78=0,J78=0),"공시제외","공시") -> 공시 | F78: ="("&L78&") 배당수익" -> (2) 배당수익 | G78: =C78 -> 1288689005 | I78: 793453895 | L78: =IF(OR(G78>0,I78>0),L77+1,L77) -> 2
B79: =F79 -> (3) 기타수익 | C79: =SUM('통합기준가격대장(결산후)'!G355:G366) -> 11660249 | D79: =G82-G96 -> 33267189096 | E79: =IF(AND(G79=0,H79=0,I79=0,J79=0),"공시제외","공시") -> 공시 | F79: ="("&L79&") 기타수익" -> (3) 기타수익 | G79: =C79 -> 11660249 | I79: 16159176 | L79: =IF(OR(G79>0,I79>0),L78+1,L78) -> 3
B80: =F80 -> 2. 매매이익과 평가이익 | C80: =SUM(C81:C93) -> 166074002619 | E80: =IF(AND(G80=0,H80=0,I80=0,J80=0),"공시제외","공시") -> 공시 | F80: 2. 매매이익과 평가이익 | G80: =SUM(G81:G93) -> 166074002619 | I80: 51942504580
B81: =F81 -> (1) 지분증권매매이익 | C81: =SUBTOTAL(9,'통합기준가격대장(결산후)'!G264:G270) -> 561112490 | E81: =IF(AND(G81=0,H81=0,I81=0,J81=0),"공시제외","공시") -> 공시 | F81: ="("&L81&") 지분증권매매이익" -> (1) 지분증권매매이익 | G81: =C81 -> 561112490 | I81: 1376119625 | L81: =IF(OR(G81>0,I81>0),1,0) -> 1
B82: =F82 -> (2) 지분증권평가이익 (주석4) | C82: =SUM('통합기준가격대장(결산후)'!G306:G309)+'통합기준가격대장(결산후)'!G324-2 -> 33658782894 | E82: =IF(AND(G82=0,H82=0,I82=0,J82=0),"공시제외","공시") -> 공시 | F82: ="("&L82&") 지분증권평가이익 (주석"&K82&")" -> (2) 지분증권평가이익 (주석4) | G82: =C82 -> 33658782894 | I82: 2696263117 | K82: =K22 -> 4 | L82: =IF(OR(G82>0,I82>0),L81+1,L81) -> 2
B83: =F83 -> (2) 채무증권매매이익 | C83: =SUM('통합기준가격대장(결산후)'!G271,'통합기준가격대장(결산후)'!G273,) -> 0 | E83: =IF(AND(G83=0,H83=0,I83=0,J83=0),"공시제외","공시") -> 공시제외 | F83: ="("&L83&") 채무증권매매이익" -> (2) 채무증권매매이익 | G83: =C83 -> 0 | I83: 0 | L83: =IF(OR(G83>0,I83>0),L82+1,L82) -> 2
B84: =F84 -> (2) 채무증권평가이익 (주석4) | C84: =SUM('통합기준가격대장(결산후)'!G310,'통합기준가격대장(결산후)'!G313)-'통합기준가격대장(결산후)'!G310 -> 0 | E84: =IF(AND(G84=0,H84=0,I84=0,J84=0),"공시제외","공시") -> 공시제외 | F84: ="("&L84&") 채무증권평가이익 (주석"&K84&")" -> (2) 채무증권평가이익 (주석4) | G84: =C84 -> 0 | I84: 0 | K84: =K23 -> 4 | L84: =IF(OR(G84>0,I84>0),L83+1,L83) -> 2
B85: =F85 -> (3) 수익증권매매이익 | C85: =SUM('통합기준가격대장(결산후)'!G276:G277,'통합기준가격대장(결산후)'!G279:G283) -> 6659502732 | D85: 수익증권 평가손익을 네팅 | E85: =IF(AND(G85=0,H85=0,I85=0,J85=0),"공시제외","공시") -> 공시 | F85: ="("&L85&") 수익증권매매이익" -> (3) 수익증권매매이익 | G85: =C85 -> 6659502732 | I85: 1202332293 | L85: =IF(OR(G85>0,I85>0),L84+1,L84) -> 3
B86: =F86 -> (4) 수익증권평가이익 (주석5) | C86: =SUM('통합기준가격대장(결산후)'!G315:G321) -> 1046317003 | E86: =IF(AND(G86=0,H86=0,I86=0,J86=0),"공시제외","공시") -> 공시 | F86: ="("&L86&") 수익증권평가이익 (주석"&K86&")" -> (4) 수익증권평가이익 (주석5) | G86: =C86 -> 1046317003 | I86: 0 | K86: =K24 -> 5 | L86: =IF(OR(G86>0,I86>0),L85+1,L85) -> 4
B87: =F87 -> (5) 파생상품매매이익 | C87: =SUM('통합기준가격대장(결산후)'!G284:G304) -> 124148287500 | E87: =IF(AND(G87=0,H87=0,I87=0,J87=0),"공시제외","공시") -> 공시 | F87: ="("&L87&") 파생상품매매이익" -> (5) 파생상품매매이익 | G87: =C87 -> 124148287500 | I87: 46667237500 | L87: =IF(OR(G87>0,I87>0),L86+1,L86) -> 5
B88: =F88 -> (5) 파생상품평가이익 (주석6) | C88: =SUM('통합기준가격대장(결산후)'!G322:G326)-'통합기준가격대장(결산후)'!G324 -> 0 | E88: =IF(AND(G88=0,H88=0,I88=0,J88=0),"공시제외","공시") -> 공시제외 | F88: ="("&L88&") 파생상품평가이익 (주석"&K88&")" -> (5) 파생상품평가이익 (주석6) | G88: =C88 -> 0 | I88: 0 | K88: =K26 -> 6 | L88: =IF(OR(G88>0,I88>0),L87+1,L87) -> 5
B89: =F89 -> (6) 매도유가증권매매이익 | C89: =SUM('통합기준가격대장(결산후)'!G272,'통합기준가격대장(결산후)'!G278,'통합기준가격대장(결산후)'!G329) -> 0 | E89: =IF(AND(G89=0,H89=0,I89=0,J89=0),"공시제외","공시") -> 공시 | F89: ="("&L89&") 매도유가증권매매이익" -> (6) 매도유가증권매매이익 | G89: =C89 -> 0 | I89: 552045 | L89: =IF(OR(G89>0,I89>0),L88+1,L88) -> 6
B90: =F90 -> (6) 매도유가증권평가이익 | C90: =SUM('통합기준가격대장(결산후)'!G311:G312,'통합기준가격대장(결산후)'!G317) -> 0 | E90: =IF(AND(G90=0,H90=0,I90=0,J90=0),"공시제외","공시") -> 공시제외 | F90: ="("&L90&") 매도유가증권평가이익" -> (6) 매도유가증권평가이익 | G90: =C90 -> 0 | I90: 0 | L90: =IF(OR(G90>0,I90>0),L89+1,L89) -> 6
B91: =F91 -> (6) 외환거래이익 | C91: ='통합기준가격대장(결산후)'!G305 -> 0 | E91: =IF(AND(G91=0,H91=0,I91=0,J91=0),"공시제외","공시") -> 공시제외 | F91: ="("&L91&") 외환거래이익" -> (6) 외환거래이익 | G91: =C91 -> 0 | I91: 0 | L91: =IF(OR(G91>0,I91>0),L90+1,L90) -> 6
B92: =F92 -> (6) 외화환산이익 | C92: ='통합기준가격대장(결산후)'!G327 -> 0 | E92: =IF(AND(G92=0,H92=0,I92=0,J92=0),"공시제외","공시") -> 공시제외 | F92: ="("&L92&") 외화환산이익" -> (6) 외화환산이익 | G92: =C92 -> 0 | I92: 0 | L92: =IF(OR(G92>0,I92>0),L91+1,L91) -> 6
B93: =F93 -> (6) 기타매매이익 | C93: =SUM('통합기준가격대장(결산후)'!G274:G275,'통합기준가격대장(결산후)'!G314,'통합기준가격대장(결산후)'!G331:G332) -> 0 | E93: =IF(AND(G93=0,H93=0,I93=0,J93=0),"공시제외","공시") -> 공시제외 | F93: ="("&L93&") 기타매매이익" -> (6) 기타매매이익 | G93: =C93 -> 0 | I93: 0 | L93: =IF(OR(G93>0,I93>0),L92+1,L92) -> 6
B94: =F94 -> 3. 매매손실과 평가손실 | C94: =-SUM(C95:C107) -> -79190324097 | E94: =IF(AND(G94=0,H94=0,I94=0,J94=0),"공시제외","공시") -> 공시 | F94: 3. 매매손실과 평가손실 | G94: =-SUM(G95:G107) -> -79190324097 | I94: -60190520747
B95: =F95 -> (1) 지분증권매매손실 | C95: =SUM('통합기준가격대장(결산후)'!D161:D163) -> 44085416 | E95: =IF(AND(G95=0,H95=0,I95=0,J95=0),"공시제외","공시") -> 공시 | F95: ="("&L95&") 지분증권매매손실" -> (1) 지분증권매매손실 | G95: =C95 -> 44085416 | I95: 784307652 | L95: =IF(OR(G95>0,I95>0),1,0) -> 1
B96: =F96 -> (2) 지분증권평가손실 (주석4) | C96: =SUM('통합기준가격대장(결산후)'!D200:D202) -> 391593798 | E96: =IF(AND(G96=0,H96=0,I96=0,J96=0),"공시제외","공시") -> 공시 | F96: ="("&L96&") 지분증권평가손실 (주석"&K96&")" -> (2) 지분증권평가손실 (주석4) | G96: =C96 -> 391593798 | I96: 5927195035 | K96: =K22 -> 4 | L96: =IF(OR(G96>0,I96>0),L95+1,L95) -> 2
B97: =F97 -> (2) 채무증권매매손실 | C97: =SUM('통합기준가격대장(결산후)'!D164,'통합기준가격대장(결산후)'!D167,'통합기준가격대장(결산후)'!D223,'통합기준가격대장(결산후)'!D225) -> 0 | E97: =IF(AND(G97=0,H97=0,I97=0,J97=0),"공시제외","공시") -> 공시제외 | F97: ="("&L97&") 채무증권매매손실" -> (2) 채무증권매매손실 | G97: =C97 -> 0 | I97: 0 | L97: =IF(OR(G97>0,I97>0),L96+1,L96) -> 2
B98: =F98 -> (2) 채무증권평가손실 (주석4) | C98: =SUM('통합기준가격대장(결산후)'!D203,'통합기준가격대장(결산후)'!D206) -> 0 | E98: =IF(AND(G98=0,H98=0,I98=0,J98=0),"공시제외","공시") -> 공시제외 | F98: ="("&L98&") 채무증권평가손실 (주석"&K98&")" -> (2) 채무증권평가손실 (주석4) | G98: =C98 -> 0 | I98: 0 | K98: =K23 -> 4 | L98: =IF(OR(G98>0,I98>0),L97+1,L97) -> 2
B99: =F99 -> (3) 수익증권매매손실 | C99: =SUM('통합기준가격대장(결산후)'!D172:D173,'통합기준가격대장(결산후)'!D175:D179) -> 969019883 | E99: =IF(AND(G99=0,H99=0,I99=0,J99=0),"공시제외","공시") -> 공시 | F99: ="("&L99&") 수익증권매매손실" -> (3) 수익증권매매손실 | G99: =C99 -> 969019883 | I99: 1777108544 | L99: =IF(OR(G99>0,I99>0),L98+1,L98) -> 3
B100: =F100 -> (4) 수익증권평가손실 (주석5) | C100: =SUM('통합기준가격대장(결산후)'!D208:D216)-D86-'통합기준가격대장(결산후)'!D211-'통합기준가격대장(결산후)'!H210 -> 0 | D100: =SUM('통합기준가격대장(결산후)'!G315:G321) -> 1046317003 | E100: =IF(AND(G100=0,H100=0,I100=0,J100=0),"공시제외","공시") -> 공시 | F100: ="("&L100&") 수익증권평가손실 (주석"&K100&")" -> (4) 수익증권평가손실 (주석5) | G100: =C100 -> 0 | I100: 353434840 | K100: =K24 -> 5 | L100: =IF(OR(G100>0,I100>0),L99+1,L99) -> 4
B101: =F101 -> (5) 파생상품매매손실 | C101: =SUM('통합기준가격대장(결산후)'!D180:D198) -> 77785625000 | E101: =IF(AND(G101=0,H101=0,I101=0,J101=0),"공시제외","공시") -> 공시 | F101: ="("&L101&") 파생상품매매손실" -> (5) 파생상품매매손실 | G101: =C101 -> 77785625000 | I101: 51310325000 | L101: =IF(OR(G101>0,I101>0),L100+1,L100) -> 5
B102: =F102 -> (5) 파생상품평가손실 (주석6) | C102: =SUM('통합기준가격대장(결산후)'!D217:D220) -> 0 | E102: =IF(AND(G102=0,H102=0,I102=0,J102=0),"공시제외","공시") -> 공시제외 | F102: ="("&L102&") 파생상품평가손실 (주석"&K102&")" -> (5) 파생상품평가손실 (주석6) | G102: =C102 -> 0 | I102: 0 | K102: =K26 -> 6 | L102: =IF(OR(G102>0,I102>0),L101+1,L101) -> 5
...

Sheet C2_자산부채평가
A1: ='C1_정산표'!B1 -> 한빛코스피레버리지증권상장지수투자신탁(주식-파생형)
A2: ='C1_정산표'!B2 -> 45657 | G2: Prepared by : | H2: ='C1_정산표'!H2 -> SJ
A3: 자산부채확인 | G3: Reviewed by :
A6: 절차 : 자산부채금액이 정산표와 일치하고, 자산수탁조회서와 일치하는지 확인
A8: 결과 : 자산부채명세와 일치함을 확인함
A12: 작성여부 | C12: 구 분 | D12: B/S | E12: 명세서 | F12: 차액
A13: O | C13: 예금 | D13: ='C1_정산표'!C12 -> 7196301321 | E13: =F41 -> 7196301321 | F13: =D13-E13 -> 0 | G13: =SUM(F13:F14) -> 0
A14: O | C14: 예치금 | D14: ='C1_정산표'!C13 -> 0 | F14: =D14-E14 -> 0
A15: O | C15: 위탁증거금 | D15: ='C1_정산표'!C15 -> 0 | E15: =D54 -> 0 | F15: =D15-E15 -> 0 | G15: =SUM(F15:F16) -> 0
A16: O | C16: 현금담보증거금 | D16: 0 | E16: =E60 -> 0 | F16: =D16-E16 -> 0
A17: O | C17: 콜론 | D17: ='C1_정산표'!C17 -> 0 | E17: =E66 -> 0 | F17: =D17-E17 -> 0
A18: O | C18: REPO | D18: ='C1_정산표'!C18 -> 0 | E18: =F74 -> 0 | F18: =D18-E18 -> 0
A19: O | C19: 매입어음 | D19: ='C1_정산표'!G19 -> 0 | E19: =F80 -> 0 | F19: =D19-E19 -> 0
A20: O | C20: 전자단기사채 | D20: ='C1_정산표'!G20 -> 0 | E20: =F86 -> 0 | F20: =D20-E20 -> 0
A21: O | C21: 국채 | D21: ='통합기준가격대장(결산후)'!B18 -> 5368673944 | E21: =SUMIF($E$91:$E$94,C21,$J$91:$J$94) -> 5368673944 | F21: =D21-E21 -> 0 | G21: =SUM(F21:F24) -> 0
A22: O | C22: 특수채 | D22: ='통합기준가격대장(결산후)'!B20 -> 0 | E22: =SUMIF($E$91:$E$94,C22,$J$91:$J$94) -> 0 | F22: =D22-E22 -> 0
A23: O | C23: 통안채 | D23: ='통합기준가격대장(결산후)'!B21 -> 0 | E23: =SUMIF($E$91:$E$94,C23,$J$91:$J$94) -> 0 | F23: =D23-E23 -> 0
A24: O | C24: 회사채 | D24: ='통합기준가격대장(결산후)'!B23 -> 0 | E24: =SUMIF($E$91:$E$94,C24,$J$91:$J$94) -> 0 | F24: =D24-E24 -> 0
A25: O | C25: 상장주식 | D25: ='통합기준가격대장(결산후)'!B14 -> 106485058475 | E25: =F309 -> 106485058475 | F25: =D25-E25 -> 0 | G25: =SUM(F25:F26) -> 0
A26: O | C26: 코스닥주식 | D26: ='통합기준가격대장(결산후)'!B15+'통합기준가격대장(결산후)'!B16 -> 0 | E26: =F356 -> 0 | F26: =D26-E26 -> 0
A27: O | C27: 수익증권 | D27: ='C1_정산표'!C24 -> 24463760580 | E27: =F362 -> 24463760580 | F27: =D27-E27 -> 0
A28: O | C28: 선물미수입금 | D28: ='C1_정산표'!G33 -> 584987500 | E28: =I373 -> 584987500 | F28: =D28-E28 -> 0
A29: O | C29: 선물미지급금 | D29: ='C1_정산표'!G48 -> 0 | E29: =I383 -> 0 | F29: =D29-E29 -> 0
A30: O | C30: 옵션매수 | D30: ='C1_정산표'!G29 -> 0 | E30: =E390 -> 0 | F30: =D30-E30 -> 0
A31: O | C31: 옵션매도 | D31: ='C1_정산표'!G45 -> 0 | E31: =E428 -> 0 | F31: =D31-E31 -> 0
A32: O | C32: 매도유가증권 | D32: ='C1_정산표'!G41 -> 0 | E32: =E434 -> 0 | F32: =D32-E32 -> 0
A33: O | C33: 매도REPO | D33: ='C1_정산표'!G40 -> 5000000000 | E33: =E441 -> 5000000000 | F33: =D33-E33 -> 0
C34: 합 계 | D34: =SUM(D13:D33) -> 149098781820 | E34: =SUM(E13:E33) -> 149098781820 | F34: =SUM(F13:F33) -> 0
A36: =IF($G$13=0,"O","X") -> O | C36: 1. 예금
A37: =IF($G$13=0,"O","X") -> O | C37: 종목명 | D37: 발행률 | E37: 수량 | F37: 취득원가 | G37: 장부가평가액 | H37: 시가평가금액
A38: =IF($G$13=0,"O","X") -> O | C38: [KRW] 예금 | D38: =국내유동명세!E3 -> 2.07 | E38: =SUMIF(국내유동명세!$C:$C,'C2_자산부채평가'!C38,국내유동명세!$K:$K) -> 7196301321 | F38: =SUMIF(국내유동명세!$C:$C,'C2_자산부채평가'!$C38,국내유동명세!$Q:$Q) -> 7196301321 | G38: =SUMIF(국내유동명세!$C:$C,'C2_자산부채평가'!$C38,국내유동명세!$R:$R) -> 7202532493 | H38: =SUMIF(국내유동명세!$C:$C,'C2_자산부채평가'!$C38,국내유동명세!$S:$S) -> 7202532493
A39: =IF($G$13=0,"O","X") -> O
A40: =IF($G$13=0,"O","X") -> O
A41: =IF($G$13=0,"O","X") -> O | F41: =SUM(F38:F40) -> 7196301321
A43: =IF($G$15=0,"O","X") -> O | C43: 1-1. 위탁증거금
A44: =IF($G$15=0,"O","X") -> O | C44: 매매처명 | D44: 원화증거금
A45: =IF($G$15=0,"O","X") -> O | C45: =국내유동명세!C5 -> 0 | D45: =국내유동명세!K5 -> 0
A46: =IF($G$15=0,"O","X") -> O | C46: =국내유동명세!C5 -> 0 | D46: =국내유동명세!K5 -> 0
A47: =IF($G$15=0,"O","X") -> O | C47: =국내유동명세!C6 -> 0 | D47: =국내유동명세!K6 -> 0
A48: =IF($G$15=0,"O","X") -> O | C48: =국내유동명세!C7 -> 0 | D48: =국내유동명세!K7 -> 0
A49: =IF($G$15=0,"O","X") -> O | C49: =국내유동명세!C8 -> 0 | D49: =국내유동명세!K8 -> 0
A50: =IF($G$15=0,"O","X") -> O | C50: =국내유동명세!C9 -> 0 | D50: =국내유동명세!K9 -> 0
A51: =IF($G$15=0,"O","X") -> O | C51: =외화위탁증거금!F9 -> 0 | D51: =외화위탁증거금!H9 -> 0
A52: =IF($G$15=0,"O","X") -> O | C52: =외화위탁증거금!F10 -> 0 | D52: =외화위탁증거금!H10 -> 0
A53: =IF($G$15=0,"O","X") -> O
A54: =IF($G$15=0,"O","X") -> O | D54: =SUM(D45:D53) -> 0
A56: =IF($G$15=0,"O","X") -> O | C56: 1-2. 현금담보증거금
A57: =IF($G$15=0,"O","X") -> O | C57: 종목명 | D57: 발행률 | E57: 수량
A58: =IF($G$15=0,"O","X") -> O
A59: =IF($G$15=0,"O","X") -> O
A60: =IF($G$15=0,"O","X") -> O | E60: =SUM(E58:E59) -> 0
A62: =IF($F$17=0,"O","X") -> O | C62: 2. 콜론
A63: =IF($F$17=0,"O","X") -> O | C63: 종목명 | D63: 발행률 | E63: 수량 | F63: 장부가액 | G63: 만기일
A64: =IF($F$17=0,"O","X") -> O
A65: =IF($F$17=0,"O","X") -> O
A66: =IF($F$17=0,"O","X") -> O | E66: =SUM(E64:E65) -> 0
A68: =IF($F$18=0,"O","X") -> O | C68: =IF(E66=0,MID(C62,1,1),MID(C62,1,1)+1)&". REPO(매수)" -> 2. REPO(매수)
A69: =IF($F$18=0,"O","X") -> O | C69: 종목명 | D69: 발행률 | E69: 수량 | F69: 장부가액 | G69: 만기일 | H69: 중개기관
A70: =IF($F$18=0,"O","X") -> O
A71: =IF($F$18=0,"O","X") -> O
A72: =IF($F$18=0,"O","X") -> O
A73: =IF($F$18=0,"O","X") -> O
A74: =IF($F$18=0,"O","X") -> O | F74: =SUM(F70:F73) -> 0
A76: =IF($F$19=0,"O","X") -> O | C76: =IF(F74=0,MID(C68,1,1),MID(C68,1,1)+1)&". 매입어음" -> 2. 매입어음
A77: =IF($F$19=0,"O","X") -> O | C77: 종목명 | D77: 발행률 | E77: 수량 | F77: 장부가액 | G77: 만기일
A78: =IF($F$19=0,"O","X") -> O
A79: =IF($F$19=0,"O","X") -> O
A80: =IF($F$19=0,"O","X") -> O | F80: =SUM(F78:F79) -> 0
A82: =IF($F$20=0,"O","X") -> O | C82: =IF(F80=0,MID(C76,1,1),MID(C76,1,1)+1)&". 전자단기사채" -> 2. 전자단기사채
A83: =IF($F$20=0,"O","X") -> O | C83: 종목명 | D83: 발행률 | E83: 수량 | F83: 장부가액 | G83: 만기일 | H83: 중개기관
A84: =IF($F$20=0,"O","X") -> O
A85: =IF($F$20=0,"O","X") -> O
A86: =IF($F$20=0,"O","X") -> O | F86: =SUM(F84:F85) -> 0
A89: =IF($G$21=0,"O","X") -> O | C89: =IF(F74=0,MID(C82,1,1),MID(C82,1,1)+1)&". 채권" -> 2. 채권
A90: =IF($G$21=0,"O","X") -> O | C90: 종목명 | D90: 종류 | E90: 코스콤대분류 | F90: 발행률 | G90: 만기일 | H90: 액면 | I90: 결산전장부금액 | J90: 결산후장부금액
A91: =IF($G$21=0,"O","X") -> O | C91: =채권명세!C2 -> 국고채권01125-3909(19-6) | D91: =채권명세!F2 -> 이표(확정) | E91: =채권명세!G2 -> 국채 | F91: =채권명세!H2/100 -> 0.01125 | G91: =채권명세!Q2 -> 20390910 | H91: =채권명세!N2 -> 7100000000 | I91: =채권명세!T2-채권명세!AA2-채권명세!AE2 -> 5366908689 | J91: =채권명세!U2-채권명세!AA2-채권명세!AE2 -> 5368673944
A92: =IF($G$21=0,"O","X") -> O
A93: =IF($G$21=0,"O","X") -> O
A94: =IF($G$21=0,"O","X") -> O
A95: =IF($G$21=0,"O","X") -> O | J95: =SUM(J91:J94) -> 5368673944
A97: =IF($G$25=0,"O","X") -> O | C97: =IF(J95=0,MID(C89,1,1),MID(C89,1,1)+1)&". 거래소주식, 코스닥주식" -> 3. 거래소주식, 코스닥주식
A99: =IF($F$25=0,"O","X") -> O | C99: (1) 거래소주식
A100: =IF($F$25=0,"O","X") -> O | C100: 종목명 | D100: 수량 | E100: 결산전장부가액 | F100: 결산후장부가액
A101: =IF($F$25=0,"O","X") -> O | C101: =국내주식명세!B3 -> 종목002 | D101: =국내주식명세!D3 -> 5880 | E101: =국내주식명세!E3 -> 91764961 | F101: =국내주식명세!G3 -> 134652000
A102: =IF($F$25=0,"O","X") -> O | C102: =국내주식명세!B4 -> 종목003 | D102: =국내주식명세!D4 -> 210 | E102: =국내주식명세!E4 -> 63483000 | F102: =국내주식명세!G4 -> 88305000
A103: =IF($F$25=0,"O","X") -> O | C103: =국내주식명세!B5 -> 종목004 | D103: =국내주식명세!D5 -> 210 | E103: =국내주식명세!E5 -> 204090000 | F103: =국내주식명세!G5 -> 258510000
A104: =IF($F$25=0,"O","X") -> O | C104: =국내주식명세!B6 -> 종목005 | D104: =국내주식명세!D6 -> 35 | E104: =국내주식명세!E6 -> 28063230 | F104: =국내주식명세!G6 -> 26670000
A105: =IF($F$25=0,"O","X") -> O | C105: =국내주식명세!B7 -> 종목006 | D105: =국내주식명세!D7 -> 1855 | E105: =국내주식명세!E7 -> 311085250 | F105: =국내주식명세!G7 -> 346885000
A106: =IF($F$25=0,"O","X") -> O | C106: =국내주식명세!B8 -> 종목007 | D106: =국내주식명세!D8 -> 420 | E106: =국내주식명세!E8 -> 28544400 | F106: =국내주식명세!G8 -> 26376000
A107: =IF($F$25=0,"O","X") -> O | C107: =국내주식명세!B9 -> 종목008 | D107: =국내주식명세!D9 -> 2835 | E107: =국내주식명세!E9 -> 402100300 | F107: =국내주식명세!G9 -> 337932000
A108: =IF($F$25=0,"O","X") -> O | C108: =국내주식명세!B10 -> 종목009 | D108: =국내주식명세!D10 -> 2905 | E108: =국내주식명세!E10 -> 492148503 | F108: =국내주식명세!G10 -> 740775000
A109: =IF($F$25=0,"O","X") -> O | C109: =국내주식명세!B11 -> 종목010 | D109: =국내주식명세!D11 -> 2450 | E109: =국내주식명세!E11 -> 727251001 | F109: =국내주식명세!G11 -> 997150000
A110: =IF($F$25=0,"O","X") -> O | C110: =국내주식명세!B12 -> 종목011 | D110: =국내주식명세!D12 -> 350 | E110: =국내주식명세!E12 -> 363583220 | F110: =국내주식명세!G12 -> 460600000
A111: =IF($F$25=0,"O","X") -> O | C111: =국내주식명세!B13 -> 종목012 | D111: =국내주식명세!D13 -> 2170 | E111: =국내주식명세!E13 -> 139159001 | F111: =국내주식명세!G13 -> 180110000
A112: =IF($F$25=0,"O","X") -> O | C112: =국내주식명세!B14 -> 종목013 | D112: =국내주식명세!D14 -> 1330 | E112: =국내주식명세!E14 -> 86271401 | F112: =국내주식명세!G14 -> 117439000
... A307: =IF($F$25=0,"O","X") -> O | C307: =국내주식명세!B209 -> 0 | D307: =국내주식명세!D209 -> 0 | E307: =국내주식명세!E209 -> 0 | F307: =국내주식명세!G209 -> 0
A308: =IF($F$25=0,"O","X") -> O | F308: =국내주식명세!G208 -> 0
A309: =IF($F$25=0,"O","X") -> O | F309: =SUM(F101:F308) -> 106485058475
A311: =IF($F$26=0,"O","X") -> O | C311: (2) 코스닥주식
A312: =IF($F$26=0,"O","X") -> O | C312: 종목명 | D312: 수량 | E312: 결산전장부가액 | F312: 결산후장부가액
...

Sheet C3_수익
A1: ='C1_정산표'!B1 -> 한빛코스피레버리지증권상장지수투자신탁(주식-파생형)
A2: ='C1_정산표'!B2 -> 45657 | F2: Prepared by : | G2: ='C1_정산표'!H2 -> SJ
A3: 수익 | F3: Reviewed by :
B8: 이자수익 ARP
B13: 이자수익 재계산 | C13: 결론 | D13: =IF(J26<0.05,"적정","부적정") -> 적정
B16: 이자수익구분 | C16: 평균잔액 | D16: 기초이자율 | E16: 기말이자율 | F16: 평균이자율 | G16: 추정이자수익 | H16: 정산표상 이자수익 | I16: 차이 | J16: 차이비율
B17: ='통합기준가격대장(결산후)'!F344 -> 채권수입이자(과세) | C17: =AVERAGE(일별자산내역!J2:J366)-AVERAGE(일별자산내역!K2:K366) -> 44110508 | D17: 0.0336 | E17: 0.0336 | F17: =D17*100/365+E17*265/365 -> 0.0336 | G17: =C17*F17 -> 1482113.1 | H17: ='통합기준가격대장(결산후)'!G344 -> 661948 | I17: =G17-H17 -> 820165.08 | J17: =I17/G17 -> 0.55337551
B18: ='통합기준가격대장(결산후)'!F345 -> 외화채권수입이자(과세) | C18: 0 | D18: 0 | E18: 0 | F18: 0 | G18: =C18*F18 -> 0 | H18: 0 | I18: 0 | J18: 0
B19: ='통합기준가격대장(결산후)'!F346 -> 예금수입이자(과세) | C19: =AVERAGE(일별자산내역!B2:B366)-AVERAGE(일별자산내역!C2:C366) -> 4.0380912e+09 | D19: 0.0253 | E19: =국내유동명세!E3/100 -> 0.0207 | F19: =D19*100/365+E19*265/365 -> 0.021960274 | G19: =C19*F19 -> 88677590 | H19: ='통합기준가격대장(결산후)'!G346 -> 87439722 | I19: =G19-H19 -> 1237868 | J19: =I19/G19 -> 0.013959198
B20: ='통합기준가격대장(결산후)'!F347 -> 콜수입이자(과세) | C20: 0 | D20: 0 | E20: 0 | F20: 0 | G20: =C20*F20 -> 0 | H20: 0 | I20: =G20-H20 -> 0 | J20: 0
B21: ='통합기준가격대장(결산후)'!F348 -> 어음수입이자(과세) | C21: 0 | D21: 0 | E21: 0 | F21: 0 | G21: =C21*F21 -> 0 | H21: 0 | I21: =G21-H21 -> 0 | J21: 0
B22: ='통합기준가격대장(결산후)'!F349 -> 정기예금수입이자(과세) | C22: 0 | D22: 0 | E22: 0 | F22: 0 | G22: 0 | H22: 0 | I22: =G22-H22 -> 0 | J22: 0
B23: ='통합기준가격대장(결산후)'!F350 -> REPO수입이자(과세) | C23: 0 | D23: 0 | E23: 0 | F23: 0 | G23: =C23*F23 -> 0 | H23: 0 | I23: =G23-H23 -> 0 | J23: 0
B24: ='통합기준가격대장(결산후)'!F351 -> 위탁증거금수입이자(과세) | C24: =SUM(국내유동명세!K5:K8) -> 0 | F24: 0 | G24: =C24*F24 -> 0 | H24: 0 | I24: =G24-H24 -> 0 | J24: 0
B25: ='통합기준가격대장(결산후)'!F352 -> 외화예금수입이자(과세) | H25: ='통합기준가격대장(결산후)'!G352 -> 0
B26: 합계 | G26: =SUM(G17:G25) -> 90159703 | H26: =SUM(H17:H25) -> 88101670 | I26: =SUM(I17:I25) -> 2058033.1 | J26: =I26/G26 -> 0.022826529

Sheet 평가액검증(주식)
B1: 한빛코스피레버리지증권상장지수투자신탁(주식-파생형)
B2: ='C1_정산표'!B2 -> 45657 | G2: Prepared by : | H2: ='C1_정산표'!H2 -> SJ
B3: 평가액검증 | G3: Reviewed by :
G9: FALSE의 개수=> | H9: =COUNTIF(H12:H82,0) -> 0 | J9: =COUNTIF(I12:I82,0) -> 0
A10: Column1 | B10: Column2 | C10: Column3 | D10: Column4 | E10: Column5 | F10: Column6 | G10: Column7 | H10: Test 1 | I10: Test 2
A11: 종목 | B11: 종목명 | C11: 상품구분 | D11: 수량 | E11: 취득가액 | F11: 종가 | G11: 평가금액 | H11: 평가금액정확성 | I11: 종가검증 A | J11: 종가검증 B
A12: =국내주식명세!A3 -> KR7001440007 | B12: =국내주식명세!B3 -> 종목002 | C12: =국내주식명세!C3 -> 거래소 | D12: =국내주식명세!D3 -> 5880 | E12: =국내주식명세!E3 -> 91764961 | F12: =국내주식명세!F3 -> 22900 | G12: =국내주식명세!G3 -> 134652000 | H12: =G12=D12*F12 -> TRUE | I12: =INDEX(KRS정보시스템_주식!$A$1:$N$3000,MATCH('평가액검증(주식)'!B12,KRS정보시스템_주식!$B:$B,0),MATCH(KRS정보시스템_주식!$E$1,KRS정보시스템_주식!$1:$1,0)) -> 22900 | J12: =IF(D12=0,"TRUE",IF(F12=I12,"TRUE","FALSE")) -> TRUE
A13: =국내주식명세!A4 -> KR7002380004 | B13: =국내주식명세!B4 -> 종목003 | C13: =국내주식명세!C4 -> 거래소 | D13: =국내주식명세!D4 -> 210 | E13: =국내주식명세!E4 -> 63483000 | F13: =국내주식명세!F4 -> 420500 | G13: =국내주식명세!G4 -> 88305000 | H13: =G13=D13*F13 -> TRUE | I13: =INDEX(KRS정보시스템_주식!$A$1:$N$3000,MATCH('평가액검증(주식)'!B13,KRS정보시스템_주식!$B:$B,0),MATCH(KRS정보시스템_주식!$E$1,KRS정보시스템_주식!$1:$1,0)) -> 420500 | J13: =IF(D13=0,"TRUE",IF(F13=I13,"TRUE","FALSE")) -> TRUE
A14: =국내주식명세!A5 -> KR7003230000 | B14: =국내주식명세!B5 -> 종목004 | C14: =국내주식명세!C5 -> 거래소 | D14: =국내주식명세!D5 -> 210 | E14: =국내주식명세!E5 -> 204090000 | F14: =국내주식명세!F5 -> 1231000 | G14: =국내주식명세!G5 -> 258510000 | H14: =G14=D14*F14 -> TRUE | I14: =INDEX(KRS정보시스템_주식!$A$1:$N$3000,MATCH('평가액검증(주식)'!B14,KRS정보시스템_주식!$B:$B,0),MATCH(KRS정보시스템_주식!$E$1,KRS정보시스템_주식!$1:$1,0)) -> 1231000 | J14: =IF(D14=0,"TRUE",IF(F14=I14,"TRUE","FALSE")) -> TRUE
A15: =국내주식명세!A6 -> KR7003240009 | B15: =국내주식명세!B6 -> 종목005 | C15: =국내주식명세!C6 -> 거래소 | D15: =국내주식명세!D6 -> 35 | E15: =국내주식명세!E6 -> 28063230 | F15: =국내주식명세!F6 -> 762000 | G15: =국내주식명세!G6 -> 26670000 | H15: =G15=D15*F15 -> TRUE | I15: =INDEX(KRS정보시스템_주식!$A$1:$N$3000,MATCH('평가액검증(주식)'!B15,KRS정보시스템_주식!$B:$B,0),MATCH(KRS정보시스템_주식!$E$1,KRS정보시스템_주식!$1:$1,0)) -> 762000 | J15: =IF(D15=0,"TRUE",IF(F15=I15,"TRUE","FALSE")) -> TRUE
A16: =국내주식명세!A7 -> KR7003670007 | B16: =국내주식명세!B7 -> 종목006 | C16: =국내주식명세!C7 -> 거래소 | D16: =국내주식명세!D7 -> 1855 | E16: =국내주식명세!E7 -> 311085250 | F16: =국내주식명세!F7 -> 187000 | G16: =국내주식명세!G7 -> 346885000 | H16: =G16=D16*F16 -> TRUE | I16: =INDEX(KRS정보시스템_주식!$A$1:$N$3000,MATCH('평가액검증(주식)'!B16,KRS정보시스템_주식!$B:$B,0),MATCH(KRS정보시스템_주식!$E$1,KRS정보시스템_주식!$1:$1,0)) -> 187000 | J16: =IF(D16=0,"TRUE",IF(F16=I16,"TRUE","FALSE")) -> TRUE
A17: =국내주식명세!A8 -> KR7004490009 | B17: =국내주식명세!B8 -> 종목007 | C17: =국내주식명세!C8 -> 거래소 | D17: =국내주식명세!D8 -> 420 | E17: =국내주식명세!E8 -> 28544400 | F17: =국내주식명세!F8 -> 62800 | G17: =국내주식명세!G8 -> 26376000 | H17: =G17=D17*F17 -> TRUE | I17: =INDEX(KRS정보시스템_주식!$A$1:$N$3000,MATCH('평가액검증(주식)'!B17,KRS정보시스템_주식!$B:$B,0),MATCH(KRS정보시스템_주식!$E$1,KRS정보시스템_주식!$1:$1,0)) -> 62800 | J17: =IF(D17=0,"TRUE",IF(F17=I17,"TRUE","FALSE")) -> TRUE
A18: =국내주식명세!A9 -> KR7007660004 | B18: =국내주식명세!B9 -> 종목008 | C18: =국내주식명세!C9 -> 거래소 | D18: =국내주식명세!D9 -> 2835 | E18: =국내주식명세!E9 -> 402100300 | F18: =국내주식명세!F9 -> 119200 | G18: =국내주식명세!G9 -> 337932000 | H18: =G18=D18*F18 -> TRUE | I18: =INDEX(KRS정보시스템_주식!$A$1:$N$3000,MATCH('평가액검증(주식)'!B18,KRS정보시스템_주식!$B:$B,0),MATCH(KRS정보시스템_주식!$E$1,KRS정보시스템_주식!$1:$1,0)) -> 119200 | J18: =IF(D18=0,"TRUE",IF(F18=I18,"TRUE","FALSE")) -> TRUE
A19: =국내주식명세!A10 -> KR7009150004 | B19: =국내주식명세!B10 -> 종목009 | C19: =국내주식명세!C10 -> 거래소 | D19: =국내주식명세!D10 -> 2905 | E19: =국내주식명세!E10 -> 492148503 | F19: =국내주식명세!F10 -> 255000 | G19: =국내주식명세!G10 -> 740775000 | H19: =G19=D19*F19 -> TRUE | I19: =INDEX(KRS정보시스템_주식!$A$1:$N$3000,MATCH('평가액검증(주식)'!B19,KRS정보시스템_주식!$B:$B,0),MATCH(KRS정보시스템_주식!$E$1,KRS정보시스템_주식!$1:$1,0)) -> 255000 | J19: =IF(D19=0,"TRUE",IF(F19=I19,"TRUE","FALSE")) -> TRUE
A20: =국내주식명세!A11 -> KR7009540006 | B20: =국내주식명세!B11 -> 종목010 | C20: =국내주식명세!C11 -> 거래소 | D20: =국내주식명세!D11 -> 2450 | E20: =국내주식명세!E11 -> 727251001 | F20: =국내주식명세!F11 -> 407000 | G20: =국내주식명세!G11 -> 997150000 | H20: =G20=D20*F20 -> TRUE | I20: =INDEX(KRS정보시스템_주식!$A$1:$N$3000,MATCH('평가액검증(주식)'!B20,KRS정보시스템_주식!$B:$B,0),MATCH(KRS정보시스템_주식!$E$1,KRS정보시스템_주식!$1:$1,0)) -> 407000 | J20: =IF(D20=0,"TRUE",IF(F20=I20,"TRUE","FALSE")) -> TRUE
A21: =국내주식명세!A12 -> KR7010130003 | B21: =국내주식명세!B12 -> 종목011 | C21: =국내주식명세!C12 -> 거래소 | D21: =국내주식명세!D12 -> 350 | E21: =국내주식명세!E12 -> 363583220 | F21: =국내주식명세!F12 -> 1316000 | G21: =국내주식명세!G12 -> 460600000 | H21: =G21=D21*F21 -> TRUE | I21: =INDEX(KRS정보시스템_주식!$A$1:$N$3000,MATCH('평가액검증(주식)'!B21,KRS정보시스템_주식!$B:$B,0),MATCH(KRS정보시스템_주식!$E$1,KRS정보시스템_주식!$1:$1,0)) -> 1316000 | J21: =IF(D21=0,"TRUE",IF(F21=I21,"TRUE","FALSE")) -> TRUE
A22: =국내주식명세!A13 -> KR7010950004 | B22: =국내주식명세!B13 -> 종목012 | C22: =국내주식명세!C13 -> 거래소 | D22: =국내주식명세!D13 -> 2170 | E22: =국내주식명세!E13 -> 139159001 | F22: =국내주식명세!F13 -> 83000 | G22: =국내주식명세!G13 -> 180110000 | H22: =G22=D22*F22 -> TRUE | I22: =INDEX(KRS정보시스템_주식!$A$1:$N$3000,MATCH('평가액검증(주식)'!B22,KRS정보시스템_주식!$B:$B,0),MATCH(KRS정보시스템_주식!$E$1,KRS정보시스템_주식!$1:$1,0)) -> 83000 | J22: =IF(D22=0,"TRUE",IF(F22=I22,"TRUE","FALSE")) -> TRUE
A23: =국내주식명세!A14 -> KR7017800004 | B23: =국내주식명세!B14 -> 종목013 | C23: =국내주식명세!C14 -> 거래소 | D23: =국내주식명세!D14 -> 1330 | E23: =국내주식명세!E14 -> 86271401 | F23: =국내주식명세!F14 -> 88300 | G23: =국내주식명세!G14 -> 117439000 | H23: =G23=D23*F23 -> TRUE | I23: =INDEX(KRS정보시스템_주식!$A$1:$N$3000,MATCH('평가액검증(주식)'!B23,KRS정보시스템_주식!$B:$B,0),MATCH(KRS정보시스템_주식!$E$1,KRS정보시스템_주식!$1:$1,0)) -> 88300 | J23: =IF(D23=0,"TRUE",IF(F23=I23,"TRUE","FALSE")) -> TRUE
... A42: =국내주식명세!A33 -> KR70126Z0002 | B42: =국내주식명세!B33 -> 종목032 | C42: =국내주식명세!C33 -> 거래소 | D42: =국내주식명세!D33 -> 280 | E42: =국내주식명세!E33 -> 235064992 | F42: =국내주식명세!F33 -> 743000 | G42: =국내주식명세!G33 -> 208040000 | H42: =G42=D42*F42 -> TRUE | I42: =INDEX(KRS정보시스템_주식!$A$1:$N$3000,MATCH('평가액검증(주식)'!B42,KRS정보시스템_주식!$B:$B,0),MATCH(KRS정보시스템_주식!$E$1,KRS정보시스템_주식!$1:$1,0)) -> 743000 | J42: =IF(D42=0,"TRUE",IF(F42=I42,"TRUE","FALSE")) -> TRUE
A43: =국내주식명세!A34 -> KR701888000A | B43: =국내주식명세!B34 -> 종목033 | C43: =국내주식명세!C34 -> 거래소 | D43: =국내주식명세!D34 -> 2529 | E43: =국내주식명세!E34 -> 7157070 | F43: =국내주식명세!F34 -> 2965 | G43: =국내주식명세!G34 -> 7498485 | H43: =G43=D43*F43 -> TRUE | I43: 2965 | J43: =IF(D43=0,"TRUE",IF(F43=I43,"TRUE","FALSE")) -> TRUE
A44: =국내주식명세!A35 -> KR7023530009 | B44: =국내주식명세!B35 -> 종목034 | C44: =국내주식명세!C35 -> 거래소 | D44: =국내주식명세!D35 -> 525 | E44: =국내주식명세!E35 -> 32378487 | F44: =국내주식명세!F35 -> 72500 | G44: =국내주식명세!G35 -> 38062500 | H44: =G44=D44*F44 -> TRUE | I44: =INDEX(KRS정보시스템_주식!$A$1:$N$3000,MATCH('평가액검증(주식)'!B44,KRS정보시스템_주식!$B:$B,0),MATCH(KRS정보시스템_주식!$E$1,KRS정보시스템_주식!$1:$1,0)) -> 72500 | J44: =IF(D44=0,"TRUE",IF(F44=I44,"TRUE","FALSE")) -> TRUE
A45: =국내주식명세!A36 -> KR7028260008 | B45: =국내주식명세!B36 -> 종목035 | C45: =국내주식명세!C36 -> 거래소 | D45: =국내주식명세!D36 -> 5250 | E45: =국내주식명세!E36 -> 845438975 | F45: =국내주식명세!F36 -> 239500 | G45: =국내주식명세!G36 -> 1257375000 | H45: =G45=D45*F45 -> TRUE | I45: =INDEX(KRS정보시스템_주식!$A$1:$N$3000,MATCH('평가액검증(주식)'!B45,KRS정보시스템_주식!$B:$B,0),MATCH(KRS정보시스템_주식!$E$1,KRS정보시스템_주식!$1:$1,0)) -> 239500 | J45: =IF(D45=0,"TRUE",IF(F45=I45,"TRUE","FALSE")) -> TRUE
A46: =국내주식명세!A37 -> KR7032830002 | B46: =국내주식명세!B37 -> 종목036 | C46: =국내주식명세!C37 -> 거래소 | D46: =국내주식명세!D37 -> 4410 | E46: =국내주식명세!E37 -> 513802800 | F46: =국내주식명세!F37 -> 157600 | G46: =국내주식명세!G37 -> 695016000 | H46: =G46=D46*F46 -> TRUE | I46: =INDEX(KRS정보시스템_주식!$A$1:$N$3000,MATCH('평가액검증(주식)'!B46,KRS정보시스템_주식!$B:$B,0),MATCH(KRS정보시스템_주식!$E$1,KRS정보시스템_주식!$1:$1,0)) -> 157600 | J46: =IF(D46=0,"TRUE",IF(F46=I46,"TRUE","FALSE")) -> TRUE
A47: =국내주식명세!A38 -> KR7034220004 | B47: =국내주식명세!B38 -> 종목037 | C47: =국내주식명세!C38 -> 거래소 | D47: =국내주식명세!D38 -> 15190 | E47: =국내주식명세!E38 -> 155584662 | F47: =국내주식명세!F38 -> 11810 | G47: =국내주식명세!G38 -> 179393900 | H47: =G47=D47*F47 -> TRUE | I47: =INDEX(KRS정보시스템_주식!$A$1:$N$3000,MATCH('평가액검증(주식)'!B47,KRS정보시스템_주식!$B:$B,0),MATCH(KRS정보시스템_주식!$E$1,KRS정보시스템_주식!$1:$1,0)) -> 11810 | J47: =IF(D47=0,"TRUE",IF(F47=I47,"TRUE","FALSE")) -> TRUE
A48: =국내주식명세!A39 -> KR7034230003 | B48: =국내주식명세!B39 -> 종목038 | C48: =국내주식명세!C39 -> 거래소 | D48: =국내주식명세!D39 -> 2275 | E48: =국내주식명세!E39 -> 39950500 | F48: =국내주식명세!F39 -> 16550 | G48: =국내주식명세!G39 -> 37651250 | H48: =G48=D48*F48 -> TRUE | I48: =INDEX(KRS정보시스템_주식!$A$1:$N$3000,MATCH('평가액검증(주식)'!B48,KRS정보시스템_주식!$B:$B,0),MATCH(KRS정보시스템_주식!$E$1,KRS정보시스템_주식!$1:$1,0)) -> 16550 | J48: =IF(D48=0,"TRUE",IF(F48=I48,"TRUE","FALSE")) -> TRUE
A49: =국내주식명세!A40 -> KR7042670000 | B49: =국내주식명세!B40 -> 종목039 | C49: =국내주식명세!C40 -> 거래소 | D49: =국내주식명세!D40 -> 760 | E49: =국내주식명세!E40 -> 7135940 | F49: =국내주식명세!F40 -> 13800 | G49: =국내주식명세!G40 -> 10488000 | H49: =G49=D49*F49 -> TRUE | I49: =INDEX(KRS정보시스템_주식!$A$1:$N$3000,MATCH('평가액검증(주식)'!B49,KRS정보시스템_주식!$B:$B,0),MATCH(KRS정보시스템_주식!$E$1,KRS정보시스템_주식!$1:$1,0)) -> 13800 | J49: =IF(D49=0,"TRUE",IF(F49=I49,"TRUE","FALSE")) -> TRUE
A50: =국내주식명세!A41 -> KR7051910008 | B50: =국내주식명세!B41 -> 종목040 | C50: =국내주식명세!C41 -> 거래소 | D50: =국내주식명세!D41 -> 2415 | E50: =국내주식명세!E41 -> 694830001 | F50: =국내주식명세!F41 -> 333000 | G50: =국내주식명세!G41 -> 804195000 | H50: =G50=D50*F50 -> TRUE | I50: =INDEX(KRS정보시스템_주식!$A$1:$N$3000,MATCH('평가액검증(주식)'!B50,KRS정보시스템_주식!$B:$B,0),MATCH(KRS정보시스템_주식!$E$1,KRS정보시스템_주식!$1:$1,0)) -> 333000 | J50: =IF(D50=0,"TRUE",IF(F50=I50,"TRUE","FALSE")) -> TRUE
A51: =국내주식명세!A42 -> KR7068270008 | B51: =국내주식명세!B42 -> 종목041 | C51: =국내주식명세!C42 -> 거래소 | D51: =국내주식명세!D42 -> 8120 | E51: =국내주식명세!E42 -> 1446332762 | F51: =국내주식명세!F42 -> 181000 | G51: =국내주식명세!G42 -> 1469720000 | H51: =G51=D51*F51 -> TRUE | I51: =INDEX(KRS정보시스템_주식!$A$1:$N$3000,MATCH('평가액검증(주식)'!B51,KRS정보시스템_주식!$B:$B,0),MATCH(KRS정보시스템_주식!$E$1,KRS정보시스템_주식!$1:$1,0)) -> 181000 | J51: =IF(D51=0,"TRUE",IF(F51=I51,"TRUE","FALSE")) -> TRUE
A52: =국내주식명세!A43 -> KR7071320006 | B52: =국내주식명세!B43 -> 종목042 | C52: =국내주식명세!C43 -> 거래소 | D52: =국내주식명세!D43 -> 140 | E52: =국내주식명세!E43 -> 12231440 | F52: =국내주식명세!F43 -> 96400 | G52: =국내주식명세!G43 -> 13496000 | H52: =G52=D52*F52 -> TRUE | I52: =INDEX(KRS정보시스템_주식!$A$1:$N$3000,MATCH('평가액검증(주식)'!B52,KRS정보시스템_주식!$B:$B,0),MATCH(KRS정보시스템_주식!$E$1,KRS정보시스템_주식!$1:$1,0)) -> 96400 | J52: =IF(D52=0,"TRUE",IF(F52=I52,"TRUE","FALSE")) -> TRUE
A53: =국내주식명세!A44 -> KR7073240004 | B53: =국내주식명세!B44 -> 종목043 | C53: =국내주식명세!C44 -> 거래소 | D53: =국내주식명세!D44 -> 8295 | E53: =국내주식명세!E44 -> 41897109 | F53: =국내주식명세!F44 -> 5860 | G53: =국내주식명세!G44 -> 48608700 | H53: =G53=D53*F53 -> TRUE | I53: =INDEX(KRS정보시스템_주식!$A$1:$N$3000,MATCH('평가액검증(주식)'!B53,KRS정보시스템_주식!$B:$B,0),MATCH(KRS정보시스템_주식!$E$1,KRS정보시스템_주식!$1:$1,0)) -> 5860 | J53: =IF(D53=0,"TRUE",IF(F53=I53,"TRUE","FALSE")) -> TRUE
A54: =국내주식명세!A45 -> KR7078930005 | B54: =국내주식명세!B45 -> 종목044 | C54: =국내주식명세!C45 -> 거래소 | D54: =국내주식명세!D45 -> 2345 | E54: =국내주식명세!E45 -> 103478152 | F54: =국내주식명세!F45 -> 56300 | G54: =국내주식명세!G45 -> 132023500 | H54: =G54=D54*F54 -> TRUE | I54: =INDEX(KRS정보시스템_주식!$A$1:$N$3000,MATCH('평가액검증(주식)'!B54,KRS정보시스템_주식!$B:$B,0),MATCH(KRS정보시스템_주식!$E$1,KRS정보시스템_주식!$1:$1,0)) -> 56300 | J54: =IF(D54=0,"TRUE",IF(F54=I54,"TRUE","FALSE")) -> TRUE
A55: =국내주식명세!A46 -> KR7093370005 | B55: =국내주식명세!B46 -> 종목045 | C55: =국내주식명세!C46 -> 거래소 | D55: =국내주식명세!D46 -> 2870 | E55: =국내주식명세!E46 -> 17329063 | F55: =국내주식명세!F46 -> 7530 | G55: =국내주식명세!G46 -> 21611100 | H55: =G55=D55*F55 -> TRUE | I55: =INDEX(KRS정보시스템_주식!$A$1:$N$3000,MATCH('평가액검증(주식)'!B55,KRS정보시스템_주식!$B:$B,0),MATCH(KRS정보시스템_주식!$E$1,KRS정보시스템_주식!$1:$1,0)) -> 7530 | J55: =IF(D55=0,"TRUE",IF(F55=I55,"TRUE","FALSE")) -> TRUE
... A107: =국내주식명세!A98 -> KR7454910001 | B107: =국내주식명세!B98 -> 종목097 | C107: =국내주식명세!C98 -> 거래소 | D107: =국내주식명세!D98 -> 1015 | E107: =국내주식명세!E98 -> 61857003 | F107: =국내주식명세!F98 -> 78000 | G107: =국내주식명세!G98 -> 79170000 | H107: =G107=D107*F107 -> TRUE | I107: =INDEX(KRS정보시스템_주식!$A$1:$N$3000,MATCH('평가액검증(주식)'!B107,KRS정보시스템_주식!$B:$B,0),MATCH(KRS정보시스템_주식!$E$1,KRS정보시스템_주식!$1:$1,0)) -> 78000 | J107: =IF(D107=0,"TRUE",IF(F107=I107,"TRUE","FALSE")) -> TRUE
A108: =국내주식명세!A99 -> KR700067000D | B108: =국내주식명세!B99 -> 종목098 | C108: =국내주식명세!C99 -> 거래소 | D108: =국내주식명세!D99 -> 6 | E108: =국내주식명세!E99 -> 3000 | F108: =국내주식명세!F99 -> 47500 | G108: =국내주식명세!G99 -> 285000 | H108: =G108=D108*F108 -> TRUE | I108: 47500 | J108: =IF(D108=0,"TRUE",IF(F108=I108,"TRUE","FALSE")) -> TRUE
A109: =국내주식명세!A100 -> KR7000720003 | B109: =국내주식명세!B100 -> 종목099 | C109: =국내주식명세!C100 -> 거래소 | D109: =국내주식명세!D100 -> 3850 | E109: =국내주식명세!E100 -> 163515001 | F109: =국내주식명세!F100 -> 70100 | G109: =국내주식명세!G100 -> 269885000 | H109: =G109=D109*F109 -> TRUE | I109: =INDEX(KRS정보시스템_주식!$A$1:$N$3000,MATCH('평가액검증(주식)'!B109,KRS정보시스템_주식!$B:$B,0),MATCH(KRS정보시스템_주식!$E$1,KRS정보시스템_주식!$1:$1,0)) -> 70100 | J109: =IF(D109=0,"TRUE",IF(F109=I109,"TRUE","FALSE")) -> TRUE
A110: =국내주식명세!A101 -> KR7000880005 | B110: =국내주식명세!B101 -> 종목100 | C110: =국내주식명세!C101 -> 거래소 | D110: =국내주식명세!D101 -> 1470 | E110: =국내주식명세!E101 -> 72979200 | F110: =국내주식명세!F101 -> 81600 | G110: =국내주식명세!G101 -> 119952000 | H110: =G110=D110*F110 -> TRUE | I110: =INDEX(KRS정보시스템_주식!$A$1:$N$3000,MATCH('평가액검증(주식)'!B110,KRS정보시스템_주식!$B:$B,0),MATCH(KRS정보시스템_주식!$E$1,KRS정보시스템_주식!$1:$1,0)) -> 81600 | J110: =IF(D110=0,"TRUE",IF(F110=I110,"TRUE","FALSE")) -> TRUE
A111: =국내주식명세!A102 -> KR7002030005 | B111: =국내주식명세!B102 -> 종목101 | C111: =국내주식명세!C102 -> 거래소 | D111: =국내주식명세!D102 -> 35 | E111: =국내주식명세!E102 -> 12702090 | F111: =국내주식명세!F102 -> 326500 | G111: =국내주식명세!G102 -> 11427500 | H111: =G111=D111*F111 -> TRUE | I111: =INDEX(KRS정보시스템_주식!$A$1:$N$3000,MATCH('평가액검증(주식)'!B111,KRS정보시스템_주식!$B:$B,0),MATCH(KRS정보시스템_주식!$E$1,KRS정보시스템_주식!$1:$1,0)) -> 326500 | J111: =IF(D111=0,"TRUE",IF(F111=I111,"TRUE","FALSE")) -> TRUE
A112: =국내주식명세!A103 -> KR7004990008 | B112: =국내주식명세!B103 -> 종목102 | C112: =국내주식명세!C103 -> 거래소 | D112: =국내주식명세!D103 -> 1540 | E112: =국내주식명세!E103 -> 38323903 | F112: =국내주식명세!F103 -> 26450 | G112: =국내주식명세!G103 -> 40733000 | H112: =G112=D112*F112 -> TRUE | I112: =INDEX(KRS정보시스템_주식!$A$1:$N$3000,MATCH('평가액검증(주식)'!B112,KRS정보시스템_주식!$B:$B,0),MATCH(KRS정보시스템_주식!$E$1,KRS정보시스템_주식!$1:$1,0)) -> 26450 | J112: =IF(D112=0,"TRUE",IF(F112=I112,"TRUE","FALSE")) -> TRUE
A113: =국내주식명세!A104 -> KR7008730004 | B113: =국내주식명세!B104 -> 종목103 | C113: =국내주식명세!C104 -> 거래소 | D113: =국내주식명세!D104 -> 560 | E113: =국내주식명세!E104 -> 13429600 | F113: =국내주식명세!F104 -> 25800 | G113: =국내주식명세!G104 -> 14448000 | H113: =G113=D113*F113 -> TRUE | I113: =INDEX(KRS정보시스템_주식!$A$1:$N$3000,MATCH('평가액검증(주식)'!B113,KRS정보시스템_주식!$B:$B,0),MATCH(KRS정보시스템_주식!$E$1,KRS정보시스템_주식!$1:$1,0)) -> 25800 | J113: =IF(D113=0,"TRUE",IF(F113=I113,"TRUE","FALSE")) -> TRUE
A114: =국내주식명세!A105 -> KR7009970005 | B114: =국내주식명세!B105 -> 종목104 | C114: =국내주식명세!C105 -> 거래소 | D114: =국내주식명세!D105 -> 280 | E114: =국내주식명세!E105 -> 33441600 | F114: =국내주식명세!F105 -> 191500 | G114: =국내주식명세!G105 -> 53620000 | H114: =G114=D114*F114 -> TRUE | I114: =INDEX(KRS정보시스템_주식!$A$1:$N$3000,MATCH('평가액검증(주식)'!B114,KRS정보시스템_주식!$B:$B,0),MATCH(KRS정보시스템_주식!$E$1,KRS정보시스템_주식!$1:$1,0)) -> 191500 | J114: =IF(D114=0,"TRUE",IF(F114=I114,"TRUE","FALSE")) -> TRUE
A115: =국내주식명세!A106 -> KR7011200003 | B115: =국내주식명세!B106 -> 종목105 | C115: =국내주식명세!C106 -> 거래소 | D115: =국내주식명세!D106 -> 16310 | E115: =국내주식명세!E106 -> 312010828 | F115: =국내주식명세!F106 -> 20500 | G115: =국내주식명세!G106 -> 334355000 | H115: =G115=D115*F115 -> TRUE | I115: =INDEX(KRS정보시스템_주식!$A$1:$N$3000,MATCH('평가액검증(주식)'!B115,KRS정보시스템_주식!$B:$B,0),MATCH(KRS정보시스템_주식!$E$1,KRS정보시스템_주식!$1:$1,0)) -> 20500 | J115: =IF(D115=0,"TRUE",IF(F115=I115,"TRUE","FALSE")) -> TRUE
A116: =국내주식명세!A107 -> KR7011790003 | B116: =국내주식명세!B107 -> 종목106 | C116: =국내주식명세!C107 -> 거래소 | D116: =국내주식명세!D107 -> 1015 | E116: =국내주식명세!E107 -> 107868403 | F116: =국내주식명세!F107 -> 104400 | G116: =국내주식명세!G107 -> 105966000 | H116: =G116=D116*F116 -> TRUE | I116: =INDEX(KRS정보시스템_주식!$A$1:$N$3000,MATCH('평가액검증(주식)'!B116,KRS정보시스템_주식!$B:$B,0),MATCH(KRS정보시스템_주식!$E$1,KRS정보시스템_주식!$1:$1,0)) -> 104400 | J116: =IF(D116=0,"TRUE",IF(F116=I116,"TRUE","FALSE")) -> TRUE
A117: =국내주식명세!A108 -> KR7016360000 | B117: =국내주식명세!B108 -> 종목107 | C117: =국내주식명세!C108 -> 거래소 | D117: =국내주식명세!D108 -> 3185 | E117: =국내주식명세!E108 -> 179579402 | F117: =국내주식명세!F108 -> 75400 | G117: =국내주식명세!G108 -> 240149000 | H117: =G117=D117*F117 -> TRUE | I117: =INDEX(KRS정보시스템_주식!$A$1:$N$3000,MATCH('평가액검증(주식)'!B117,KRS정보시스템_주식!$B:$B,0),MATCH(KRS정보시스템_주식!$E$1,KRS정보시스템_주식!$1:$1,0)) -> 75400 | J117: =IF(D117=0,"TRUE",IF(F117=I117,"TRUE","FALSE")) -> TRUE
A118: =국내주식명세!A109 -> KR7017670001 | B118: =국내주식명세!B109 -> 종목108 | C118: =국내주식명세!C109 -> 거래소 | D118: =국내주식명세!D109 -> 7770 | E118: =국내주식명세!E109 -> 423553346 | F118: =국내주식명세!F109 -> 53500 | G118: =국내주식명세!G109 -> 415695000 | H118: =G118=D118*F118 -> TRUE | I118: =INDEX(KRS정보시스템_주식!$A$1:$N$3000,MATCH('평가액검증(주식)'!B118,KRS정보시스템_주식!$B:$B,0),MATCH(KRS정보시스템_주식!$E$1,KRS정보시스템_주식!$1:$1,0)) -> 53500 | J118: =IF(D118=0,"TRUE",IF(F118=I118,"TRUE","FALSE")) -> TRUE
A119: =국내주식명세!A110 -> KR7018260000 | B119: =국내주식명세!B110 -> 종목109 | C119: =국내주식명세!C110 -> 거래소 | D119: =국내주식명세!D110 -> 1995 | E119: =국내주식명세!E110 -> 283734602 | F119: =국내주식명세!F110 -> 171500 | G119: =국내주식명세!G110 -> 342142500 | H119: =G119=D119*F119 -> TRUE | I119: =INDEX(KRS정보시스템_주식!$A$1:$N$3000,MATCH('평가액검증(주식)'!B119,KRS정보시스템_주식!$B:$B,0),MATCH(KRS정보시스템_주식!$E$1,KRS정보시스템_주식!$1:$1,0)) -> 171500 | J119: =IF(D119=0,"TRUE",IF(F119=I119,"TRUE","FALSE")) -> TRUE
A120: =국내주식명세!A111 -> KR7018880005 | B120: =국내주식명세!B111 -> 종목110 | C120: =국내주식명세!C111 -> 거래소 | D120: =국내주식명세!D111 -> 10386 | E120: =국내주식명세!E111 -> 37899397 | F120: =국내주식명세!F111 -> 2965 | G120: =국내주식명세!G111 -> 30794490 | H120: =G120=D120*F120 -> TRUE | I120: =INDEX(KRS정보시스템_주식!$A$1:$N$3000,MATCH('평가액검증(주식)'!B120,KRS정보시스템_주식!$B:$B,0),MATCH(KRS정보시스템_주식!$E$1,KRS정보시스템_주식!$1:$1,0)) -> 2965 | J120: =IF(D120=0,"TRUE",IF(F120=I120,"TRUE","FALSE")) -> TRUE
... A215: =국내주식명세!A206 -> KR7450080007 | B215: =국내주식명세!B206 -> 종목206 | C215: =국내주식명세!C206 -> 거래소 | D215: =국내주식명세!D206 -> 1330 | E215: =국내주식명세!E206 -> 79251490 | F215: =국내주식명세!F206 -> 52100 | G215: =국내주식명세!G206 -> 69293000 | H215: =G215=D215*F215 -> TRUE | I215: =INDEX(KRS정보시스템_주식!$A$1:$N$3000,MATCH('평가액검증(주식)'!B215,KRS정보시스템_주식!$B:$B,0),MATCH(KRS정보시스템_주식!$E$1,KRS정보시스템_주식!$1:$1,0)) -> 52100 | J215: =IF(D215=0,"TRUE",IF(F215=I215,"TRUE","FALSE")) -> TRUE

Sheet KRS정보시스템_주식
A1: 종목코드 | B1: 종목명 | C1: 시장구분 | D1: 소속부 | E1: 종가 | F1: 대비 | G1: 등락률 | H1: 시가 | I1: 고가 | J1: 저가 | K1: 거래량 | L1: 거래대금 | M1: 시가총액 | N1: 상장주식수
A2: 060310 | B2: 3S | C2: KOSDAQ | D2: 벤처기업부 | E2: 1555 | F2: 52 | G2: 3.46 | H2: 1504 | I2: 1605 | J2: 1504 | K2: 480513 | L2: 750346819 | M2: 82506807200 | N2: 53059040
A3: 095570 | B3: AJ네트웍스 | C3: KOSPI | E3: 4660 | F3: 35 | G3: 0.76 | H3: 4625 | I3: 4740 | J3: 4610 | K3: 111113 | L3: 520145365 | M3: 210877856940 | N3: 45252759
A4: 006840 | B4: AK홀딩스 | C4: KOSPI | E4: 8710 | F4: -140 | G4: -1.58 | H4: 8860 | I4: 8860 | J4: 8660 | K4: 5634 | L4: 49295190 | M4: 115386256310 | N4: 13247561
A5: 054620 | B5: APS | C5: KOSDAQ | D5: 중견기업부 | E5: 4060 | F5: -60 | G5: -1.46 | H5: 4090 | I5: 4100 | J5: 3990 | K5: 4278 | L5: 17264175 | M5: 74680537260 | N5: 18394221
A6: 265520 | B6: AP시스템 | C6: KOSDAQ | D6: 우량기업부 | E6: 19370 | F6: -60 | G6: -0.31 | H6: 19410 | I6: 19660 | J6: 19250 | K6: 47653 | L6: 924577775 | M6: 291534402770 | N6: 15050821
A7: 211270 | B7: AP위성 | C7: KOSDAQ | D7: 우량기업부 | E7: 12670 | F7: -30 | G7: -0.24 | H7: 12550 | I7: 12790 | J7: 12300 | K7: 162880 | L7: 2039301055 | M7: 191092791680 | N7: 15082304
A8: 139050 | B8: BF랩스 | C8: KOSDAQ | D8: 관리종목(소속부없음) | E8: 2805 | F8: 0 | G8: 0 | H8: 0 | I8: 0 | J8: 0 | K8: 0 | L8: 0 | M8: 24247965555 | N8: 8644551
A9: 027410 | B9: BGF | C9: KOSPI | E9: 3920 | F9: 25 | G9: 0.64 | H9: 3900 | I9: 3945 | J9: 3870 | K9: 52227 | L9: 204211735 | M9: 375209820720 | N9: 95716791
A10: 282330 | B10: 종목050 | C10: KOSPI | E10: 104800 | F10: -1100 | G10: -1.04 | H10: 105300 | I10: 106500 | J10: 104300 | K10: 35230 | L10: 3689188800 | M10: 1811353348800 | N10: 17283906
A11: 126600 | B11: BGF에코머티리얼즈 | C11: KOSDAQ | D11: 우량기업부 | E11: 3660 | F11: 30 | G11: 0.83 | H11: 3635 | I11: 3680 | J11: 3610 | K11: 56844 | L11: 206895470 | M11: 229726850340 | N11: 62766899
A12: 138930 | B12: 종목155 | C12: KOSPI | E12: 15870 | F12: -170 | G12: -1.06 | H12: 15960 | I12: 16000 | J12: 15840 | K12: 392664 | L12: 6243509760 | M12: 4989927193980 | N12: 314425154
A13: 001460 | B13: BYC | C13: KOSPI | E13: 42100 | F13: 200 | G13: 0.48 | H13: 41900 | I13: 42800 | J13: 41650 | K13: 1967 | L13: 83350300 | M13: 262962915000 | N13: 6246150
A14: 001465 | B14: BYC우 | C14: KOSPI | E14: 24450 | F14: -150 | G14: -0.61 | H14: 24200 | I14: 24900 | J14: 24000 | K14: 824 | L14: 20076850 | M14: 52661632500 | N14: 2153850
A15: 083790 | B15: CG인바이츠 | C15: KOSDAQ | D15: 벤처기업부 | E15: 1487 | F15: 97 | G15: 6.98 | H15: 1390 | I15: 1487 | J15: 1350 | K15: 315331 | L15: 443981945 | M15: 114341648634 | N15: 76894182
A16: 001040 | B16: 종목159 | C16: KOSPI | E16: 172000 | F16: 800 | G16: 0.47 | H16: 170900 | I16: 175600 | J16: 169400 | K16: 122220 | L16: 21001321400 | M16: 5018443656000 | N16: 29176998
A17: 079160 | B17: CJ CGV | C17: KOSPI | E17: 5950 | F17: -50 | G17: -0.83 | H17: 5940 | I17: 6000 | J17: 5780 | K17: 344935 | L17: 2040614265 | M17: 985209901200 | N17: 165581496
A18: 035760 | B18: CJ ENM | C18: KOSDAQ GLOBAL | D18: 중견기업부 | E18: 64600 | F18: 1800 | G18: 2.87 | H18: 62800 | I18: 65100 | J18: 62600 | K18: 54276 | L18: 3496091200 | M18: 1416623348400 | N18: 21929154
A19: 311690 | B19: CJ 바이오사이언스 | C19: KOSDAQ | D19: 기술성장기업부 | E19: 9320 | F19: -320 | G19: -3.32 | H19: 9640 | I19: 9640 | J19: 9280 | K19: 26999 | L19: 252260985 | M19: 121770105840 | N19: 13065462
A20: 00104K | B20: CJ4우(전환) | C20: KOSPI | E20: 152500 | F20: -300 | G20: -0.2 | H20: 152400 | I20: 154900 | J20: 150300 | K20: 7853 | L20: 1194044350 | M20: 644543080000 | N20: 4226512
A21: 000120 | B21: 종목182 | C21: KOSPI | E21: 94600 | F21: 1400 | G21: 1.5 | H21: 93200 | I21: 95300 | J21: 92800 | K21: 49711 | L21: 4686350150 | M21: 2158047742400 | N21: 22812344
A22: 011150 | B22: CJ씨푸드 | C22: KOSPI | E22: 2855 | F22: -45 | G22: -1.55 | H22: 2885 | I22: 2890 | J22: 2810 | K22: 892173 | L22: 2545899199 | M22: 102582356915 | N22: 35930773
A23: 011155 | B23: CJ씨푸드1우 | C23: KOSPI | E23: 16400 | F23: -900 | G23: -5.2 | H23: 16810 | I23: 16810 | J23: 16030 | K23: 9976 | L23: 164257500 | M23: 3280000000 | N23: 200000
A24: 001045 | B24: CJ우 | C24: KOSPI | E24: 89300 | F24: 500 | G24: 0.56 | H24: 88900 | I24: 90300 | J24: 87900 | K24: 1980 | L24: 176597800 | M24: 201837913900 | N24: 2260223
A25: 097950 | B25: 종목017 | C25: KOSPI | E25: 208000 | F25: -1500 | G25: -0.72 | H25: 209500 | I25: 210000 | J25: 207500 | K25: 40062 | L25: 8347646250 | M25: 3131270688000 | N25: 15054186
A26: 097955 | B26: CJ제일제당 우 | C26: KOSPI | E26: 138000 | F26: 300 | G26: 0.22 | H26: 137900 | I26: 138600 | J26: 137500 | K26: 2915 | L26: 402274700 | M26: 183185754000 | N26: 1327433
A27: 051500 | B27: CJ프레시웨이 | C27: KOSDAQ | D27: 우량기업부 | E27: 26750 | F27: -450 | G27: -1.65 | H27: 26900 | I27: 27150 | J27: 26500 | K27: 19476 | L27: 520212900 | M27: 317564925500 | N27: 11871586
A28: 058820 | B28: CMG제약 | C28: KOSDAQ | D28: 중견기업부 | E28: 1858 | F28: -4 | G28: -0.21 | H28: 1855 | I28: 1874 | J28: 1855 | K28: 186467 | L28: 347067717 | M28: 274690776014 | N28: 147842183
A29: 056730 | B29: CNT85 | C29: KOSDAQ | D29: 벤처기업부 | E29: 601 | F29: 1 | G29: 0.17 | H29: 603 | I29: 603 | J29: 593 | K29: 18540 | L29: 11095264 | M29: 44540822786 | N29: 74111186
A30: 000480 | B30: CR홀딩스 | C30: KOSPI | E30: 4835 | F30: -35 | G30: -0.72 | H30: 4870 | I30: 4870 | J30: 4825 | K30: 25752 | L30: 124559746 | M30: 226715519150 | N30: 46890490
A31: 065770 | B31: CS | C31: KOSDAQ | D31: 벤처기업부 | E31: 776 | F31: -2 | G31: -0.26 | H31: 778 | I31: 786 | J31: 775 | K31: 74714 | L31: 58186207 | M31: 15063036880 | N31: 19411130
A32: 083660 | B32: CSA 코스믹 | C32: KOSDAQ | D32: 중견기업부 | E32: 482 | F32: -23 | G32: -4.55 | H32: 504 | I32: 505 | J32: 479 | K32: 508485 | L32: 248132621 | M32: 30283799238 | N32: 62829459
A33: 000590 | B33: CS홀딩스 | C33: KOSPI | E33: 77500 | F33: 100 | G33: 0.13 | H33: 77000 | I33: 77500 | J33: 76500 | K33: 159 | L33: 12260600 | M33: 89472355000 | N33: 1154482
A34: 012030 | B34: DB | C34: KOSPI | E34: 1474 | F34: -1 | G34: -0.07 | H34: 1475 | I34: 1485 | J34: 1461 | K34: 236591 | L34: 349038306 | M34: 296530377242 | N34: 201173933
A35: 477760 | B35: DB금융스팩12호 | C35: KOSDAQ | D35: SPAC(소속부없음) | E35: 2125 | F35: -5 | G35: -0.23 | H35: 2125 | I35: 2130 | J35: 2115 | K35: 1867 | L35: 3972700 | M35: 12410000000 | N35: 5840000
A36: 005830 | B36: 종목161 | C36: KOSPI | E36: 131100 | F36: 2100 | G36: 1.63 | H36: 129300 | I36: 131700 | J36: 128400 | K36: 154324 | L36: 20130430340 | M36: 9281880000000 | N36: 70800000
A37: 016610 | B37: DB증권 | C37: KOSPI | E37: 10850 | F37: 150 | G37: 1.4 | H37: 10700 | I37: 10910 | J37: 10590 | K37: 54682 | L37: 590619390 | M37: 460543320650 | N37: 42446389
A38: 000990 | B38: DB하이텍 | C38: KOSPI | E38: 67600 | F38: 500 | G38: 0.75 | H38: 66800 | I38: 68100 | J38: 66100 | K38: 307807 | L38: 20672310800 | M38: 2940910148800 | N38: 43504588
A39: 099520 | B39: DGI | C39: KOSDAQ | D39: 관리종목(소속부없음) | E39: 1284 | F39: 0 | G39: 0 | H39: 0 | I39: 0 | J39: 0 | K39: 0 | L39: 0 | M39: 58141862016 | N39: 45281824
A40: 000300 | B40: DH오토넥스 | C40: KOSPI | E40: 1984 | F40: 0 | G40: 0 | H40: 0 | I40: 0 | J40: 0 | K40: 0 | L40: 0 | M40: 164422234240 | N40: 82874110
A41: 290120 | B41: DH오토리드 | C41: KOSDAQ | D41: 우량기업부 | E41: 2460 | F41: 25 | G41: 1.03 | H41: 2435 | I41: 2470 | J41: 2405 | K41: 14039 | L41: 34320485 | M41: 38927652540 | N41: 15824249
A42: 025440 | B42: DH오토웨어 | C42: KOSDAQ | D42: 중견기업부 | E42: 778 | F42: 9 | G42: 1.17 | H42: 760 | I42: 794 | J42: 760 | K42: 140628 | L42: 108496379 | M42: 37951792272 | N42: 48781224
A43: 001530 | B43: DI동일 | C43: KOSPI | E43: 19650 | F43: -50 | G43: -0.25 | H43: 19820 | I43: 20100 | J43: 19490 | K43: 34517 | L43: 682209395 | M43: 387680352000 | N43: 19729280
A44: 015590 | B44: DKME | C44: KOSPI | E44: 515 | F44: 0 | G44: 0 | H44: 0 | I44: 0 | J44: 0 | K44: 0 | L44: 0 | M44: 122045495160 | N44: 236981544
A45: 000210 | B45: 종목076 | C45: KOSPI | E45: 37650 | F45: 100 | G45: 0.27 | H45: 37550 | I45: 37950 | J45: 37150 | K45: 30380 | L45: 1145244000 | M45: 788989032600 | N45: 20955884
A46: 000215 | B46: DL우 | C46: KOSPI | E46: 23550 | F46: -250 | G46: -1.05 | H46: 23800 | I46: 23800 | J46: 23100 | K46: 6211 | L46: 144953750 | M46: 39708008250 | N46: 1686115
A47: 375500 | B47: 종목178 | C47: KOSPI | E47: 41150 | F47: 0 | G47: 0 | H47: 40900 | I47: 41700 | J47: 40850 | K47: 87986 | L47: 3637442000 | M47: 1592242586450 | N47: 38693623
A48: 37550L | B48: DL이앤씨2우(전환) | C48: KOSPI | E48: 30500 | F48: 150 | G48: 0.49 | H48: 29350 | I48: 31100 | J48: 29350 | K48: 2087 | L48: 62259650 | M48: 64414505500 | N48: 2111951
A49: 37550K | B49: DL이앤씨우 | C49: KOSPI | E49: 21700 | F49: 0 | G49: 0 | H49: 21600 | I49: 22300 | J49: 21500 | K49: 5049 | L49: 109684850 | M49: 45871304500 | N49: 2113885
A50: 068790 | B50: DMS | C50: KOSDAQ | D50: 관리종목(소속부없음) | E50: 6330 | F50: 0 | G50: 0 | H50: 0 | I50: 0 | J50: 0 | K50: 0 | L50: 0 | M50: 149939488590 | N50: 23687123
A51: 007340 | B51: 종목135 | C51: KOSPI | E51: 24400 | F51: 250 | G51: 1.04 | H51: 24300 | I51: 24600 | J51: 23850 | K51: 102276 | L51: 2477328125 | M51: 1427665106000 | N51: 58510865
A52: 004840 | B52: DRB동일 | C52: KOSPI | E52: 4955 | F52: -25 | G52: -0.5 | H52: 4945 | I52: 4995 | J52: 4945 | K52: 12725 | L52: 63150655 | M52: 98753150000 | N52: 19930000
A53: 241520 | B53: DSC인베스트먼트 | C53: KOSDAQ | D53: 중견기업부 | E53: 7220 | F53: -90 | G53: -1.23 | H53: 7310 | I53: 7330 | J53: 7160 | K53: 197632 | L53: 1427581885 | M53: 194940000000 | N53: 27000000
A54: 155660 | B54: DSR | C54: KOSPI | E54: 3905 | F54: 125 | G54: 3.31 | H54: 3780 | I54: 3905 | J54: 3770 | K54: 25926 | L54: 100230614 | M54: 62480000000 | N54: 16000000
A55: 069730 | B55: DSR제강 | C55: KOSPI | E55: 3840 | F55: 25 | G55: 0.66 | H55: 3825 | I55: 3850 | J55: 3810 | K55: 8347 | L55: 31908795 | M55: 55296000000 | N55: 14400000
A56: 017860 | B56: DS단석 | C56: KOSPI | E56: 18170 | F56: -100 | G56: -0.55 | H56: 18240 | I56: 18330 | J56: 18030 | K56: 62173 | L56: 1127577155 | M56: 319505132040 | N56: 17584212
A57: 180400 | B57: DXVX | C57: KOSDAQ | D57: 관리종목(소속부없음) | E57: 3140 | F57: 110 | G57: 3.63 | H57: 3065 | I57: 3300 | J57: 2910 | K57: 1027305 | L57: 3246794404 | M57: 154549016480 | N57: 49219432
A58: 092780 | B58: DYP | C58: KOSPI | E58: 3320 | F58: 45 | G58: 1.37 | H58: 3285 | I58: 3360 | J58: 3285 | K58: 20515 | L58: 68161620 | M58: 43719287200 | N58: 13168460
A59: 017940 | B59: E1 | C59: KOSPI | E59: 83300 | F59: 400 | G59: 0.48 | H59: 83000 | I59: 83600 | J59: 82500 | K59: 6212 | L59: 516373900 | M59: 571438000000 | N59: 6860000
A60: 418620 | B60: E8 | C60: KOSDAQ | D60: 기술성장기업부 | E60: 1514 | F60: -40 | G60: -2.57 | H60: 1554 | I60: 1600 | J60: 1505 | K60: 67956 | L60: 105294358 | M60: 19455622178 | N60: 12850477
A61: 245620 | B61: EDGC | C61: KOSDAQ | D61: 관리종목(소속부없음) | E61: 415 | F61: 0 | G61: 0 | H61: 0 | I61: 0 | J61: 0 | K61: 0 | L61: 0 | M61: 57474989665 | N61: 138493951
A62: 037370 | B62: EG | C62: KOSDAQ | D62: 벤처기업부 | E62: 5460 | F62: -80 | G62: -1.44 | H62: 5480 | I62: 5600 | J62: 5450 | K62: 9448 | L62: 51801180 | M62: 47092347120 | N62: 8624972
A63: 278990 | B63: EMB | C63: KONEX | D63: 일반기업부 | E63: 3400 | F63: 0 | G63: 0 | H63: 3400 | I63: 3400 | J63: 2900 | K63: 101 | L63: 319400 | M63: 27420241800 | N63: 8064777
A64: 365550 | B64: ESR켄달스퀘어리츠 | C64: KOSPI | E64: 4265 | F64: 10 | G64: 0.24 | H64: 4250 | I64: 4265 | J64: 4210 | K64: 158047 | L64: 671189420 | M64: 1049569585000 | N64: 246089000
A65: 050120 | B65: ES큐브 | C65: KOSDAQ | D65: 중견기업부 | E65: 2940 | F65: 80 | G65: 2.8 | H65: 2830 | I65: 2940 | J65: 2830 | K65: 6785 | L65: 19324175 | M65: 39878412840 | N65: 13564086
A66: 383220 | B66: 종목179 | C66: KOSPI | E66: 68500 | F66: -1500 | G66: -2.14 | H66: 70100 | I66: 70500 | J66: 68100 | K66: 62463 | L66: 4296761800 | M66: 2624034637500 | N66: 38307075
A67: 007700 | B67: F&F홀딩스 | C67: KOSPI | E67: 18690 | F67: -410 | G67: -2.15 | H67: 19100 | I67: 19450 | J67: 18660 | K67: 24584 | L67: 462373040 | M67: 731047519230 | N67: 39114367
A68: 214270 | B68: FSN | C68: KOSDAQ | D68: 중견기업부 | E68: 1927 | F68: -34 | G68: -1.73 | H68: 1962 | I68: 2010 | J68: 1921 | K68: 190003 | L68: 374361511 | M68: 84192477993 | N68: 43690959
A69: 130500 | B69: GH신소재 | C69: KOSDAQ | D69: 우량기업부 | E69: 2430 | F69: 20 | G69: 0.83 | H69: 2410 | I69: 2450 | J69: 2390 | K69: 33461 | L69: 81001335 | M69: 35344476360 | N69: 14545052
A70: 114090 | B70: 종목152 | C70: KOSPI | E70: 14970 | F70: 340 | G70: 2.32 | H70: 14520 | I70: 14980 | J70: 14500 | K70: 93495 | L70: 1385996855 | M70: 925979379900 | N70: 61855670
A71: 900290 | B71: GRT | C71: KOSDAQ | D71: 외국기업(소속부없음) | E71: 3110 | F71: -90 | G71: -2.81 | H71: 3220 | I71: 3220 | J71: 3110 | K71: 186352 | L71: 587909170 | M71: 251443500000 | N71: 80850000
A72: 078930 | B72: 종목044 | C72: KOSPI | E72: 56300 | F72: 2300 | G72: 4.26 | H72: 54000 | I72: 56400 | J72: 53500 | K72: 237712 | L72: 13178948000 | M72: 5231135781400 | N72: 92915378
A73: 083450 | B73: GST | C73: KOSDAQ | D73: 우량기업부 | E73: 28850 | F73: 1800 | G73: 6.65 | H73: 26850 | I73: 30000 | J73: 26850 | K73: 1643113 | L73: 47280695475 | M73: 531705500000 | N73: 18430000
A74: 006360 | B74: 종목162 | C74: KOSPI | E74: 19700 | F74: 390 | G74: 2.02 | H74: 19300 | I74: 19860 | J74: 19220 | K74: 488134 | L74: 9607178215 | M74: 1685955353000 | N74: 85581490
A75: 001250 | B75: GS글로벌 | C75: KOSPI | E75: 2315 | F75: -15 | G75: -0.64 | H75: 2335 | I75: 2350 | J75: 2255 | K75: 1785871 | L75: 4094519629 | M75: 191065663660 | N75: 82533764
A76: 007070 | B76: 종목163 | C76: KOSPI | E76: 20100 | F76: -50 | G76: -0.25 | H76: 20000 | I76: 20200 | J76: 19840 | K76: 94545 | L76: 1894284780 | M76: 1680509041500 | N76: 83607415
A77: 078935 | B77: GS우 | C77: KOSPI | E77: 48100 | F77: 450 | G77: 0.94 | H77: 47650 | I77: 48150 | J77: 47400 | K77: 4792 | L77: 229294575 | M77: 85850130600 | N77: 1784826
A78: 499790 | B78: 종목053 | C78: KOSPI | E78: 42000 | F78: 200 | G78: 0.48 | H78: 41900 | I78: 42250 | J78: 41050 | K78: 139912 | L78: 5821760625 | M78: 832895322000 | N78: 19830841
A79: 297890 | B79: HB솔루션 | C79: KOSDAQ | D79: 우량기업부 | E79: 2100 | F79: 10 | G79: 0.48 | H79: 2070 | I79: 2150 | J79: 2070 | K79: 289387 | L79: 611493262 | M79: 153595919400 | N79: 73140914
A80: 440290 | B80: HB인베스트먼트 | C80: KOSDAQ | D80: 중견기업부 | E80: 2140 | F80: -40 | G80: -1.83 | H80: 2190 | I80: 2195 | J80: 2130 | K80: 266305 | L80: 572966037 | M80: 58863760200 | N80: 27506430
A81: 078150 | B81: HB테크놀러지 | C81: KOSDAQ | D81: 우량기업부 | E81: 1857 | F81: 6 | G81: 0.32 | H81: 1852 | I81: 1888 | J81: 1828 | K81: 438890 | L81: 819407638 | M81: 172173456012 | N81: 92715916
A82: 225530 | B82: HC보광산업 | C82: KOSDAQ | D82: 우량기업부 | E82: 2915 | F82: 25 | G82: 0.87 | H82: 2910 | I82: 2945 | J82: 2890 | K82: 8226 | L82: 23977600 | M82: 105927389205 | N82: 36338727
A83: 060560 | B83: HC홈센타 | C83: KOSDAQ | D83: 중견기업부 | E83: 744 | F83: 0 | G83: 0 | H83: 738 | I83: 769 | J83: 738 | K83: 92085 | L83: 69330022 | M83: 94986126600 | N83: 127669525
A84: 012630 | B84: HDC | C84: KOSPI | E84: 18710 | F84: 1150 | G84: 6.55 | H84: 17570 | I84: 18960 | J84: 17570 | K84: 305400 | L84: 5676186500 | M84: 1117767599910 | N84: 59741721
A85: 039570 | B85: HDC랩스 | C85: KOSPI | E85: 8440 | F85: 10 | G85: 0.12 | H85: 8410 | I85: 8520 | J85: 8390 | K85: 9362 | L85: 78913950 | M85: 219082152440 | N85: 25957601
A86: 089470 | B86: HDC현대EP | C86: KOSPI | E86: 4290 | F86: 35 | G86: 0.82 | H86: 4280 | I86: 4290 | J86: 4225 | K86: 20421 | L86: 86775495 | M86: 136851000000 | N86: 31900000
A87: 294870 | B87: HDC현대산업개발 | C87: KOSPI | E87: 21900 | F87: 1200 | G87: 5.8 | H87: 20750 | I87: 22200 | J87: 20750 | K87: 446167 | L87: 9744327000 | M87: 1443370527000 | N87: 65907330
A88: 009540 | B88: 종목010 | C88: KOSPI | E88: 407000 | F88: -3500 | G88: -0.85 | H88: 406000 | I88: 408000 | J88: 404000 | K88: 123304 | L88: 50033705250 | M88: 28804658212000 | N88: 70773116
A89: 267250 | B89: 종목199 | C89: KOSPI | E89: 188500 | F89: -500 | G89: -0.26 | H89: 187500 | I89: 188500 | J89: 185700 | K89: 126671 | L89: 23730560400 | M89: 14890196522500 | N89: 78993085
A90: 267270 | B90: HD현대건설기계 | C90: KOSPI | E90: 98400 | F90: -6100 | G90: -5.84 | H90: 101100 | I90: 101200 | J90: 96400 | K90: 255281 | L90: 25130354600 | M90: 1707989119200 | N90: 17357613
A91: 443060 | B91: 종목180 | C91: KOSPI | E91: 193500 | F91: -2500 | G91: -1.28 | H91: 195100 | I91: 196100 | J91: 190800 | K91: 48281 | L91: 9316416750 | M91: 8674452135000 | N91: 44829210
A92: 071970 | B92: 종목119 | C92: KOSPI | E92: 89500 | F92: -1700 | G92: -1.86 | H92: 91100 | I92: 91300 | J92: 88100 | K92: 217908 | L92: 19463209200 | M92: 3035973802500 | N92: 33921495
A93: 322000 | B93: HD현대에너지솔루션 | C93: KOSPI | E93: 54700 | F93: -1100 | G93: -1.97 | H93: 56400 | I93: 56400 | J93: 54700 | K93: 52239 | L93: 2886921000 | M93: 612640000000 | N93: 11200000
A94: 042670 | B94: 종목039 | C94: KOSPI | E94: 13800 | F94: 0 | G94: 0 | H94: 0 | I94: 0 | J94: 0 | K94: 0 | L94: 0 | M94: 2606147084400 | N94: 188851238
A95: 267260 | B95: 종목048 | C95: KOSPI | E95: 774000 | F95: -14000 | G95: -1.78 | H95: 779000 | I95: 785000 | J95: 774000 | K95: 91306 | L95: 70860199000 | M95: 27900482490000 | N95: 36047135
A96: 329180 | B96: 종목203 | C96: KOSPI | E96: 509000 | F96: -14000 | G96: -2.68 | H96: 517000 | I96: 520000 | J96: 509000 | K96: 141632 | L96: 72619243500 | M96: 53425263525000 | N96: 104961225
A97: 376270 | B97: HEM파마 | C97: KOSDAQ | D97: 기술성장기업부 | E97: 45850 | F97: -1600 | G97: -3.37 | H97: 47450 | I97: 47450 | J97: 45000 | K97: 62768 | L97: 2869956125 | M97: 327952532950 | N97: 7152727
A98: 097230 | B98: HJ중공업 | C98: KOSPI | E98: 21050 | F98: -550 | G98: -2.55 | H98: 21600 | I98: 21650 | J98: 20850 | K98: 833825 | L98: 17544702825 | M98: 1900716991200 | N98: 90295344
A99: 195940 | B99: HK이노엔 | C99: KOSDAQ GLOBAL | D99: 우량기업부 | E99: 49300 | F99: -550 | G99: -1.1 | H99: 49600 | I99: 49650 | J99: 49050 | K99: 178215 | L99: 8788221575 | M99: 1396663626300 | N99: 28329891
A100: 014790 | B100: HL D&I | C100: KOSPI | E100: 2700 | F100: 80 | G100: 3.05 | H100: 2655 | I100: 2710 | J100: 2615 | K100: 71796 | L100: 192288743 | M100: 102218222700 | N100: 37858601
...

Sheet 평가액검증(수익증권)
B1: 한빛코스피레버리지증권상장지수투자신탁(주식-파생형)
B2: ='C1_정산표'!B2 -> 45657 | G2: Prepared by : | H2: ='C1_정산표'!H2 -> SJ
B3: 평가액검증 | G3: Reviewed by :
A5: Column1 | B5: Column2 | C5: Column3 | D5: Column4 | E5: Column5 | F5: Column6 | G5: Column7 | H5: Column8
A6: 종목코드 | B6: 표준코드 | C6: 종목명 | D6: 좌수 | E6: 취득가액 | F6: 기준가격 | G6: 평가금액 | H6: 평가손익 | I6: 평가금액정확성 | J6: 정산가검증 A | K6: 정산가검증 B
A7: =수익증권명세!A3 -> KR7102110004 | B7: =수익증권명세!B3 -> KR7102110004 | C7: =수익증권명세!C3 -> 종목ETF001 | D7: =수익증권명세!G3 -> 401506 | E7: =수익증권명세!K3 -> 23417443577 | F7: =수익증권명세!I3 -> 60930 | G7: =수익증권명세!J3 -> 24463760580 | H7: =수익증권명세!L3 -> 1046317003 | I7: =D7*F7=G7 -> TRUE | J7: =INDEX(KRX정보시스템_ETF!$A$1:$R$2000,MATCH('평가액검증(수익증권)'!C7,KRX정보시스템_ETF!$B:$B,0),MATCH(KRX정보시스템_ETF!$C$1,KRX정보시스템_ETF!$1:$1,0)) -> 60930 | K7: =IF(F7=0,"TRUE",IF(F7=J7,"TRUE","FALSE")) -> TRUE

Sheet KRX정보시스템_ETF
A1: 종목코드 | B1: 종목명 | C1: 종가 | D1: 대비 | E1: 등락률 | F1: 순자산가치(NAV) | G1: 시가 | H1: 고가 | I1: 저가 | J1: 거래량 | K1: 거래대금 | L1: 시가총액 | M1: 순자산총액 | N1: 상장좌수 | O1: 기초지수_지수명 | P1: 기초지수_종가 | Q1: 기초지수_대비 | R1: 기초지수_등락률
A2: 491610 | B2: 1Q CD금리액티브(합성) | C2: 102975 | D2: 35 | E2: 0.03 | F2: 102942.94 | G2: 102960 | H2: 102975 | I2: 102960 | J2: 4996 | K2: 514407646 | L2: 230252100000 | M2: 240165889323 | N2: 2236000 | O2: KIS 하나 CD금리 총수익지수 | P2: 11650.99 | Q2: 2.74 | R2: 0.02
A3: 451060 | B3: 1Q K200액티브 | C3: 19795 | D3: 70 | E3: 0.35 | F3: 19827.18 | G3: 19705 | H3: 19855 | I3: 19675 | J3: 75541 | K3: 1494874190 | L3: 154401000000 | M3: 154652008289 | N3: 7800000 | O3: 코스피 200 | P3: 605.98 | Q3: 0.29 | R3: 0.05
A4: 0103T0 | B4: 1Q K소버린AI | C4: 10005 | D4: -10 | E4: -0.1 | F4: 10012.11 | G4: 10015 | H4: 10035 | I4: 9915 | J4: 152734 | K4: 1522706804 | L4: 33516750000 | M4: 33540578646 | N4: 3350000 | O4: iSelect K소버린AI 지수 | P4: 1974.89 | Q4: -6.34 | R4: -0.32
A5: 463290 | B5: 1Q 단기금융채액티브 | C5: 107215 | D5: 20 | E5: 0.02 | F5: 107216.56 | G5: 107265 | H5: 107265 | I5: 107205 | J5: 1963 | K5: 210470891 | L5: 167255400000 | M5: 167257833015 | N5: 1560000 | O5: MK 머니마켓 지수(총수익) | P5: 14481.79 | Q5: 3.19 | R5: 0.02
A6: 0131W0 | B6: 1Q 단기특수은행채액티브 | C6: 100300 | D6: 35 | E6: 0.03 | F6: 100295.73 | G6: 100295 | H6: 100305 | I6: 100295 | J6: 173 | K6: 17352670 | L6: 105114400000 | M6: 120154278916 | N6: 1048000 | O6: KIS 단기특수은행채 지수(총수익) | P6: 115.11 | Q6: 0.03 | R6: 0.03
A7: 479080 | B7: 1Q 머니마켓액티브 | C7: 52620 | D7: 5 | E7: 0.01 | F7: 52621.36 | G7: 52620 | H7: 52625 | I7: 52620 | J7: 31758 | K7: 1671172152 | L7: 1007462520000 | M7: 1135989981848 | N7: 19146000 | O7: KIS-하나 MMF 지수(총수익) | P7: 118.46 | Q7: 0.03 | R7: 0.03
A8: 0026S0 | B8: 1Q 미국S&P500 | C8: 12085 | D8: 35 | E8: 0.29 | F8: 12071.67 | G8: 12020 | H8: 12085 | I8: 11990 | J8: 330564 | K8: 3976618895 | L8: 188526000000 | M8: 237811821334 | N8: 15600000 | O8: S&P 500 | P8: 6896.24 | Q8: -9.5 | R8: -0.14
A9: 0052S0 | B9: 1Q 미국S&P500미국채혼합50액티브 | C9: 11410 | D9: 35 | E9: 0.31 | F9: 11408.58 | G9: 11365 | H9: 11410 | I9: 11325 | J9: 353743 | K9: 4021983605 | L9: 185983000000 | M9: 192805003698 | N9: 16300000 | O9: S&P 500 and Short-Term Treasury 50/50 Blend Index | P9: 276.17 | Q9: -0.17 | R9: -0.06
A10: 0069M0 | B10: 1Q 미국나스닥100 | C10: 12195 | D10: 10 | E10: 0.08 | F10: 12201.31 | G10: 12120 | H10: 12195 | I10: 12115 | J10: 356651 | K10: 4333883340 | L10: 73170000000 | M10: 75648141659 | N10: 6000000 | O10: NASDAQ 100 | P10: 25462.56 | Q10: -63 | R10: -0.25
A11: 0111P0 | B11: 1Q 미국나스닥100미국채혼합50액티브 | C11: 10420 | D11: 30 | E11: 0.29 | F11: 10405.2 | G11: 10370 | H11: 10420 | I11: 10320 | J11: 283347 | K11: 2941610538 | L11: 141712000000 | M11: 145672864086 | N11: 13600000 | O11: Nasdaq-100 US T-Bills 0-6 Month 50/50 Index | P11: 2875.8 | Q11: -3.32 | R11: -0.12
A12: 0083S0 | B12: 1Q 미국메디컬AI | C12: 11535 | D12: -40 | E12: -0.35 | F12: 11552.29 | G12: 11495 | H12: 11545 | I12: 11440 | J12: 110969 | K12: 1273753465 | L12: 49600500000 | M12: 49674838852 | N12: 4300000 | O12: KEDI 미국메디컬AI 지수 | P12: 2070.33 | Q12: -14.51 | R12: -0.7
A13: 0004G0 | B13: 1Q 미국배당TOP30 | C13: 8985 | D13: 5 | E13: 0.06 | F13: 8944.84 | G13: 8960 | H13: 8985 | I13: 8915 | J13: 17427 | K13: 155938778 | L13: 7188000000 | M13: 7155871987 | N13: 800000 | O13: Solactive U.S. Dividend TOP 30 Index PR | P13: 4050.72 | Q13: -3.93 | R13: -0.1
... A54: 494330 | B54: ACE 라이프자산주주가치액티브 | C54: 15855 | D54: 35 | E54: 0.22 | F54: 15815.53 | G54: 15740 | H54: 15855 | I54: 15720 | J54: 31380 | K54: 494664477 | L54: 54699750000 | M54: 54563592998 | N54: 3450000 | O54: FnGuide 기업가치 지수(시장가격) | P54: 2316.09 | Q54: -12.18 | R54: -0.52
A55: 265690 | B55: ACE 러시아MSCI(합성) | C55: 8535 | D55: 0 | E55: 0 | F55: 47.98 | G55: 0 | H55: 0 | I55: 0 | J55: 0 | K55: 0 | L55: 15789750000 | M55: 88768672 | N55: 1850000 | O55: MSCI Russia 25% Capped Price Return Index | P55: - | Q55: - | R55: -
A56: 152500 | B56: ACE 레버리지 | C56: 19385 | D56: 135 | E56: 0.7 | F56: 19394.6 | G56: 19120 | H56: 19500 | I56: 19025 | J56: 27743 | K56: 536945495 | L56: 23262000000 | M56: 23273524582 | N56: 1200000 | O56: 코스피 200 | P56: 605.98 | Q56: 0.29 | R56: 0.05
A57: 483330 | B57: ACE 마이크로소프트밸류체인액티브 | C57: 12655 | D57: -65 | E57: -0.51 | F57: 12618.62 | G57: 12720 | H57: 12720 | I57: 12645 | J57: 24060 | K57: 304411393 | L57: 16451500000 | M57: 15142349989 | N57: 1300000 | O57: KEDI 글로벌생성형AI 지수 | P57: 4314.01 | Q57: -2.39 | R57: -0.06
A58: 487340 | B58: ACE 머니마켓액티브 | C58: 103530 | D58: 35 | E58: 0.03 | F58: 103501.45 | G58: 103520 | H58: 103530 | I58: 103520 | J58: 16953 | K58: 1755099485 | L58: 465263820000 | M58: 465135507318 | N58: 4494000 | O58: MK-KAP 머니마켓 총수익지수 | P58: 118.9 | Q58: 0.01 | R58: 0.01
A59: 0085P0 | B59: ACE 미국10년국채액티브 | C59: 10605 | D59: 85 | E59: 0.81 | F59: 10598.59 | G59: 10565 | H59: 10605 | I59: 10540 | J59: 255265 | K59: 2698516017 | L59: 58327500000 | M59: 58292254281 | N59: 5500000 | O59: ICE U.S. Treasury 7-10 Year Bond Index (Total Return) | P59: 114.94 | Q59: -0.12 | R59: -0.11
A60: 0085N0 | B60: ACE 미국10년국채액티브(H) | C60: 10160 | D60: 15 | E60: 0.15 | F60: 10154.21 | G60: 10085 | H60: 10165 | I60: 10080 | J60: 138845 | K60: 1410392600 | L60: 18288000000 | M60: 18277584916 | N60: 1800000 | O60: ICE U.S. Treasury 7-10 Year Bond Index (Total Return) | P60: 114.94 | Q60: -0.12 | R60: -0.11
A61: 452250 | B61: ACE 미국30년국채선물레버리지(합성 H) | C61: 5435 | D61: 25 | E61: 0.46 | F61: 5456.69 | G61: 5420 | H61: 5445 | I61: 5405 | J61: 49751 | K61: 269807200 | L61: 68752750000 | M61: 69027089004 | N61: 12650000 | O61: S&P Ultra T-Bond Futures Index(ER) | P61: 110.81 | Q61: -0.12 | R61: -0.11
A62: 476760 | B62: ACE 미국30년국채액티브 | C62: 9930 | D62: 70 | E62: 0.71 | F62: 9932.17 | G62: 9880 | H62: 9935 | I62: 9865 | J62: 353028 | K62: 3498598311 | L62: 340599000000 | M62: 340673523269 | N62: 34300000 | O62: Bloomberg U.S Treasury 20+ Year Total Return Index | P62: 594.25 | Q62: -1.02 | R62: -0.17
A63: 453850 | B63: ACE 미국30년국채액티브(H) | C63: 7680 | D63: 15 | E63: 0.2 | F63: 7689.16 | G63: 7690 | H63: 7695 | I63: 7670 | J63: 1677792 | K63: 12891109861 | L63: 2197248000000 | M63: 2199868775471 | N63: 286100000 | O63: Bloomberg U.S Treasury 20+ Year Total Return Index | P63: 594.25 | Q63: -1.02 | R63: -0.17
A64: 476750 | B64: ACE 미국30년국채엔화노출액티브(H) | C64: 8615 | D64: 100 | E64: 1.17 | F64: 8590.67 | G64: 8560 | H64: 8615 | I64: 8550 | J64: 449792 | K64: 3855232194 | L64: 96488000000 | M64: 96215517192 | N64: 11200000 | O64: Bloomberg U.S. Treasury 20+ Year Total Return Index T1530 JPY Currency Hedged | P64: 111.82 | Q64: 0.38 | R64: 0.34
A65: 480030 | B65: ACE 미국500데일리타겟커버드콜(합성) | C65: 10765 | D65: 30 | E65: 0.28 | F65: 10760.8 | G65: 10725 | H65: 10765 | I65: 10665 | J65: 56584 | K65: 607138655 | L65: 152863000000 | M65: 152803290892 | N65: 14200000 | O65: Bloomberg US 500 Large Cap Premium Decrement 15% Distribution Index | P65: 1120.92 | Q65: -1.94 | R65: -0.17
A66: 0118Z0 | B66: ACE 미국AI테크핵심산업액티브 | C66: 8315 | D66: -170 | E66: -2 | F66: 8282.93 | G66: 8495 | H66: 8495 | I66: 8290 | J66: 164755 | K66: 1369459525 | L66: 145928250000 | M66: 129627890554 | N66: 17550000 | O66: Akros U.S. AI Innovator Price Return Index | P66: 17238.23 | Q66: -129.33 | R66: -0.74
A67: 280320 | B67: ACE 미국IT인터넷(합성 H) | C67: 20605 | D67: 50 | E67: 0.24 | F67: 20688.48 | G67: 20555 | H67: 20710 | I67: 20555 | J67: 1595 | K67: 32865975 | L67: 16484000000 | M67: 16550786858 | N67: 800000 | O67: 다우존스 인터넷 종합지수 | P67: 1242.64 | Q67: -2.04 | R67: -0.16
... A1059: 140950 | B1059: 파워 코스피100 | C1059: 46995 | D1059: 325 | E1059: 0.7 | F1059: 46968.32 | G1059: 46655 | H1059: 47055 | I1059: 46655 | J1059: 4606 | K1059: 216248574 | L1059: 26317200000 | M1059: 26302258551 | N1059: 560000 | O1059: 코스피 100 | P1059: 4620.99 | Q1059: 5.3 | R1059: 0.11

Sheet 평가액검증(선물)
G1: 한빛코스피레버리지증권상장지수투자신탁(주식-파생형)
G2: 44926 | L2: Prepared by : | M2: ='C1_정산표'!H2 -> SJ
G3: 평가액검증 | L3: Reviewed by :
A12: Column1 | B12: Column2 | C12: Column3 | E12: Column4 | F12: Column5 | G12: Column6 | H12: Column7 | I12: Column8 | J12: Column9 | K12: Column10 | L12: Column11 | M12: Column12 | N12: Test 1 | O12: Test 2
A13: 매매처 | B13: 매매처명 | C13: 종목코드 | D13: 표준코드 | E13: 종목명 | F13: 포지션 | G13: 계약수 | H13: 정산가 | I13: 평가금액 | J13: 취득가액 | K13: 정산손익 | L13: 미수입금 | M13: 미지급금 | N13: 평가금액정확성 | O13: 정산가검증 A | P13: 정산가검증 B
A14: 000012 | B14: =선물명세!B3 -> 종목132 | C14: =MID(D14,4,8) -> A0163000 | D14: =선물명세!D3 -> KR4A01630008 | E14: =선물명세!E3 -> 선물2026년03월물 | F14: =선물명세!F3 -> 선물매수 | G14: =선물명세!G3 -> 182 | H14: =선물명세!H3 -> 608 | I14: =선물명세!I3 -> 27664000000 | J14: =선물명세!J3 -> 26650965056 | K14: =선물명세!K3 -> 1013034944 | ... M14: =선물명세!M3 -> 0 | N14: =G14*H14*250000=I14 -> TRUE | O14: =INDEX(KRX정보시스템_코스피200!$A$1:$L$14,MATCH('평가액검증(선물)'!C14,KRX정보시스템_코스피200!$A:$A,0),MATCH(KRX정보시스템_코스피200!$C$1,KRX정보시스템_코스피200!$1:$1,0)) -> 608 | P14: =IF(H14=0,"TRUE",IF(H14=O14,"TRUE","FALSE")) -> TRUE
A15: 000025 | B15: =선물명세!B4 -> 한화투자증권 | C15: =MID(D15,4,8) -> A0163000 | D15: =선물명세!D4 -> KR4A01630008 | E15: =선물명세!E4 -> 선물2026년03월물 | F15: =선물명세!F4 -> 선물매수 | G15: =선물명세!G4 -> 179 | H15: =선물명세!H4 -> 608 | I15: =선물명세!I4 -> 27208000000 | J15: =선물명세!J4 -> 26296087500 | K15: =선물명세!K4 -> 911912500 | ... M15: =선물명세!M4 -> 0 | N15: =G15*H15*250000=I15 -> TRUE | O15: =INDEX(KRX정보시스템_코스피200!$A$1:$L$14,MATCH('평가액검증(선물)'!C15,KRX정보시스템_코스피200!$A:$A,0),MATCH(KRX정보시스템_코스피200!$C$1,KRX정보시스템_코스피200!$1:$1,0)) -> 608 | P15: =IF(H15=0,"TRUE",IF(H15=O15,"TRUE","FALSE")) -> TRUE
A16: 000046 | B16: =선물명세!B5 -> SK증권 | C16: =MID(D16,4,8) -> A0163000 | D16: =선물명세!D5 -> KR4A01630008 | E16: =선물명세!E5 -> 선물2026년03월물 | F16: =선물명세!F5 -> 선물매수 | G16: =선물명세!G5 -> 179 | H16: =선물명세!H5 -> 608 | I16: =선물명세!I5 -> 27208000000 | J16: =선물명세!J5 -> 26071238500 | K16: =선물명세!K5 -> 1136761500 | ... M16: =선물명세!M5 -> 0 | N16: =G16*H16*250000=I16 -> TRUE | O16: =INDEX(KRX정보시스템_코스피200!$A$1:$L$14,MATCH('평가액검증(선물)'!C16,KRX정보시스템_코스피200!$A:$A,0),MATCH(KRX정보시스템_코스피200!$C$1,KRX정보시스템_코스피200!$1:$1,0)) -> 608 | P16: =IF(H16=0,"TRUE",IF(H16=O16,"TRUE","FALSE")) -> TRUE
A17: 000050 | B17: =선물명세!B6 -> iM증권 | C17: =MID(D17,4,8) -> A0163000 | D17: =선물명세!D6 -> KR4A01630008 | E17: =선물명세!E6 -> 선물2026년03월물 | F17: =선물명세!F6 -> 선물매수 | G17: =선물명세!G6 -> 165 | H17: =선물명세!H6 -> 608 | I17: =선물명세!I6 -> 25080000000 | J17: =선물명세!J6 -> 24050546159 | K17: =선물명세!K6 -> 1029453841 | ... M17: =선물명세!M6 -> 0 | N17: =G17*H17*250000=I17 -> TRUE | O17: =INDEX(KRX정보시스템_코스피200!$A$1:$L$14,MATCH('평가액검증(선물)'!C17,KRX정보시스템_코스피200!$A:$A,0),MATCH(KRX정보시스템_코스피200!$C$1,KRX정보시스템_코스피200!$1:$1,0)) -> 608 | P17: =IF(H17=0,"TRUE",IF(H17=O17,"TRUE","FALSE")) -> TRUE
B18: =선물명세!B7 -> 종목170 | C18: =MID(D18,4,8) -> A0163000 | D18: =선물명세!D7 -> KR4A01630008 | E18: =선물명세!E7 -> 선물2026년03월물 | F18: =선물명세!F7 -> 선물매수 | G18: =선물명세!G7 -> 178 | H18: =선물명세!H7 -> 608 | I18: =선물명세!I7 -> 27056000000 | J18: =선물명세!J7 -> 26053215256 | K18: =선물명세!K7 -> 1002784744 | ... M18: =선물명세!M7 -> 0
D19: =선물명세!D8 -> 0 | E19: =선물명세!E8 -> 0 | F19: =선물명세!F8 -> 0 | G19: =선물명세!G8 -> 0 | H19: =선물명세!H8 -> 0 | I19: =선물명세!I8 -> 0 | J19: =선물명세!J8 -> 0 | K19: =선물명세!K8 -> 0 | ... M19: =선물명세!M8 -> 0
D20: =선물명세!D9 -> 0 | E20: =선물명세!E9 -> 0 | F20: =선물명세!F9 -> 0 | G20: =선물명세!G9 -> 0 | H20: =선물명세!H9 -> 0 | I20: =선물명세!I9 -> 0 | J20: =선물명세!J9 -> 0 | K20: =선물명세!K9 -> 0 | ... M20: =선물명세!M9 -> 0
P29: =M29-O29 -> 0

Sheet KRX정보시스템_코스피200
A1: 종목코드 | B1: 종목명 | C1: 종가 | D1: 대비 | E1: 시가 | F1: 고가 | G1: 저가 | H1: 현물가 | I1: 정산가 | J1: 거래량 | K1: 거래대금 | L1: 미결제약정
A2: A0163000 | B2: 코스피200 F 202603 (주간) | C2: 608 | D2: 2.65 | E2: 605.95 | F2: 610.2 | G2: 601.9 | H2: 605.98 | I2: 608 | J2: 141299 | K2: 21468954 | L2: 215446
A3: A0166000 | B3: 코스피200 F 202606 (주간) | C3: 608.4 | D3: 2.65 | E3: 604.55 | F3: 610.25 | G3: 602.5 | H3: 605.98 | I3: 608.4 | J3: 720 | K3: 109361 | L3: 9330
A4: A0169000 | B4: 코스피200 F 202609 (주간) | C4: 609.2 | D4: -0.35 | E4: 609.2 | F4: 609.2 | G4: 609.2 | H4: 605.98 | I4: 609.2 | J4: 1 | K4: 152 | L4: 58
A5: A016C000 | B5: 코스피200 F 202612 (주간) | C5: 611.25 | D5: -1.35 | E5: 611.5 | F5: 611.5 | G5: 611.25 | H5: 605.98 | I5: 611.25 | J5: 2 | K5: 306 | L5: 5937
A6: A0176000 | B6: 코스피200 F 202706 (주간) | C6: - | D6: - | E6: - | F6: - | G6: - | H6: 605.98 | I6: 617.95 | J6: 0 | K6: 0 | L6: 16
A7: A017C000 | B7: 코스피200 F 202712 (주간) | C7: - | D7: - | E7: - | F7: - | G7: - | H7: 605.98 | I7: 624.5 | J7: 0 | K7: 0 | L7: 95
A8: A018C000 | B8: 코스피200 F 202812 (주간) | C8: - | D8: - | E8: - | F8: - | G8: - | H8: 605.98 | I8: 635.4 | J8: 0 | K8: 0 | L8: 1
A9: D016366S | B9: 코스피200 SP 2603-2606 (주간) | C9: 0.45 | D9: 0.45 | E9: 0.45 | F9: 0.55 | G9: 0.2 | H9: 605.98 | I9: 0 | J9: 242 | K9: 73415 | L9: -
A10: D016369S | B10: 코스피200 SP 2603-2609 (주간) | C10: - | D10: - | E10: - | F10: - | G10: - | H10: 605.98 | I10: 0 | J10: 0 | K10: 0 | L10: -
A11: D01636CS | B11: 코스피200 SP 2603-2612 (주간) | C11: - | D11: - | E11: - | F11: - | G11: - | H11: 605.98 | I11: 0 | J11: 0 | K11: 0 | L11: -
A12: D016376S | B12: 코스피200 SP 2603-2706 (주간) | C12: - | D12: - | E12: - | F12: - | G12: - | H12: 605.98 | I12: 0 | J12: 0 | K12: 0 | L12: -
A13: D01637CS | B13: 코스피200 SP 2603-2712 (주간) | C13: - | D13: - | E13: - | F13: - | G13: - | H13: 605.98 | I13: 0 | J13: 0 | K13: 0 | L13: -
A14: D01638CS | B14: 코스피200 SP 2603-2812 (주간) | C14: - | D14: - | E14: - | F14: - | G14: - | H14: 605.98 | I14: 0 | J14: 0 | K14: 0 | L14: -

Sheet C4_수수료비용 등
A1: ='C1_정산표'!B1 -> 한빛코스피레버리지증권상장지수투자신탁(주식-파생형)
A2: ='C1_정산표'!B2 -> 45657 | G2: Prepared by : | H2: ='C1_정산표'!H2 -> SJ
A3: 수수료비용 검토 | G3: Reviewed by :
A6: 1. 수수료 비용 | C6: 결론 | D6: =IF(G13<0.01,"적정","부적정") -> 적정
A8: 구 분 | B8: 지급처 | C8: 보수율 | D8: PL보수금액 | E8: 재계산금액 | F8: 차이 | G8: 차이율 | H8: 비고
A9: 자산운용회사 | B9: 한빛자산운용 | C9: 1e-05 | D9: ='C1_정산표'!G110 -> 650007 | E9: =C387 -> 650164.37 | F9: =D9-E9 -> -157.36732 | G9: =F9/E9 -> -0.00024204237 | H9: Minor pass
A10: 판매회사 | B10: 한빛증권 등 | C10: 1e-05 | D10: ='C1_정산표'!G111 -> 650007 | E10: =D387 -> 650164.37 | F10: =D10-E10 -> -157.36732 | G10: =F10/E10 -> -0.00024204237 | H10: Minor pass
A11: 수탁회사 | B11: 한아름은행 | C11: 0.0001 | D11: ='C1_정산표'!G112 -> 6501699 | E11: =E387 -> 6501643.7 | F11: =D11-E11 -> 55.326774 | G11: =F11/E11 -> 8.5096596e-06 | H11: Minor pass
A12: 사무관리회사 | B12: 한빛펀드서비스 | C12: 0.0001 | D12: ='C1_정산표'!G113 -> 6501699 | E12: =F387 -> 6501643.7 | F12: =D12-E12 -> 55.326774 | G12: =F12/E12 -> 8.5096596e-06 | H12: Minor pass
A13: 합 계 | D13: =SUM(D9:D12) -> 14303412 | E13: =SUM(E9:E12) -> 14303616 | F13: =D13-E13 -> -204.0811 | G13: =F13/E13 -> -1.4267797e-05
A19: 2. 수수료비용 재계산
A20: 기준일 | B20: 순자산총액 | C20: 운용보수 | D20: 판매보수 | E20: 수탁보수 | F20: 사무관리보수
C21: =C9 -> 1e-05 | D21: =C10 -> 1e-05 | E21: =C11 -> 0.0001 | F21: =C12 -> 0.0001
A22: =가중평균좌수!B3 -> 20250101 | B22: =가중평균좌수!D3 -> 42432491295 | C22: =B22*C$21 -> 424324.91 | D22: =B22*D$21 -> 424324.91 | E22: =B22*E$21 -> 4243249.1 | F22: =B22*F$21 -> 4243249.1
A23: =가중평균좌수!B4 -> 20250102 | B23: =가중평균좌수!D4 -> 42222545434 | C23: =B23*C$21 -> 422225.45 | D23: =B23*D$21 -> 422225.45 | E23: =B23*E$21 -> 4222254.5 | F23: =B23*F$21 -> 4222254.5
A24: =가중평균좌수!B5 -> 20250103 | B24: =가중평균좌수!D5 -> 44040329603 | C24: =B24*C$21 -> 440403.3 | D24: =B24*D$21 -> 440403.3 | E24: =B24*E$21 -> 4404033 | F24: =B24*F$21 -> 4404033
A25: =가중평균좌수!B6 -> 20250104 | B25: =가중평균좌수!D6 -> 44040414305 | C25: =B25*C$21 -> 440404.14 | D25: =B25*D$21 -> 440404.14 | E25: =B25*E$21 -> 4404041.4 | F25: =B25*F$21 -> 4404041.4
A26: =가중평균좌수!B7 -> 20250105 | B26: =가중평균좌수!D7 -> 44040499107 | C26: =B26*C$21 -> 440404.99 | D26: =B26*D$21 -> 440404.99 | E26: =B26*E$21 -> 4404049.9 | F26: =B26*F$21 -> 4404049.9
A27: =가중평균좌수!B8 -> 20250106 | B27: =가중평균좌수!D8 -> 45815035044 | C27: =B27*C$21 -> 458150.35 | D27: =B27*D$21 -> 458150.35 | E27: =B27*E$21 -> 4581503.5 | F27: =B27*F$21 -> 4581503.5
A28: =가중평균좌수!B9 -> 20250107 | B28: =가중평균좌수!D9 -> 45881053601 | C28: =B28*C$21 -> 458810.54 | D28: =B28*D$21 -> 458810.54 | E28: =B28*E$21 -> 4588105.4 | F28: =B28*F$21 -> 4588105.4
A29: =가중평균좌수!B10 -> 20250108 | B29: =가중평균좌수!D10 -> 46770675242 | C29: =B29*C$21 -> 467706.75 | D29: =B29*D$21 -> 467706.75 | E29: =B29*E$21 -> 4677067.5 | F29: =B29*F$21 -> 4677067.5
A30: =가중평균좌수!B11 -> 20250109 | B30: =가중평균좌수!D11 -> 46770351338 | C30: =B30*C$21 -> 467703.51 | D30: =B30*D$21 -> 467703.51 | E30: =B30*E$21 -> 4677035.1 | F30: =B30*F$21 -> 4677035.1
A31: =가중평균좌수!B12 -> 20250110 | B31: =가중평균좌수!D12 -> 46743577702 | C31: =B31*C$21 -> 467435.78 | D31: =B31*D$21 -> 467435.78 | E31: =B31*E$21 -> 4674357.8 | F31: =B31*F$21 -> 4674357.8
A32: =가중평균좌수!B13 -> 20250111 | B32: =가중평균좌수!D13 -> 46743752358 | C32: =B32*C$21 -> 467437.52 | D32: =B32*D$21 -> 467437.52 | E32: =B32*E$21 -> 4674375.2 | F32: =B32*F$21 -> 4674375.2
A33: =가중평균좌수!B14 -> 20250112 | B33: =가중평균좌수!D14 -> 46743927013 | C33: =B33*C$21 -> 467439.27 | D33: =B33*D$21 -> 467439.27 | E33: =B33*E$21 -> 4674392.7 | F33: =B33*F$21 -> 4674392.7
... A386: =가중평균좌수!B367 -> 20251231 | B386: =가중평균좌수!D367 -> 137368956901 | C386: =B386*C$21 -> 1373689.6 | D386: =B386*D$21 -> 1373689.6 | E386: =B386*E$21 -> 13736896 | F386: =B386*F$21 -> 13736896
B387: =SUM(AVERAGE(B22:B386)) -> 6.5016437e+10 | C387: =AVERAGE(C22:C386) -> 650164.37 | D387: =AVERAGE(D22:D386) -> 650164.37 | E387: =AVERAGE(E22:E386) -> 6501643.7 | F387: =AVERAGE(F22:F386) -> 6501643.7
B388: =B386='C1_정산표'!H65 -> TRUE

Sheet 미지급해지금
A1: 펀드 | B1: 일자 | C1: 적요 | F1: 차변계정 | G1: 차변과목 | H1: 차변금액 | I1: 대변계정 | J1: 대변과목 | K1: 대변금액 | L1: 수탁사
A2: 512140 | B2: 44091 | C2: 81130 | D2: 일부해지 | E2: 유안타증권 | F2: 301010 | G2: 원본액 | H2: 5276352 | I2: 243010 | J2: 미지급해지금 | K2: 6324255 | L2: IBK기업은행
A3: 512140 | B3: 44091 | C3: 81130 | D3: 일부해지 | E3: KB증권 | F3: 301010 | G3: 원본액 | H3: 29130475 | I3: 243010 | J3: 미지급해지금 | K3: 34915901 | L3: IBK기업은행
A4: 512140 | B4: 44091 | C4: 81130 | D4: 일부해지 | E4: 하나은행 | F4: 301010 | G4: 원본액 | H4: 7483232 | I4: 243010 | J4: 미지급해지금 | K4: 8969431 | L4: IBK기업은행
A5: 512140 | B5: 44091 | C5: 81130 | D5: 일부해지 | E5: NH농협은행 | F5: 301010 | G5: 원본액 | H5: 43170527 | I5: 243010 | J5: 미지급해지금 | K5: 51744362 | L5: IBK기업은행
A6: 512140 | B6: 44091 | C6: 81130 | D6: 일부해지 | E6: 유안타증권 | F6: 301010 | G6: 원본액 | H6: 4522854 | I6: 243010 | J6: 미지급해지금 | K6: 5421110 | L6: IBK기업은행
A7: 512140 | B7: 44091 | C7: 81130 | D7: 일부해지 | E7: 종목107 | F7: 301010 | G7: 원본액 | H7: 11561656 | I7: 243010 | J7: 미지급해지금 | K7: 13857845 | L7: IBK기업은행
A8: 512140 | B8: 44091 | C8: 81130 | D8: 일부해지 | E8: 우리은행 | F8: 301010 | G8: 원본액 | H8: 13324084 | I8: 243010 | J8: 미지급해지금 | K8: 15970298 | L8: IBK기업은행
A9: 512140 | B9: 44091 | C9: 81130 | D9: 일부해지 | E9: 한아름은행 | F9: 301010 | G9: 원본액 | H9: 32011091 | I9: 243010 | J9: 미지급해지금 | K9: 38368618 | L9: IBK기업은행
A10: 512140 | B10: 44091 | C10: 81130 | D10: 일부해지 | E10: 제주은행 | F10: 301010 | G10: 원본액 | H10: 9438282 | I10: 243010 | J10: 미지급해지금 | K10: 11312761 | L10: IBK기업은행
A11: 512140 | B11: 44091 | C11: 81130 | D11: 일부해지 | E11: 한빛증권 | F11: 301010 | G11: 원본액 | H11: 36819592 | I11: 243010 | J11: 미지급해지금 | K11: 44132106 | L11: IBK기업은행
A12: 512140 | B12: 44092 | C12: 81130 | D12: 일부해지 | E12: 모펀드판매사 | F12: 301010 | G12: 원본액 | H12: 8325 | I12: 243010 | J12: 미지급해지금 | K12: 9545 | L12: IBK기업은행
A13: 512140 | B13: 44092 | C13: 81130 | D13: 일부해지 | E13: 모펀드판매사 | F13: 301010 | G13: 원본액 | H13: 227472070 | I13: 243010 | J13: 미지급해지금 | K13: 260784664 | L13: IBK기업은행
... A152: 512140 | B152: 44120 | C152: 81130 | D152: 일부해지 | E152: 한아름은행 | F152: 301010 | G152: 원본액 | H152: 10800109 | I152: 243010 | J152: 미지급해지금 | K152: 12112142 | L152: IBK기업은행

Sheet 주식미수입금
A1: 펀드 | B1: 일자 | C1: 적요 | F1: 차변계정 | G1: 차변과목 | H1: 차변금액 | I1: 대변계정 | J1: 대변과목 | K1: 대변금액 | L1: 수탁사
A2: 512140 | B2: 44092 | C2: 10101 | D2: 주식매도 결제 | E2: 한빛증권 | F2: 101010 | G2: 예금 | H2: 160021805 | I2: 139010 | J2: 주식미수입금 | K2: 160021805 | L2: IBK기업은행
A3: 512140 | B3: 44092 | C3: 10101 | D3: 주식매도 결제 | E3: 신한금융투자 | F3: 101010 | G3: 예금 | H3: 356989488 | I3: 139010 | J3: 주식미수입금 | K3: 356989488 | L3: IBK기업은행
A4: 512140 | B4: 44092 | C4: 10101 | D4: 주식매도 결제 | E4: 한화투자증권 | F4: 101010 | G4: 예금 | H4: 307111225 | I4: 139010 | J4: 주식미수입금 | K4: 307111225 | L4: IBK기업은행
A5: 512140 | B5: 44095 | C5: 10101 | D5: 주식매도 결제 | E5: 한빛증권 | F5: 101010 | G5: 예금 | H5: 197502865 | I5: 139010 | J5: 주식미수입금 | K5: 197502865 | L5: IBK기업은행
A6: 512140 | B6: 44095 | C6: 10101 | D6: 주식매도 결제 | E6: 이베스트투자증권 | F6: 101010 | G6: 예금 | H6: 84615198 | I6: 139010 | J6: 주식미수입금 | K6: 84615198 | L6: IBK기업은행
A7: 512140 | B7: 44096 | C7: 10101 | D7: 주식매도 결제 | E7: 한빛증권 | F7: 101010 | G7: 예금 | H7: 148287641 | I7: 139010 | J7: 주식미수입금 | K7: 148287641 | L7: IBK기업은행
A8: 512140 | B8: 44097 | C8: 10101 | D8: 주식매도 결제 | E8: 한빛증권 | F8: 101010 | G8: 예금 | H8: 2673279193 | I8: 139010 | J8: 주식미수입금 | K8: 2673279193 | L8: IBK기업은행
A9: 512140 | B9: 44098 | C9: 10101 | D9: 주식매도 결제 | E9: 한빛증권 | F9: 101010 | G9: 예금 | H9: 56002166 | I9: 139010 | J9: 주식미수입금 | K9: 56002166 | L9: IBK기업은행
A10: 512140 | B10: 44099 | C10: 10101 | D10: 주식매도 결제 | E10: KB증권 | F10: 101010 | G10: 예금 | H10: 429789958 | I10: 139010 | J10: 주식미수입금 | K10: 429789958 | L10: IBK기업은행
A11: 512140 | B11: 44117 | C11: 10101 | D11: 주식매도 결제 | E11: 종목132 | F11: 101010 | G11: 예금 | H11: 359537986 | I11: 139010 | J11: 주식미수입금 | K11: 359537986 | L11: IBK기업은행
A12: 512140 | B12: 44117 | C12: 10101 | D12: 주식매도 결제 | E12: 한빛증권 | F12: 101010 | G12: 예금 | H12: 800024414 | I12: 139010 | J12: 주식미수입금 | K12: 800024414 | L12: IBK기업은행
A13: 512140 | B13: 44118 | C13: 10101 | D13: 주식매도 결제 | E13: 유안타증권 | F13: 101010 | G13: 예금 | H13: 385023757 | I13: 139010 | J13: 주식미수입금 | K13: 385023757 | L13: IBK기업은행
A14: 512140 | B14: 44120 | C14: 10101 | D14: 주식매도 결제 | E14: 한빛증권 | F14: 101010 | G14: 예금 | H14: 374829120 | I14: 139010 | J14: 주식미수입금 | K14: 374829120 | L14: IBK기업은행

Sheet 주식미지급금
A1: 펀드 | B1: 일자 | C1: 적요 | F1: 차변계정 | G1: 차변과목 | H1: 차변금액 | I1: 대변계정 | J1: 대변과목 | K1: 대변금액 | L1: 수탁사
A2: 512140 | B2: 44095 | C2: 10102 | D2: 주식매수 결제 | E2: 종목132 | F2: 239010 | G2: 주식미지급금 | H2: 273088627 | I2: 101010 | J2: 예금 | K2: 273088627 | L2: IBK기업은행
A3: 512140 | B3: 44095 | C3: 10102 | D3: 주식매수 결제 | E3: 이베스트투자증권 | F3: 239010 | G3: 주식미지급금 | H3: 176463691 | I3: 101010 | J3: 예금 | K3: 176463691 | L3: IBK기업은행
A4: 512140 | B4: 44097 | C4: 10102 | D4: 주식매수 결제 | E4: 노무라금융투자 | F4: 239010 | G4: 주식미지급금 | H4: 253985140 | I4: 101010 | J4: 예금 | K4: 253985140 | L4: IBK기업은행
A5: 512140 | B5: 44097 | C5: 10102 | D5: 주식매수 결제 | E5: 한빛증권 | F5: 239010 | G5: 주식미지급금 | H5: 151348360 | I5: 101010 | J5: 예금 | K5: 151348360 | L5: IBK기업은행
A6: 512140 | B6: 44098 | C6: 10102 | D6: 주식매수 결제 | E6: 신한금융투자 | F6: 239010 | G6: 주식미지급금 | H6: 285454413 | I6: 101010 | J6: 예금 | K6: 285454413 | L6: IBK기업은행
A7: 512140 | B7: 44099 | C7: 10102 | D7: 주식매수 결제 | E7: 한빛증권 | F7: 239010 | G7: 주식미지급금 | H7: 673384989 | I7: 101010 | J7: 예금 | K7: 673384989 | L7: IBK기업은행
A8: 512140 | B8: 44102 | C8: 10102 | D8: 주식매수 결제 | E8: 대신증권 | F8: 239010 | G8: 주식미지급금 | H8: 163383140 | I8: 101010 | J8: 예금 | K8: 163383140 | L8: IBK기업은행
A9: 512140 | B9: 44103 | C9: 10102 | D9: 주식매수 결제 | E9: 이베스트투자증권 | F9: 239010 | G9: 주식미지급금 | H9: 130852721 | I9: 101010 | J9: 예금 | K9: 130852721 | L9: IBK기업은행
A10: 512140 | B10: 44110 | C10: 10102 | D10: 주식매수 결제 | E10: 신한금융투자 | F10: 239010 | G10: 주식미지급금 | H10: 169295560 | I10: 101010 | J10: 예금 | K10: 169295560 | L10: IBK기업은행
A11: 512140 | B11: 44111 | C11: 10102 | D11: 주식매수 결제 | E11: 한빛증권 | F11: 239010 | G11: 주식미지급금 | H11: 347452714 | I11: 101010 | J11: 예금 | K11: 347452714 | L11: IBK기업은행
A12: 512140 | B12: 44112 | C12: 10102 | D12: 주식매수 결제 | E12: 한빛증권 | F12: 239010 | G12: 주식미지급금 | H12: 288027018 | I12: 101010 | J12: 예금 | K12: 288027018 | L12: IBK기업은행
A13: 512140 | B13: 44117 | C13: 10102 | D13: 주식매수 결제 | E13: 한빛증권 | F13: 239010 | G13: 주식미지급금 | H13: 334677947 | I13: 101010 | J13: 예금 | K13: 334677947 | L13: IBK기업은행
... A15: 512140 | B15: 44120 | C15: 10102 | D15: 주식매수 결제 | E15: 한빛증권 | F15: 239010 | G15: 주식미지급금 | H15: 296916055 | I15: 101010 | J15: 예금 | K15: 296916055 | L15: IBK기업은행

Sheet C5_F.N
A1: ='C1_정산표'!B1 -> 한빛코스피레버리지증권상장지수투자신탁(주식-파생형) | F1: C5
A2: ='C1_정산표'!B2 -> 45657 | F2: Prepared by : | G2: ='C1_정산표'!H2 -> SJ | L2: ROUND(A1/1000,0) - IF(MOD(A1,1000)=500,1,0)
A3: 주석사항 검토 | F3: Reviewed by :
A5: 작성여부 | C5: <천원단위> | L5: <원단위>
A7: O | C7: =L7 -> 1. 현금및예치금 | L7: 1. 현금및예치금
A8: O | C8: 당기말 및 전기말 현재 현금및예치금의 내역은 다음과 같습니다. (원화단위: 천원) | L8: 당기말 및 전기말 현재 현금및예치금의 내역은 다음과 같습니다. (원화단위: 원)
A9: O
A10: O | C10: =L10 -> <당기말> | L10: <당기말>
A11: O | C11: 종류 | D11: 금융기관 | E11: 외화금액 | F11: 원화금액 | G11: 이자율 | L11: 종류 | M11: 금융기관 | N11: 외화금액 | O11: 원화금액 | P11: 이자율 | Q11: 종목통화
A12: O | C12: =L12 -> 보유예금 | D12: =M12 -> (주)한아름은행 | E12: =N12 -> 0 | F12: =ROUND(O12/1000,0) -> 7196301 | G12: =P12 -> 0.0207 | L12: 보유예금 | M12: (주)한아름은행 | O12: ='C2_자산부채평가'!F38 -> 7196301321 | P12: ='C2_자산부채평가'!D38/100 -> 0.0207
A13: O | C13: =L13 -> 0 | D13: =M13 -> 0 | E13: =N13 -> 0 | F13: =ROUND(O13/1000,0) -> 0 | G13: =P13 -> 0
A14: O | C14: =L14 -> 정기예금 소계 | E14: =N14 -> 0 | F14: =SUM(F13:F13) -> 0 | L14: 정기예금 소계 | O14: =SUM(O13:O13) -> 0 | P14: 0
A15: O | C15: =L15 -> 증거금 | D15: =M15 -> 0 | E15: =$Q15&" "&TEXT(N15,"#,###")&" " | F15: =ROUND(O15/1000,0) -> 0 | G15: =P15 -> 0 | L15: 증거금 | M15: ='C2_자산부채평가'!C45 -> 0 | O15: ='C2_자산부채평가'!D45 -> 0
A16: O | D16: =M16 -> 0 | F16: =ROUND(O16/1000,0) -> 0 | M16: ='C2_자산부채평가'!C46 -> 0 | O16: ='C2_자산부채평가'!D46 -> 0
A17: O | D17: =M17 -> 0 | F17: =ROUND(O17/1000,0) -> 0 | M17: ='C2_자산부채평가'!C47 -> 0 | O17: ='C2_자산부채평가'!D47 -> 0
A18: O | D18: =M18 -> 0 | F18: =ROUND(O18/1000,0) -> 0 | M18: ='C2_자산부채평가'!C48 -> 0 | O18: ='C2_자산부채평가'!D48 -> 0
A19: O | D19: =M19 -> 0 | F19: =ROUND(O19/1000,0) -> 0 | M19: ='C2_자산부채평가'!C49 -> 0 | O19: ='C2_자산부채평가'!D49 -> 0
A20: O | D20: =M20 -> 0 | F20: =ROUND(O20/1000,0) -> 0 | M20: ='C2_자산부채평가'!C50 -> 0 | O20: ='C2_자산부채평가'!D50 -> 0
A21: O | D21: =M21 -> 0 | F21: =ROUND(O21/1000,0) -> 0 | M21: ='C2_자산부채평가'!C51 -> 0 | O21: ='C2_자산부채평가'!D51 -> 0
A22: O | D22: =M22 -> 0 | F22: =ROUND(O22/1000,0) -> 0 | M22: ='C2_자산부채평가'!C52 -> 0 | O22: ='C2_자산부채평가'!D52 -> 0
A23: O | D23: =M23 -> 0 | F23: =ROUND(O23/1000,0) -> 0
A24: O | C24: =L24 -> 0 | D24: =M24 -> 0 | E24: =$Q24&" "&TEXT(N24,"#,###")&" " | F24: =ROUND(O24/1000,0) -> 0 | G24: =P24 -> 0
A25: O | C25: =L25 -> 증거금 소계 | E25: =N25 -> 0 | F25: =SUM(F15:F24) -> 0 | L25: 증거금 소계 | O25: =SUM(O15:O24) -> 0
A26: O | C26: 합계 | F26: =F12+F14+F25 -> 7196301 | L26: 합계 | O26: =O12+O14+O25 -> 7196301321
A27: O | E27: 단수검증 | F27: =F26=ROUND(O26/1000,0) -> TRUE | N27: 정산표대사 | O27: ='C1_정산표'!G11=O26 -> TRUE
A28: O
A29: O | C29: =L29 -> <전기말> | L29: <전기말>
A30: O | C30: 종류 | D30: 금융기관 | E30: 외화금액 | F30: 원화금액 | G30: 이자율 | L30: 종류 | M30: 금융기관 | N30: 외화금액 | O30: 원화금액 | P30: 이자율 | Q30: 종목통화
A31: O | C31: =L31 -> 0 | D31: =M31 -> 0 | E31: =N31 -> 0 | F31: =ROUND(O31/1000,0) -> 0 | G31: =P31 -> 0
A32: O | C32: =L32 -> 0 | D32: =M32 -> 0 | E32: =$Q32&" "&TEXT(N32,"#,###")&" " | F32: =ROUND(O32/1000,0) -> 0 | G32: =P32 -> 0
A33: O | C33: =L33 -> 0 | D33: =M33 -> 0 | E33: =N33 -> 0 | F33: =ROUND(O33/1000,0) -> 0 | G33: =P33 -> 0
A34: O | C34: =L34 -> 외화예금 소계 | E34: =N34 -> 0 | F34: =SUM(F32:F33) -> 0 | L34: 외화예금 소계 | O34: =SUM(O32:O33) -> 0 | P34: 0
A35: O | C35: =L35 -> 0 | D35: =M35 -> 0 | E35: =$Q35&" "&TEXT(N35,"#,###")&" " | F35: =ROUND(O35/1000,0) -> 0 | G35: =P35 -> 0
A36: O | C36: =L36 -> 0 | D36: =M36 -> 0 | E36: =$Q36&" "&TEXT(N36,"#,###")&" " | F36: =ROUND(O36/1000,0) -> 0 | G36: =P36 -> 0
A37: O | C37: =L37 -> 증거금 소계 | E37: =N37 -> 0 | F37: =SUM(F35:F36) -> 0 | L37: 증거금 소계 | O37: =SUM(O35:O36) -> 0
A38: O | C38: 합계 | F38: =F31+F34+F37 -> 0 | L38: 합계 | O38: =O31+O34+O37 -> 0
E39: 단수검증 | F39: =F38=ROUND(O38/1000,0) -> TRUE | N39: 정산표대사 | O39: ='C1_정산표'!I11=O38 -> FALSE
O40: ='C1_정산표'!I11-O38 -> 2337568068
A42: O | C42: =L42 -> 1. 대출채권 | L42: 1. 대출채권
A43: O | C43: 당기말 및 전기말 현재 대출채권의 내역은 다음과 같습니다. (원화단위: 천원) | L43: 당기말 및 전기말 현재 대출채권의 내역은 다음과 같습니다. (원화단위: 원)
A44: O
A45: O | C45: =L45 -> <당기말> | L45: <당기말>
A46: O | C46: 종류 | D46: 금융기관 / 종목명 | E46: 금액 | F46: 만기 | G46: 연이자율 | L46: 종류 | M46: 금융기관 / 종목명 | N46: 금액 | O46: 만기 | P46: 연이자율 | R46: 다트입력용 날짜
A47: O | C47: =L47 -> 콜론 | D47: =M47 -> 0 | E47: =ROUND(N47/1000,0) -> 0 | F47: =LEFT(O47,4)&"."&MID(O47,5,2)&"."&RIGHT(O47,2) -> 0..0 | G47: =P47 -> 0 | L47: 콜론 | M47: ='C2_자산부채평가'!C64 -> 0 | N47: ='C2_자산부채평가'!E64 -> 0 | O47: ='C2_자산부채평가'!G64 -> 0 | P47: ='C2_자산부채평가'!D64/100 -> 0 | R47: =LEFT(O47,4)&"."&MID(O47,5,2)&"."&RIGHT(O47,2) -> 0..0
A48: O | C48: =L48 -> 콜론 | D48: =M48 -> 0 | E48: =ROUND(N48/1000,0) -> 0 | F48: =LEFT(O48,4)&"."&MID(O48,5,2)&"."&RIGHT(O48,2) -> 0..0 | G48: =P48 -> 0 | L48: 콜론 | M48: ='C2_자산부채평가'!C65 -> 0 | N48: ='C2_자산부채평가'!E65 -> 0 | O48: ='C2_자산부채평가'!G65 -> 0 | P48: ='C2_자산부채평가'!D65/100 -> 0 | R48: =LEFT(O48,4)&"."&MID(O48,5,2)&"."&RIGHT(O48,2) -> 0..0
A49: O | C49: =L49 -> REPO(매수) | D49: =M49 -> 0 | E49: =ROUND(N49/1000,0) -> 0 | F49: =LEFT(O49,4)&"."&MID(O49,5,2)&"."&RIGHT(O49,2) -> 0..0 | G49: =P49 -> 0 | L49: REPO(매수) | M49: ='C2_자산부채평가'!C70 -> 0 | N49: ='C2_자산부채평가'!F70 -> 0 | O49: ='C2_자산부채평가'!G70 -> 0 | P49: ='C2_자산부채평가'!D70/100 -> 0 | R49: =LEFT(O49,4)&"."&MID(O49,5,2)&"."&RIGHT(O49,2) -> 0..0
A50: O | C50: =L50 -> REPO(매수) | D50: =M50 -> 0 | E50: =ROUND(N50/1000,0) -> 0 | F50: =LEFT(O50,4)&"."&MID(O50,5,2)&"."&RIGHT(O50,2) -> 0..0 | G50: =P50 -> 0 | L50: REPO(매수) | M50: ='C2_자산부채평가'!C71 -> 0 | N50: ='C2_자산부채평가'!F71 -> 0 | O50: ='C2_자산부채평가'!G71 -> 0 | P50: ='C2_자산부채평가'!D71/100 -> 0 | R50: =LEFT(O50,4)&"."&MID(O50,5,2)&"."&RIGHT(O50,2) -> 0..0
A51: O | C51: =L51 -> REPO(매수) | D51: =M51 -> 0 | E51: =ROUND(N51/1000,0) -> 0 | F51: =LEFT(O51,4)&"."&MID(O51,5,2)&"."&RIGHT(O51,2) -> 0..0 | G51: =P51 -> 0 | L51: REPO(매수) | M51: ='C2_자산부채평가'!C72 -> 0 | N51: ='C2_자산부채평가'!F72 -> 0 | O51: ='C2_자산부채평가'!G72 -> 0 | P51: ='C2_자산부채평가'!D72/100 -> 0 | R51: =LEFT(O51,4)&"."&MID(O51,5,2)&"."&RIGHT(O51,2) -> 0..0
A52: O
A53: O | C53: 합계 | E53: =SUM(E47:E52) -> 0 | L53: 합계 | N53: =SUM(N47:N52) -> 0
A54: O | D54: 단수검증 | E54: =E53=ROUND(N53/1000,0) -> TRUE | M54: 정산표대사 | N54: ='C1_정산표'!G16=N53 -> TRUE
A55: O
A56: O | C56: =L56 -> <전기말> | L56: <전기말>
A57: O | C57: 종류 | D57: 금융기관 | E57: 금액 | F57: 만기 | G57: 연이자율 | L57: 종류 | M57: 금융기관 | N57: 금액 | O57: 만기 | P57: 연이자율 | R57: 다트입력용 날짜
A58: O | C58: =L58 -> 0 | D58: =M58 -> 0 | E58: =ROUND(N58/1000,0) -> 0 | F58: =LEFT(O58,4)&"."&MID(O58,5,2)&"."&RIGHT(O58,2) -> .. | G58: =P58 -> 0 | R58: =LEFT(O58,4)&"."&MID(O58,5,2)&"."&RIGHT(O58,2) -> ..
A59: O | C59: =L59 -> 0 | D59: =M59 -> 0 | E59: =ROUND(N59/1000,0) -> 0 | F59: =LEFT(O59,4)&"."&MID(O59,5,2)&"."&RIGHT(O59,2) -> .. | G59: =P59 -> 0 | R59: =LEFT(O59,4)&"."&MID(O59,5,2)&"."&RIGHT(O59,2) -> ..
A60: O | C60: =L60 -> 0 | D60: =M60 -> 0 | E60: =ROUND(N60/1000,0) -> 0 | F60: =LEFT(O60,4)&"."&MID(O60,5,2)&"."&RIGHT(O60,2) -> .. | G60: =P60 -> 0 | R60: =LEFT(O60,4)&"."&MID(O60,5,2)&"."&RIGHT(O60,2) -> ..
A61: O | C61: 합계 | E61: =SUM(E58:E60) -> 0 | L61: 합계 | N61: =SUM(N58:N60) -> 0
A62: O | D62: 단수검증 | E62: =E61=ROUND(N61/1000,0) -> TRUE | M62: 정산표대사 | N62: =N61='C1_정산표'!I16 -> TRUE
A64: O | C64: =L64 -> 1. 지분증권 | L64: 1. 지분증권
A65: O | C65: 당기말 및 전기말 현재 지분증권의 내역은 다음과 같습니다 | L65: 당기말 및 전기말 현재 지분증권의 내역은 다음과 같습니다
A66: O
A67: O | C67: =L67 -> <당기말> | L67: <당기말>
A68: O | C68: 종목 | D68: 수량(주) | E68: =N68 -> 결산전 장부금액 | F68: =O68 -> 결산후 장부금액 | G68: =P68 -> 평가손익 | H68: 구성비 | L68: 종목 | M68: 수량(주) | N68: 결산전 장부금액 | O68: 결산후 장부금액 | P68: 평가손익 | Q68: 외화환산손익
A69: O | C69: =L69 -> <유가증권시장주식> | L69: <유가증권시장주식>
A70: O | C70: =L70 -> 종목002 | D70: =M70 -> 5880 | E70: =ROUND(N70/1000,0) -> 91765 | F70: =ROUND(O70/1000,0) -> 134652 | G70: =F70-E70 -> 42887 | H70: =ROUND(F70/$F$568,4) -> 0.0013 | I70: =F70/$F$568 -> 0.0012645154 | L70: ='C2_자산부채평가'!C101 -> 종목002 | M70: ='C2_자산부채평가'!D101 -> 5880 | N70: ='C2_자산부채평가'!E101 -> 91764961 | O70: ='C2_자산부채평가'!F101 -> 134652000 | P70: =O70-N70 -> 42887039
A71: O | C71: =L71 -> 종목003 | D71: =M71 -> 210 | E71: =ROUND(N71/1000,0)-IF(MOD(N71,1000)=500,1,0) -> 63483 | F71: =ROUND(O71/1000,0) - IF(MOD(O71,1000)=500,1,0) -> 88305 | G71: =F71-E71 -> 24822 | H71: =ROUND(F71/$F$568,4) -> 0.0008 | I71: =F71/$F$568 -> 0.00082927128 | L71: ='C2_자산부채평가'!C102 -> 종목003 | M71: ='C2_자산부채평가'!D102 -> 210 | N71: ='C2_자산부채평가'!E102 -> 63483000 | O71: ='C2_자산부채평가'!F102 -> 88305000 | P71: =O71-N71 -> 24822000
A72: O | C72: =L72 -> 종목004 | D72: =M72 -> 210 | E72: =ROUND(N72/1000,0)-IF(MOD(N72,1000)=500,1,0) -> 204090 | F72: =ROUND(O72/1000,0) - IF(MOD(O72,1000)=500,1,0) -> 258510 | G72: =F72-E72 -> 54420 | H72: =ROUND(F72/$F$568,4) -> 0.0024 | I72: =F72/$F$568 -> 0.0024276645 | L72: ='C2_자산부채평가'!C103 -> 종목004 | M72: ='C2_자산부채평가'!D103 -> 210 | N72: ='C2_자산부채평가'!E103 -> 204090000 | O72: ='C2_자산부채평가'!F103 -> 258510000 | P72: =O72-N72 -> 54420000
A73: O | C73: =L73 -> 종목005 | D73: =M73 -> 35 | E73: =ROUND(N73/1000,0)-IF(MOD(N73,1000)=500,1,0) -> 28063 | F73: =ROUND(O73/1000,0) - IF(MOD(O73,1000)=500,1,0) -> 26670 | G73: =F73-E73 -> -1393 | H73: =ROUND(F73/$F$568,4) -> 0.0003 | I73: =F73/$F$568 -> 0.00025045767 | L73: ='C2_자산부채평가'!C104 -> 종목005 | M73: ='C2_자산부채평가'!D104 -> 35 | N73: ='C2_자산부채평가'!E104 -> 28063230 | O73: ='C2_자산부채평가'!F104 -> 26670000 | P73: =O73-N73 -> -1393230
A74: O | C74: =L74 -> 종목006 | D74: =M74 -> 1855 | E74: =ROUND(N74/1000,0)-IF(MOD(N74,1000)=500,1,0) -> 311085 | F74: =ROUND(O74/1000,0) - IF(MOD(O74,1000)=500,1,0) -> 346885 | G74: =F74-E74 -> 35800 | H74: =ROUND(F74/$F$568,4) -> 0.0033 | I74: =F74/$F$568 -> 0.0032575932 | L74: ='C2_자산부채평가'!C105 -> 종목006 | M74: ='C2_자산부채평가'!D105 -> 1855 | N74: ='C2_자산부채평가'!E105 -> 311085250 | O74: ='C2_자산부채평가'!F105 -> 346885000 | P74: =O74-N74 -> 35799750
A75: O | C75: =L75 -> 종목007 | D75: =M75 -> 420 | E75: =ROUND(N75/1000,0)-IF(MOD(N75,1000)=500,1,0) -> 28544 | F75: =ROUND(O75/1000,0) - IF(MOD(O75,1000)=500,1,0) -> 26376 | G75: =F75-E75 -> -2168 | H75: =ROUND(F75/$F$568,4) -> 0.0002 | I75: =F75/$F$568 -> 0.00024769672 | L75: ='C2_자산부채평가'!C106 -> 종목007 | M75: ='C2_자산부채평가'!D106 -> 420 | N75: ='C2_자산부채평가'!E106 -> 28544400 | O75: ='C2_자산부채평가'!F106 -> 26376000 | P75: =O75-N75 -> -2168400
A76: O | C76: =L76 -> 종목008 | D76: =M76 -> 2835 | E76: =ROUND(N76/1000,0)-IF(MOD(N76,1000)=500,1,0) -> 402100 | F76: =ROUND(O76/1000,0) - IF(MOD(O76,1000)=500,1,0) -> 337932 | G76: =F76-E76 -> -64168 | H76: =ROUND(F76/$F$568,4) -> 0.0032 | I76: =F76/$F$568 -> 0.0031735157 | L76: ='C2_자산부채평가'!C107 -> 종목008 | M76: ='C2_자산부채평가'!D107 -> 2835 | N76: ='C2_자산부채평가'!E107 -> 402100300 | O76: ='C2_자산부채평가'!F107 -> 337932000 | P76: =O76-N76 -> -64168300
A77: O | C77: =L77 -> 종목009 | D77: =M77 -> 2905 | E77: =ROUND(N77/1000,0)-IF(MOD(N77,1000)=500,1,0) -> 492149 | F77: =ROUND(O77/1000,0) - IF(MOD(O77,1000)=500,1,0) -> 740775 | G77: =F77-E77 -> 248626 | H77: =ROUND(F77/$F$568,4) -> 0.007 | I77: =F77/$F$568 -> 0.0069566098 | L77: ='C2_자산부채평가'!C108 -> 종목009 | M77: ='C2_자산부채평가'!D108 -> 2905 | N77: ='C2_자산부채평가'!E108 -> 492148503 | O77: ='C2_자산부채평가'!F108 -> 740775000 | P77: =O77-N77 -> 248626497
A78: O | C78: =L78 -> 종목010 | D78: =M78 -> 2450 | E78: =ROUND(N78/1000,0)-IF(MOD(N78,1000)=500,1,0) -> 727251 | F78: =ROUND(O78/1000,0) - IF(MOD(O78,1000)=500,1,0) -> 997150 | G78: =F78-E78 -> 269899 | H78: =ROUND(F78/$F$568,4) -> 0.0094 | I78: =F78/$F$568 -> 0.0093642246 | L78: ='C2_자산부채평가'!C109 -> 종목010 | M78: ='C2_자산부채평가'!D109 -> 2450 | N78: ='C2_자산부채평가'!E109 -> 727251001 | O78: ='C2_자산부채평가'!F109 -> 997150000 | P78: =O78-N78 -> 269898999
A79: O | C79: =L79 -> 종목011 | D79: =M79 -> 350 | E79: =ROUND(N79/1000,0)-IF(MOD(N79,1000)=500,1,0) -> 363583 | F79: =ROUND(O79/1000,0) - IF(MOD(O79,1000)=500,1,0) -> 460600 | G79: =F79-E79 -> 97017 | H79: =ROUND(F79/$F$568,4)-0.0001 -> 0.0042 | I79: =F79/$F$568 -> 0.0043254895 | L79: ='C2_자산부채평가'!C110 -> 종목011 | M79: ='C2_자산부채평가'!D110 -> 350 | N79: ='C2_자산부채평가'!E110 -> 363583220 | O79: ='C2_자산부채평가'!F110 -> 460600000 | P79: =O79-N79 -> 97016780
A80: O | C80: =L80 -> 종목012 | D80: =M80 -> 2170 | E80: =ROUND(N80/1000,0)-IF(MOD(N80,1000)=500,1,0) -> 139159 | F80: =ROUND(O80/1000,0) - IF(MOD(O80,1000)=500,1,0) -> 180110 | G80: =F80-E80 -> 40951 | H80: =ROUND(F80/$F$568,4) -> 0.0017 | I80: =F80/$F$568 -> 0.001691411 | L80: ='C2_자산부채평가'!C111 -> 종목012 | M80: ='C2_자산부채평가'!D111 -> 2170 | N80: ='C2_자산부채평가'!E111 -> 139159001 | O80: ='C2_자산부채평가'!F111 -> 180110000 | P80: =O80-N80 -> 40950999
A81: O | C81: =L81 -> 종목013 | D81: =M81 -> 1330 | E81: =ROUND(N81/1000,0)-IF(MOD(N81,1000)=500,1,0) -> 86271 | F81: =ROUND(O81/1000,0) - IF(MOD(O81,1000)=500,1,0) -> 117439 | G81: =F81-E81 -> 31168 | H81: =ROUND(F81/$F$568,4) -> 0.0011 | I81: =F81/$F$568 -> 0.0011028683 | L81: ='C2_자산부채평가'!C112 -> 종목013 | M81: ='C2_자산부채평가'!D112 -> 1330 | N81: ='C2_자산부채평가'!E112 -> 86271401 | O81: ='C2_자산부채평가'!F112 -> 117439000 | P81: =O81-N81 -> 31167599
A82: O | C82: =L82 -> 종목014 | D82: =M82 -> 1680 | E82: =ROUND(N82/1000,0)-IF(MOD(N82,1000)=500,1,0) -> 43538 | F82: =ROUND(O82/1000,0) - IF(MOD(O82,1000)=500,1,0) -> 50148 | G82: =F82-E82 -> 6610 | H82: =ROUND(F82/$F$568,4) -> 0.0005 | I82: =F82/$F$568 -> 0.00047093931 | L82: ='C2_자산부채평가'!C113 -> 종목014 | M82: ='C2_자산부채평가'!D113 -> 1680 | N82: ='C2_자산부채평가'!E113 -> 43538051 | O82: ='C2_자산부채평가'!F113 -> 50148000 | P82: =O82-N82 -> 6609949
A83: O | C83: =L83 -> 종목015 | D83: =M83 -> 2205 | E83: =ROUND(N83/1000,0)-IF(MOD(N83,1000)=500,1,0) -> 215013 | F83: =ROUND(O83/1000,0) - IF(MOD(O83,1000)=500,1,0) -> 280917 | G83: =F83-E83 -> 65904 | H83: =ROUND(F83/$F$568,4) -> 0.0026 | I83: =F83/$F$568 -> 0.0026380884 | L83: ='C2_자산부채평가'!C114 -> 종목015 | M83: ='C2_자산부채평가'!D114 -> 2205 | N83: ='C2_자산부채평가'!E114 -> 215012704 | O83: ='C2_자산부채평가'!F114 -> 280917000 | P83: =O83-N83 -> 65904296
A84: O | C84: =L84 -> 종목016 | D84: =M84 -> 2135 | E84: =ROUND(N84/1000,0)-IF(MOD(N84,1000)=500,1,0) -> 224016 | F84: =ROUND(O84/1000,0) - IF(MOD(O84,1000)=500,1,0) -> 345229 | G84: =F84-E84 -> 121213 | H84: =ROUND(F84/$F$568,4) -> 0.0032 | I84: =F84/$F$568 -> 0.0032420417 | L84: ='C2_자산부채평가'!C115 -> 종목016 | M84: ='C2_자산부채평가'!D115 -> 2135 | N84: ='C2_자산부채평가'!E115 -> 224016403 | O84: ='C2_자산부채평가'!F115 -> 345229500 | P84: =O84-N84 -> 121213097
A85: O | C85: =L85 -> 종목017 | D85: =M85 -> 420 | E85: =ROUND(N85/1000,0)-IF(MOD(N85,1000)=500,1,0) -> 100008 | F85: =ROUND(O85/1000,0) - IF(MOD(O85,1000)=500,1,0) -> 87360 | G85: =F85-E85 -> -12648 | H85: =ROUND(F85/$F$568,4) -> 0.0008 | I85: =F85/$F$568 -> 0.00082039679 | L85: ='C2_자산부채평가'!C116 -> 종목017 | M85: ='C2_자산부채평가'!D116 -> 420 | N85: ='C2_자산부채평가'!E116 -> 100008000 | O85: ='C2_자산부채평가'!F116 -> 87360000 | P85: =O85-N85 -> -12648000
A86: O | C86: =L86 -> 종목018 | D86: =M86 -> 7315 | E86: =ROUND(N86/1000,0)-IF(MOD(N86,1000)=500,1,0) -> 78734 | F86: =ROUND(O86/1000,0) - IF(MOD(O86,1000)=500,1,0) -> 113748 | G86: =F86-E86 -> 35014 | H86: =ROUND(F86/$F$568,4) -> 0.0011 | I86: =F86/$F$568 -> 0.0010682062 | L86: ='C2_자산부채평가'!C117 -> 종목018 | M86: ='C2_자산부채평가'!D117 -> 7315 | N86: ='C2_자산부채평가'!E117 -> 78734485 | O86: ='C2_자산부채평가'!F117 -> 113748250 | P86: =O86-N86 -> 35013765
A87: O | C87: =L87 -> 종목019 | D87: =M87 -> 525 | E87: =ROUND(N87/1000,0)-IF(MOD(N87,1000)=500,1,0) -> 639948 | F87: =ROUND(O87/1000,0) - IF(MOD(O87,1000)=500,1,0) -> 889875 | G87: =F87-E87 -> 249927 | H87: =ROUND(F87/$F$568,4) -> 0.0084 | I87: =F87/$F$568 -> 0.0083568063 | L87: ='C2_자산부채평가'!C118 -> 종목019 | M87: ='C2_자산부채평가'!D118 -> 525 | N87: ='C2_자산부채평가'!E118 -> 639947948 | O87: ='C2_자산부채평가'!F118 -> 889875000 | P87: =O87-N87 -> 249927052
A88: O | C88: =L88 -> 종목020 | D88: =M88 -> 1155 | E88: =ROUND(N88/1000,0)-IF(MOD(N88,1000)=500,1,0) -> 121301 | F88: =ROUND(O88/1000,0) - IF(MOD(O88,1000)=500,1,0) -> 122083 | G88: =F88-E88 -> 782 | H88: =ROUND(F88/$F$568,4) -> 0.0011 | I88: =F88/$F$568 -> 0.0011464801 | L88: ='C2_자산부채평가'!C119 -> 종목020 | M88: ='C2_자산부채평가'!D119 -> 1155 | N88: ='C2_자산부채평가'!E119 -> 121301400 | O88: ='C2_자산부채평가'!F119 -> 122083500 | P88: =O88-N88 -> 782100
A89: O | C89: =L89 -> 종목021 | D89: =M89 -> 1365 | E89: =ROUND(N89/1000,0)-IF(MOD(N89,1000)=500,1,0) -> 67759 | F89: =ROUND(O89/1000,0) - IF(MOD(O89,1000)=500,1,0) -> 65793 | G89: =F89-E89 -> -1966 | H89: =ROUND(F89/$F$568,4) -> 0.0006 | I89: =F89/$F$568 -> 0.00061786133 | L89: ='C2_자산부채평가'!C120 -> 종목021 | M89: ='C2_자산부채평가'!D120 -> 1365 | N89: ='C2_자산부채평가'!E120 -> 67758600 | O89: ='C2_자산부채평가'!F120 -> 65793000 | P89: =O89-N89 -> -1965600
A90: O | C90: =L90 -> 종목022 | D90: =M90 -> 3150 | E90: =ROUND(N90/1000,0)-IF(MOD(N90,1000)=500,1,0) -> 367587 | F90: =ROUND(O90/1000,0) - IF(MOD(O90,1000)=500,1,0) -> 354060 | G90: =F90-E90 -> -13527 | H90: =ROUND(F90/$F$568,4) -> 0.0033 | I90: =F90/$F$568 -> 0.0033249735 | L90: ='C2_자산부채평가'!C121 -> 종목022 | M90: ='C2_자산부채평가'!D121 -> 3150 | N90: ='C2_자산부채평가'!E121 -> 367587006 | O90: ='C2_자산부채평가'!F121 -> 354060000 | P90: =O90-N90 -> -13527006
A91: O | C91: =L91 -> 종목023 | D91: =M91 -> 13335 | E91: =ROUND(N91/1000,0)-IF(MOD(N91,1000)=500,1,0) -> 298285 | F91: =ROUND(O91/1000,0) - IF(MOD(O91,1000)=500,1,0) -> 300704 | G91: =F91-E91 -> 2419 | H91: =ROUND(F91/$F$568,4) -> 0.0028 | I91: =F91/$F$568 -> 0.0028239079 | L91: ='C2_자산부채평가'!C122 -> 종목023 | M91: ='C2_자산부채평가'!D122 -> 13335 | N91: ='C2_자산부채평가'!E122 -> 298284901 | O91: ='C2_자산부채평가'!F122 -> 300704250 | P91: =O91-N91 -> 2419349
... A93: O | C93: =L93 -> 종목025 | D93: =M93 -> 1330 | E93: =ROUND(N93/1000,0)-IF(MOD(N93,1000)=500,1,0) -> 20670 | F93: =ROUND(O93/1000,0) - IF(MOD(O93,1000)=500,1,0) -> 19085 | G93: =F93-E93 -> -1585 | H93: =ROUND(F93/$F$568,4) -> 0.0002 | I93: =F93/$F$568 -> 0.00017922702 | L93: ='C2_자산부채평가'!C124 -> 종목025 | M93: ='C2_자산부채평가'!D124 -> 1330 | N93: ='C2_자산부채평가'!E124 -> 20669722 | O93: ='C2_자산부채평가'!F124 -> 19085500 | P93: =O93-N93 -> -1584222
A94: O | C94: =L94 -> 종목026 | D94: =M94 -> 280 | E94: =ROUND(N94/1000,0)-IF(MOD(N94,1000)=500,1,0) -> 44944 | F94: =ROUND(O94/1000,0) - IF(MOD(O94,1000)=500,1,0) -> 44520 | G94: =F94-E94 -> -424 | H94: =ROUND(F94/$F$568,4)-0.0001 -> 0.0003 | I94: =F94/$F$568 -> 0.00041808683 | L94: ='C2_자산부채평가'!C125 -> 종목026 | M94: ='C2_자산부채평가'!D125 -> 280 | N94: ='C2_자산부채평가'!E125 -> 44944000 | O94: ='C2_자산부채평가'!F125 -> 44520000 | P94: =O94-N94 -> -424000
A95: O | C95: =L95 -> 종목027 | D95: =M95 -> 3185 | E95: =ROUND(N95/1000,0)-IF(MOD(N95,1000)=500,1,0) -> 792997 | F95: =ROUND(O95/1000,0) - IF(MOD(O95,1000)=500,1,0) -> 858357 | G95: =F95-E95 -> 65360 | H95: =ROUND(F95/$F$568,4) -> 0.0081 | I95: =F95/$F$568 -> 0.0080608211 | L95: ='C2_자산부채평가'!C126 -> 종목027 | M95: ='C2_자산부채평가'!D126 -> 3185 | N95: ='C2_자산부채평가'!E126 -> 792997250 | O95: ='C2_자산부채평가'!F126 -> 858357500 | P95: =O95-N95 -> 65360250
A96: O | C96: =L96 -> 종목028 | D96: =M96 -> 14350 | E96: =ROUND(N96/1000,0)-IF(MOD(N96,1000)=500,1,0) -> 199207 | F96: =ROUND(O96/1000,0) - IF(MOD(O96,1000)=500,1,0) -> 335072 | G96: =F96-E96 -> 135865 | H96: =ROUND(F96/$F$568,4) -> 0.0031 | I96: =F96/$F$568 -> 0.0031466574 | L96: ='C2_자산부채평가'!C127 -> 종목028 | M96: ='C2_자산부채평가'!D127 -> 14350 | N96: ='C2_자산부채평가'!E127 -> 199206703 | O96: ='C2_자산부채평가'!F127 -> 335072500 | P96: =O96-N96 -> 135865797
A97: O | C97: =L97 -> 종목029 | D97: =M97 -> 1470 | E97: =ROUND(N97/1000,0)-IF(MOD(N97,1000)=500,1,0) -> 47594 | F97: =ROUND(O97/1000,0) - IF(MOD(O97,1000)=500,1,0) -> 53287 | G97: =F97-E97 -> 5693 | H97: =ROUND(F97/$F$568,4) -> 0.0005 | I97: =F97/$F$568 -> 0.00050041763 | L97: ='C2_자산부채평가'!C128 -> 종목029 | M97: ='C2_자산부채평가'!D128 -> 1470 | N97: ='C2_자산부채평가'!E128 -> 47594401 | O97: ='C2_자산부채평가'!F128 -> 53287500 | P97: =O97-N97 -> 5693099
A98: O | C98: =L98 -> 종목030 | D98: =M98 -> 420 | E98: =ROUND(N98/1000,0)-IF(MOD(N98,1000)=500,1,0) -> 19513 | F98: =ROUND(O98/1000,0) - IF(MOD(O98,1000)=500,1,0) -> 19383 | G98: =F98-E98 -> -130 | H98: =ROUND(F98/$F$568,4) -> 0.0002 | I98: =F98/$F$568 -> 0.00018202554 | L98: ='C2_자산부채평가'!C129 -> 종목030 | M98: ='C2_자산부채평가'!D129 -> 420 | N98: ='C2_자산부채평가'!E129 -> 19513201 | O98: ='C2_자산부채평가'!F129 -> 19383000 | P98: =O98-N98 -> -130201
A99: O | C99: =L99 -> 종목031 | D99: =M99 -> 700 | E99: =ROUND(N99/1000,0)-IF(MOD(N99,1000)=500,1,0) -> 56248 | F99: =ROUND(O99/1000,0) - IF(MOD(O99,1000)=500,1,0) -> 80640 | G99: =F99-E99 -> 24392 | H99: =ROUND(F99/$F$568,4) -> 0.0008 | I99: =F99/$F$568 -> 0.00075728935 | L99: ='C2_자산부채평가'!C130 -> 종목031 | M99: ='C2_자산부채평가'!D130 -> 700 | N99: ='C2_자산부채평가'!E130 -> 56248002 | O99: ='C2_자산부채평가'!F130 -> 80640000 | P99: =O99-N99 -> 24391998
A100: O | C100: =L100 -> 종목032 | D100: =M100 -> 280 | E100: =ROUND(N100/1000,0)-IF(MOD(N100,1000)=500,1,0) -> 235065 | F100: =ROUND(O100/1000,0) - IF(MOD(O100,1000)=500,1,0) -> 208040 | G100: =F100-E100 -> -27025 | H100: =ROUND(F100/$F$568,4) -> 0.002 | I100: =F100/$F$568 -> 0.0019537013 | L100: ='C2_자산부채평가'!C131 -> 종목032 | M100: ='C2_자산부채평가'!D131 -> 280 | N100: ='C2_자산부채평가'!E131 -> 235064992 | O100: ='C2_자산부채평가'!F131 -> 208040000 | P100: =O100-N100 -> -27024992
A101: O | C101: =L101 -> 종목033 | D101: =M101 -> 2529 | E101: =ROUND(N101/1000,0)-IF(MOD(N101,1000)=500,1,0) -> 7157 | F101: =ROUND(O101/1000,0) - IF(MOD(O101,1000)=500,1,0) -> 7498 | G101: =F101-E101 -> 341 | H101: =ROUND(F101/$F$568,4) -> 0.0001 | I101: =F101/$F$568 -> 7.0413635e-05 | L101: ='C2_자산부채평가'!C132 -> 종목033 | M101: ='C2_자산부채평가'!D132 -> 2529 | N101: ='C2_자산부채평가'!E132 -> 7157070 | O101: ='C2_자산부채평가'!F132 -> 7498485 | P101: =O101-N101 -> 341415
A102: O | C102: =L102 -> 종목034 | D102: =M102 -> 525 | E102: =ROUND(N102/1000,0)-IF(MOD(N102,1000)=500,1,0) -> 32378 | F102: =ROUND(O102/1000,0) - IF(MOD(O102,1000)=500,1,0) -> 38062 | G102: =F102-E102 -> 5684 | H102: =ROUND(F102/$F$568,4) -> 0.0004 | I102: =F102/$F$568 -> 0.00035743982 | L102: ='C2_자산부채평가'!C133 -> 종목034 | M102: ='C2_자산부채평가'!D133 -> 525 | N102: ='C2_자산부채평가'!E133 -> 32378487 | O102: ='C2_자산부채평가'!F133 -> 38062500 | P102: =O102-N102 -> 5684013
A103: O | C103: =L103 -> 종목035 | D103: =M103 -> 5250 | E103: =ROUND(N103/1000,0)-IF(MOD(N103,1000)=500,1,0) -> 845439 | F103: =ROUND(O103/1000,0) - IF(MOD(O103,1000)=500,1,0) -> 1257375 | G103: =F103-E103 -> 411936 | H103: =ROUND(F103/$F$568,4) -> 0.0118 | I103: =F103/$F$568 -> 0.011807995 | L103: ='C2_자산부채평가'!C134 -> 종목035 | M103: ='C2_자산부채평가'!D134 -> 5250 | N103: ='C2_자산부채평가'!E134 -> 845438975 | O103: ='C2_자산부채평가'!F134 -> 1257375000 | P103: =O103-N103 -> 411936025
A104: O | C104: =L104 -> 종목036 | D104: =M104 -> 4410 | E104: =ROUND(N104/1000,0)-IF(MOD(N104,1000)=500,1,0) -> 513803 | F104: =ROUND(O104/1000,0) - IF(MOD(O104,1000)=500,1,0) -> 695016 | G104: =F104-E104 -> 181213 | H104: =ROUND(F104/$F$568,4) -> 0.0065 | I104: =F104/$F$568 -> 0.0065268876 | L104: ='C2_자산부채평가'!C135 -> 종목036 | M104: ='C2_자산부채평가'!D135 -> 4410 | N104: ='C2_자산부채평가'!E135 -> 513802800 | O104: ='C2_자산부채평가'!F135 -> 695016000 | P104: =O104-N104 -> 181213200
A105: O | C105: =L105 -> 종목037 | D105: =M105 -> 15190 | E105: =ROUND(N105/1000,0)-IF(MOD(N105,1000)=500,1,0) -> 155585 | F105: =ROUND(O105/1000,0) - IF(MOD(O105,1000)=500,1,0) -> 179394 | G105: =F105-E105 -> 23809 | H105: =ROUND(F105/$F$568,4) -> 0.0017 | I105: =F105/$F$568 -> 0.0016846871 | L105: ='C2_자산부채평가'!C136 -> 종목037 | M105: ='C2_자산부채평가'!D136 -> 15190 | N105: ='C2_자산부채평가'!E136 -> 155584662 | O105: ='C2_자산부채평가'!F136 -> 179393900 | P105: =O105-N105 -> 23809238
...

Sheet 재무제표검증
A2: 재 무 상 태 표
A3: 제14(당)기 2023년 12월 31일 현재
A4: 제13(전)기 2022년 12월 31일 현재
A6: 한빛코스피레버리지증권상장지수투자신탁(주식-파생형) | B6: (단위: 원)
A7: 과목 | B7: 제14(당)기 | D7: 제14(당)기 | G7: 제12(전)기 | I7: 제12(전)기
A8: 자산
A9: Ⅰ. 운용자산 | C9: 44633945418 | E9: =SUM(D10,D13) -> 138145120376 | F9: =C9=E9 -> FALSE | H9: 39602903680 | J9: =SUM(I10,I13) -> 39602903680 | K9: =H9=J9 -> TRUE
A10: 1. 현금및예치금(주석3) | B10: 1383261539 | D10: =SUM(D11:D12) -> 7196301321 | F10: =B10=D10 -> FALSE | G10: 991205345 | I10: =SUM(I11:I12) -> 991205345 | K10: =G10=I10 -> TRUE
A11: (1) 현금및현금성자산 | B11: 1201737309 | D11: ='C1_정산표'!G12 -> 7196301321 | G11: 364449765 | I11: 364449765
A12: (2) 증거금 | B12: 181524230 | D12: ='C1_정산표'!G15 -> 0 | G12: 626755580 | I12: 626755580
A13: 2. 유가증권 | B13: 43250683879 | D13: =SUM(D14:D16) -> 130948819055 | F13: =B13=D13 -> FALSE | G13: 38611698335 | I13: =SUM(I14:I16) -> 38611698335 | K13: =G13=I13 -> TRUE
A14: (1) 지분증권(주석4) | B14: 37780291390 | D14: ='C1_정산표'!G22 -> 106485058475 | G14: 33507207235 | I14: 33507207235
A15: (2) 수익증권(주석5) | B15: 2425848915 | D15: ='C1_정산표'!G24 -> 24463760580 | G15: 5104491100 | I15: 5104491100
A16: (3) 채무증권(주석6) | B16: 3044543574 | D16: ='C1_정산표'!G23 -> 0 | G16: - | I16: -
A17: II . 기타자산 | C17: 2111054297 | E17: =SUM(D18:D22) -> 9675566645 | F17: =C17=E17 -> FALSE | H17: 412017290 | J17: =SUM(I18:I22) -> 412017290 | K17: =H17=J17 -> TRUE
A18: 1. 미수배당금 | B18: 270998847 | D18: ='C1_정산표'!G35 -> 221852625 | G18: 411430005 | I18: 411430005
A19: 2. 미수이자 | B19: 31654012 | D19: ='C1_정산표'!G34 -> 31164528 | G19: 426511 | I19: 426511
A20: 3. 매도유가증권미수금 | B20: 995801438 | D20: ='C1_정산표'!G32 -> 8837106649 | G20: - | I20: -
A21: 4. 정산미수금 | B21: 812600000 | D21: ='C1_정산표'!G33 -> 584987500
A22: 5. 기타자산 | B22: 0 | D22: ='C1_정산표'!G36 -> 455343 | G22: 160774 | I22: 160774
A23: 자 산 총 계 | C23: 46744999715 | E23: =SUM(E9,E17) -> 147820687021 | F23: =C23=E23 -> FALSE | H23: 40014920970 | J23: =SUM(J9,J17) -> 40014920970 | K23: =H23=J23 -> TRUE
A24: 부채
A25: I . 운용부채 | C25: 4146543574 | E25: =SUM(D26) -> 0 | F25: =C25=E25 -> FALSE | H25: 1048050000 | J25: =SUM(I26) -> 1048050000 | K25: =H25=J25 -> TRUE
A26: 1. 매도유가증권(주석8) | B26: 4146543574 | D26: ='C1_정산표'!G41 -> 0 | G26: 1048050000 | I26: 1048050000
A27: II . 기타부채 | C27: 231589887 | E27: =SUM(D28:D31) -> 4581730120 | F27: =C27=E27 -> FALSE | H27: 226861285 | J27: =SUM(I28:I31) -> 226861285 | K27: =H27=J27 -> TRUE
A28: 1. 수수료미지급금(주석9) | B28: 2361712 | D28: ='C1_정산표'!G50 -> 5525638 | G28: 2075984 | I28: 2075984
A29: 2. 유가증권미지급금 | B29: 199869580 | D29: ='C1_정산표'!G47 -> 4547096890 | G29: 4505300 | I29: 4505300
A30: 3. 정산미지급금(주석7) | B30: - | D30: ='C1_정산표'!G48 -> 0 | G30: 202425240 | I30: 202425240
A31: 4. 기타부채 | B31: 29358595 | D31: ='C1_정산표'!G54 -> 29107592 | G31: 17854761 | I31: 17854761
A32: 부 채 총 계 | C32: 4378133461 | E32: =SUM(E27,E25) -> 4581730120 | F32: =C32=E32 -> FALSE | H32: 1274911285 | J32: =SUM(J27,J25) -> 1274911285 | K32: =H32=J32 -> TRUE
A33: 자본
A34: Ⅰ. 원본(주석10) | C34: 23000000000 | E34: ='C1_정산표'!H57 -> 29000000000 | H34: 17000000000 | J34: 17000000000
A35: Ⅱ. 이익잉여금 | C35: 19366866254 | E35: ='C1_정산표'!H58 -> 108368956901 | H35: 21740009685 | J35: 21740009685
A36: (총좌수
A37: 당기: 2,900,000좌
A38: 전기: 1,700,000좌)
A39: (1좌당 기준가격 | L39: `
A40: 당기: 12,362.77원
A41: 전기: 22,788.24원)(주석14)
A42: 자 본 총 계 | C42: 42366866254 | E42: =SUM(E34:E41) -> 137368956901 | F42: =C42=E42 -> FALSE | H42: 38740009685 | J42: =SUM(J34:J41) -> 38740009685 | K42: =H42=J42 -> TRUE
A43: 부채및자본총계 | C43: 46744999715 | E43: =SUM(E42,E32) -> 141950687021 | F43: =C43=E43 -> FALSE | H43: 40014920970 | J43: =SUM(J42,J32) -> 40014920970 | K43: =H43=J43 -> TRUE
A46: 손 익 계 산 서
A47: 제14(당)기 2023년 01월 01일부터 2023년 12월 31일까지
A48: 제13(전)기 2022년 01월 01일부터 2022년 12월 31일까지
A50: 한빛코스피레버리지증권상장지수투자신탁(주식-파생형) | B50: (단위: 원)
A51: 과목 | B51: 제13(당)기 | D51: 제13(당)기 | G51: 제12(전)기 | I51: 제12(전)기
A52: I. 운용수익(손실) | C52: 18291962675 | E52: =SUM(D53,D57,D66) -> 88277940651 | F52: =C52=E52 -> FALSE | H52: 1322818086 | J52: =SUM(I53,I57,I66) -> 1322818086 | K52: =H52=J52 -> TRUE
A53: 1. 투자수익 | B53: 847946397 | D53: =SUM(D54:D56) -> 1394262129 | F53: =B53=D53 -> FALSE | G53: 770877904 | I53: =SUM(I54:I56) -> 770877904 | K53: =G53=I53 -> TRUE
A54: (1) 이자수익 | B54: 137969955 | D54: ='C1_정산표'!G77 -> 93912875 | G54: 9902067 | I54: 9902067
A55: (2) 배당금수익 | B55: 698008837 | D55: ='C1_정산표'!G78 -> 1288689005 | G55: 755945529 | I55: 755945529
A56: (3) 기타수익 | B56: 11967605 | D56: ='C1_정산표'!G79 -> 11660249 | G56: 5030308 | I56: 5030308
A57: 2. 매매이익과 평가이익 | B57: 56581877418 | D57: =SUM(D58:D65) -> 166074002619 | F57: =B57=D57 -> FALSE | G57: 36229043369 | I57: =SUM(I58:I65) -> 36229043369 | K57: =G57=I57 -> TRUE
A58: (1) 지분증권매매이익 | B58: 776052626 | D58: ='C1_정산표'!G81 -> 561112490 | G58: 696877218 | I58: 696877218
A59: (2) 지분증권평가이익(주석4) | B59: 7919460996 | D59: ='C1_정산표'!G82 -> 33658782894 | G59: 1334439546 | I59: 1334439546
A60: (3) 수익증권매매이익 | B60: 1383514868 | D60: ='C1_정산표'!G85 -> 6659502732 | G60: 850069245 | I60: 850069245
A61: (4) 수익증권평가이익(주석5) | B61: 152045581 | D61: ='C1_정산표'!G86 -> 1046317003 | G61: 59137004 | I61: 59137004
A62: (5) 채무증권매매이익 | B62: - | D62: ='C1_정산표'!G83 -> 0 | G62: - | I62: -
A63: (6) 채무증권평가이익(주석6) | B63: 327690847 | D63: ='C1_정산표'!G84 -> 0 | G63: - | I63: -
A64: (7) 파생상품매매이익 | B64: 46023112500 | D64: ='C1_정산표'!G87 -> 124148287500 | G64: 33287573011 | I64: 33287573011
A65: (8) 기타매매이익 | B65: - | D65: ='C1_정산표'!G89 -> 0 | G65: 947345 | I65: 947345
A66: 3. 매매손실과 평가손실 | B66: -39137861140 | D66: =-SUM(D67:D74) -> -79190324097 | F66: =B66=D66 -> FALSE | G66: -35677103187 | I66: =-SUM(I67:I74) -> -35677103187 | K66: =G66=I66 -> TRUE
A67: (1) 지분증권매매손실 | B67: 155674302 | D67: ='C1_정산표'!G95 -> 44085416 | G67: 341131731 | I67: 341131731
A68: (2) 지분증권평가손실(주석4) | B68: 1096719876 | D68: ='C1_정산표'!G96 -> 391593798 | G68: 1748979683 | I68: 1748979683
A69: (3) 수익증권매매손실 | B69: 416917371 | D69: ='C1_정산표'!G99 -> 969019883 | G69: 791704298 | I69: 791704298
A70: (4) 수익증권평가손실(주석5) | B70: - | D70: ='C1_정산표'!G100 -> 0 | G70: - | I70: -
A71: (5) 채무증권매매손실 | B71: - | D71: ='C1_정산표'!G97 -> 0 | G71: - | I71: -
A72: (6) 파생상품매매손실 | B72: 37087250000 | D72: ='C1_정산표'!G101 -> 77785625000 | G72: 32788040130 | I72: 32788040130
A73: (7) 기타매매손실 | B73: 15108667 | D73: ='C1_정산표'!G103 -> 0 | G73: 947345 | I73: 947345
A74: (8) 기타평가손실 | B74: 366190924 | D74: ='C1_정산표'!G104 -> 0 | G74: 6300000 | I74: 6300000
A75: Ⅱ. 운용비용 | C75: -132580424 | E75: =-SUM(D76:D81) -> -128954273 | F75: =C75=E75 -> FALSE | H75: -65726027 | J75: =-SUM(I76:I81) -> -65726027 | K75: =H75=J75 -> TRUE
A76: 1. 집합투자보수(주석9,15) | B76: 417683 | D76: ='C1_정산표'!G110 -> 650007 | G76: 9690361 | I76: 9690361
A77: 2. 판매보수(주석9,15) | B77: 417683 | D77: ='C1_정산표'!G111 -> 650007 | G77: 1742399 | I77: 1742399
A78: 3. 신탁보수(주석9) | B78: 4178486 | D78: ='C1_정산표'!G112 -> 6501699 | G78: 3119416 | I78: 3119416
A79: 4. 사무관리보수(주석9,15) | B79: 4178486 | D79: ='C1_정산표'!G113 -> 6501699 | G79: 3119416 | I79: 3119416
A80: 5. 이자비용 | B80: 62583508 | D80: ='C1_정산표'!G115 -> 5032539 | G80: 2421810 | I80: 2421810
A81: 6. 기타비용 | B81: 60804578 | D81: ='C1_정산표'!G116 -> 109618322 | G81: 45632625 | I81: 45632625
A82: Ⅲ. 당기순이익(손실)(주석13) | C82: 18159382251 | E82: =SUM(E75,E52) -> 88148986378 | F82: =C82=E82 -> FALSE | H82: 1257092059 | J82: =SUM(J75,J52) -> 1257092059 | K82: =H82=J82 -> TRUE
A83: Ⅳ. 1좌당 당기순이익(손실)(주석12) | C83: 6729.79 | E83: ='C1_정산표'!C118 -> 32190.475 | H83: 988.24 | J83: 988.24
A86: 자 본 변 동 표
A87: 제13(당)기 2022년 01월 01일부터 2022년 12월 31일까지
A88: 제12(전)기 2021년 01월 01일부터 2021년 12월 31일까지
A90: 한빛코스피레버리지증권상장지수투자신탁(주식-파생형) | B90: (단위: 원)
A91: 구분 | B91: 원본 | C91: 이익잉여금 | D91: 총계 | E91: 원본 | F91: 결손금 | G91: 총계
A92: Ⅰ. 2021년 01월 01일(전기초) | B92: 17000000000 | C92: 21740009685 | D92: 38740009685 | E92: 11000000000 | F92: 13455861158 | G92: =SUM(E92:F92) -> 24455861158
A93: 추가모집 | B93: 342000000000 | C93: 0 | D93: 342000000000 | E93: 405000000000 | F93: - | G93: =SUM(E93:F93) -> 405000000000
A94: 해지환급 | B94: -330000000000 | C94: 0 | D94: -330000000000 | E94: -399000000000 | F94: - | G94: =SUM(E94:F94) -> -399000000000
A95: 당기순이익(주석13) | B95: 0 | C95: -21633186259 | D95: -21633186259 | E95: - | F95: 1257092059 | G95: =SUM(E95:F95) -> 1257092059
A96: 설정조정금 | B96: 0 | C96: 233745770649 | D96: 233745770649 | E96: - | F96: 595728665852 | G96: =SUM(E96:F96) -> 595728665852
A97: 해지조정금 | B97: 0 | C97: -227000573620 | D97: -227000573620 | E97: - | F97: -588701609384 | G97: =SUM(E97:F97) -> -588701609384
A98: Ⅱ. 2021년 12월 31일(전기말) | B98: 29000000000 | C98: 6852020455 | D98: 35852020455 | E98: =SUM(E92:E97) -> 17000000000 | F98: =SUM(F92:F97) -> 21740009685 | G98: =SUM(G92:G97) -> 38740009685
A99: (총좌수: 1,700,000좌 | E99: =B98=E98 -> FALSE | F99: =C98=F98 -> FALSE | G99: =D98=G98 -> FALSE
A100: 1좌당 기준가격: 22,788.24원)(주석14)
A101: Ⅰ. 2022년 01월 01일(당기초) | B101: 29000000000 | C101: 6852020455 | D101: 35852020455 | E101: 17000000000 | F101: 21740009685 | G101: =SUM(E101:F101) -> 38740009685
A102: 추가모집 | B102: 260000000000 | C102: 0 | D102: 260000000000 | E102: 342000000000 | F102: - | G102: =SUM(E102:F102) -> 342000000000
A103: 해지환급 | B103: -266000000000 | C103: 0 | D103: -266000000000 | E103: -330000000000 | F103: - | G103: =SUM(E103:F103) -> -330000000000
A104: 당기순손실(주석13) | B104: 0 | C104: 18159382251 | D104: 18159382251 | E104: - | F104: -21633186259 | G104: =SUM(E104:F104) -> -21633186259
A105: 설정조정금 | B105: 0 | C105: 141011316109 | D105: 141011316109 | E105: - | F105: 233745770649 | G105: =SUM(E105:F105) -> 233745770649
A106: 해지조정금 | B106: 0 | C106: -146655852561 | D106: -146655852561 | E106: - | F106: -227000573620 | G106: =SUM(E106:F106) -> -227000573620
A107: Ⅱ. 2022년 12월 31일(당기말) | B107: 23000000000 | C107: 19366866254 | D107: 42366866254 | E107: =SUM(E101:E106) -> 29000000000 | F107: =SUM(F101:F106) -> 6852020455 | G107: =SUM(G101:G106) -> 35852020455
A108: (총좌수: 2,900,000좌 | E108: =B107=E107 -> FALSE | F108: =C107=F107 -> FALSE | G108: =D107=G107 -> FALSE
...

Sheet PBC--->>>

Sheet 국내유동명세
A1: Column1 | B1: Column2 | C1: Column3 | D1: Column4 | E1: Column5 | F1: Column6 | G1: Column7 | H1: Column8 | I1: Column9 | J1: Column10 | K1: Column11 | L1: Column12 | M1: Column13 | N1: Column14 | O1: Column15 | P1: Column16 | Q1: Column17 | R1: Column18 | S1: Column19 | T1: Column20 | U1: Column21 | V1: Column22 | W1: Column23 | X1: Column24 | Y1: Column25 | Z1: Column26 | AA1: Column27 | AB1: Column28 | AC1: Column29 | AD1: Column30 | AE1: Column31 | AF1: Column32 | AG1: Column33 | AH1: Column34 | AI1: Column35 | AJ1: Column36 | AK1: Column37 | AL1: Column38 | AM1: Column39 | AN1: Column40
A2: 종목코드 | B2: 표준코드 | C2: 종목명 | D2: 유동종류 | E2: 발행률 | F2: 시장률 | G2: 매입율 | H2: 선후급 | I2: 이자 | J2: 과세 | K2: 수량 | L2: 대용/대차수량 | M2: 만기금액 | N2: 발행일 | O2: 만기일 | P2: 매입일 | Q2: 취득원가 | R2: 장부가평가액 | S2: 시가평가금액 | T2: 상환손익 | U2: 총경과/총일수 | V2: 기경과이자 | W2: 선수이자 | X2: 이자계산 | Y2: 미수이자 | Z2: 선납원천세 | AA2: 미지급원천세 | AB2: 예수원천세 | AC2: 대조원천세 | AD2: 평가손익 | AE2: 단가 | AF2: 미지급비용 | AG2: 중개기관 | AH2: 거래상대방 | AI2: repo담보채권 | AJ2: repo담보수량 | AK2: 원화미수입금 | AL2: 원화미지급금
A3: KRWDPT000000 | B3: KRWDPT000000 | C3: [KRW] 예금 | D3: 예금 | E3: 2.07 | F3: 0 | G3: 0 | H3: 후급 | I3: 14 | J3: 비과세 | K3: 7196301321 | L3: 0 | M3: 0 | N3: 19000101 | O3: 20991231 | Q3: 7196301321 | R3: 7202532493 | S3: 7202532493 | T3: 0 | U3: 46021/73048 | V3: 0 | W3: 0 | X3: d/365 | Y3: 6231172 | Z3: 0 | AA3: 0 | AB3: 0 | AC3: 0 | AD3: 0 | AE3: 0 | AF3: 0 | AJ3: 0
A4: KRYZREPGLDVJ | B4: R00130523FCX | C4: Repo(매도)-20251230 | D4: REPO발행(차입) | E4: 2.63 | F4: 0 | G4: 0 | K4: 5000000000 | L4: 0 | M4: 5003602739 | N4: 20251230 | O4: 20260109 | P4: 20251230 | Q4: 5000000000 | R4: 5000720547 | S4: 5000720547 | T4: 0 | U4: 46063 | V4: 0 | W4: 0 | Y4: 720547 | Z4: 0 | AA4: 0 | AB4: 0 | AC4: 0 | AD4: 0 | AE4: 0 | AF4: 30000 | AG4: BGC캐피탈마켓외국환중개 | AH4: 우리은행 | AI4: KR103502G990 | AJ4: 0

Sheet 외화위탁증거금
A1: Column1 | B1: Column2 | C1: Column3 | D1: Column4 | E1: Column5 | F1: Column6 | G1: Column7 | H1: Column8 | I1: Column9 | J1: Column10 | K1: Column11
A2: 종목코드 | B2: 종목명 | C2: 통화 | D2: 평균환율 | E2: 당일환율 | F2: 매매처명 | G2: 외화증거금 | H2: 원화증거금 | I2: 환산증거금 | J2: 환산손익 | K2: 당일환산손익
A3: KRWMGN000000 | C3: KRW | D3: 1 | F3: 종목132 | G3: 238000000 | H3: 238000000 | I3: 238000000 | J3: 0 | K3: 0
A4: KRWMGN000000 | C4: KRW | D4: 1 | F4: SK증권 | G4: 32251240 | H4: 32251240 | I4: 32251240 | J4: 0 | K4: 0
A5: KRWMGN000000 | C5: KRW | D5: 1 | F5: 하이투자증권 | G5: 229600000 | H5: 229600000 | I5: 229600000 | J5: 0 | K5: 0
A6: KRWMGN000000 | C6: KRW | D6: 1 | F6: 종목170 | G6: 211451240 | H6: 211451240 | I6: 211451240 | J6: 0 | K6: 0

Sheet 담보내역
Q2: 2025-12-31 ~ 2025-12-31
C3: 대용증권·담보설정내역
Q4: 전체
C5: Korea Fund Partners | Q5: 펀드
A9: 일자 | D9: 수탁사 | E9: 펀드 | F9: 펀드명 | H9: 매매처 | K9: 자산구분 | L9: 종목코드 | M9: 종목명 | N9: 대용금액(수량) | O9: 실제금액(수량) | S9: 대용지정일 | T9: 설정구분 | V9: 전략구분 | AA9: 거래번호
A10: 20251231 | D10: 한아름은행 | E10: 490114 | F10: TIGER 레버리지 | H10: BGC캐피탈마켓외국환중개 | K10: 채권 - Repo매도담보 | L10: KR103502G990 | M10: 국고01125-3909(19-6) | N10: 7100000000 | O10: 7100000000 | S10: 20251230 | T10: Repo매도담보
A11: 20251231 | D11: 한아름은행 | E11: 490114 | F11: TIGER 레버리지 | H11: 한화투자증권 | K11: 주식 - 대용 | L11: KR7000270009 | M11: 종목126 | N11: 3500 | O11: 12705 | S11: 20240712 | T11: 대용 | AA11: M000000000 | AD11: 행 레이블 | AE11: 합계 : 대용금액(수량) | AF11: 장부가액
A12: 20251231 | D12: 한아름은행 | E12: 490114 | F12: TIGER 레버리지 | H12: 종목132 | K12: 주식 - 대용 | L12: KR7000660001 | M12: 종목183 | N12: 3500 | O12: 29435 | S12: 20200313 | T12: 대용 | AA12: M000000000 | AD12: 종목090 | AE12: 5900 | AF12: =_xleta.XLOOKUP -> #VALUE!
A13: 20251231 | D13: 한아름은행 | E13: 490114 | F13: TIGER 레버리지 | H13: iM증권 | K13: 주식 - 대용 | L13: KR7000660001 | M13: 종목183 | N13: 4600 | O13: 29435 | S13: 20200313 | T13: 대용 | AA13: M000000000 | AD13: 종목115 | AE13: 1300
A14: 20251231 | D14: 한아름은행 | E14: 490114 | F14: TIGER 레버리지 | H14: 종목170 | K14: 주식 - 대용 | L14: KR7000660001 | M14: 종목183 | N14: 5000 | O14: 29435 | S14: 20251230 | T14: 대용 | AA14: M000000000 | AD14: 종목065 | AE14: 2000
A15: 20251231 | D15: 한아름은행 | E15: 490114 | F15: TIGER 레버리지 | H15: 한국예탁결제원 | K15: 주식 - 대차담보 | L15: KR7000660001 | M15: 종목183 | N15: 4000 | O15: 29435 | S15: 20220629 | T15: 대차담보 | AA15: M000000000 | AD15: 종목040 | AE15: 500
A16: 20251231 | D16: 한아름은행 | E16: 490114 | F16: TIGER 레버리지 | H16: 한화투자증권 | K16: 주식 - 대용 | L16: KR7000810002 | M16: 종목078 | N16: 500 | O16: 1575 | S16: 20240712 | T16: 대용 | AA16: M000000000 | AD16: 종목143 | AE16: 1900
A17: 20251231 | D17: 한아름은행 | E17: 490114 | F17: TIGER 레버리지 | H17: 한국예탁결제원 | K17: 주식 - 대차담보 | L17: KR7005380001 | M17: 종목081 | N17: 2000 | O17: 7070 | S17: 20210928 | T17: 대차담보 | AA17: M000000000 | AD17: 종목059 | AE17: 1000
A18: 20251231 | D18: 한아름은행 | E18: 490114 | F18: TIGER 레버리지 | H18: 한화투자증권 | K18: 주식 - 대용 | L18: KR7005490008 | M18: 종목059 | N18: 1000 | O18: 3605 | S18: 20240712 | T18: 대용 | AA18: M000000000 | AD18: 종목183 | AE18: 17100
A19: 20251231 | D19: 한아름은행 | E19: 490114 | F19: TIGER 레버리지 | H19: 종목132 | K19: 주식 - 대용 | L19: KR7005930003 | M19: 종목188 | N19: 35000 | O19: 245315 | S19: 20180706 | T19: 대용 | AA19: M000000000 | AD19: 종목ETF001 | AE19: 265600
A20: 20251231 | D20: 한아름은행 | E20: 490114 | F20: TIGER 레버리지 | H20: 한화투자증권 | K20: 주식 - 대용 | L20: KR7005930003 | M20: 종목188 | N20: 25000 | O20: 245315 | S20: 20251230 | T20: 대용 | AA20: M000000000 | AD20: 국고01125-3909(19-6) | AE20: 7100000000
A21: 20251231 | D21: 한아름은행 | E21: 490114 | F21: TIGER 레버리지 | H21: SK증권 | K21: 주식 - 대용 | L21: KR7005930003 | M21: 종목188 | N21: 48000 | O21: 245315 | S21: 20200831 | T21: 대용 | AA21: M000000000 | AD21: 종목126 | AE21: 3500
A22: 20251231 | D22: 한아름은행 | E22: 490114 | F22: TIGER 레버리지 | H22: iM증권 | K22: 주식 - 대용 | L22: KR7005930003 | M22: 종목188 | N22: 9876 | O22: 245315 | S22: 20190924 | T22: 대용 | AA22: M000000000 | AD22: 종목035 | AE22: 1300
A23: 20251231 | D23: 한아름은행 | E23: 490114 | F23: TIGER 레버리지 | H23: 한국예탁결제원 | K23: 주식 - 대차담보 | L23: KR7005930003 | M23: 종목188 | N23: 54000 | O23: 245315 | S23: 20180605 | T23: 대차담보 | AA23: M000000000 | AD23: 종목188 | AE23: 171876
A24: 20251231 | D24: 한아름은행 | E24: 490114 | F24: TIGER 레버리지 | H24: 한국예탁결제원 | K24: 주식 - 대차담보 | L24: KR7012330007 | M24: 종목086 | N24: 902 | O24: 3220 | S24: 20180316 | T24: 대차담보 | AA24: M000000000 | AD24: 종목078 | AE24: 500
... A31: 20251231 | D31: 한아름은행 | E31: 490114 | F31: TIGER 레버리지 | H31: 한화투자증권 | K31: 주식 - 대용 | L31: KR7066570003 | M31: 종목065 | N31: 2000 | O31: 5635 | S31: 20240712 | T31: 대용 | AA31: M000000000 | AD31: 총합계 | AE31: 7100498294
A32: 20251231 | D32: 한아름은행 | E32: 490114 | F32: TIGER 레버리지 | H32: 한화투자증권 | K32: 주식 - 대용 | L32: KR7086790003 | M32: 종목069 | N32: 3500 | O32: 13125 | S32: 20240712 | T32: 대용 | AA32: M000000000
A33: 20251231 | D33: 한아름은행 | E33: 490114 | F33: TIGER 레버리지 | H33: 한화투자증권 | K33: 주식 - 대용 | L33: KR7102110004 | M33: 종목ETF001 | N33: 10000 | O33: 401506 | S33: 20240119 | T33: 대용 | AA33: M000000000
A34: 20251231 | D34: 한아름은행 | E34: 490114 | F34: TIGER 레버리지 | H34: iM증권 | K34: 주식 - 대용 | L34: KR7102110004 | M34: 종목ETF001 | N34: 18000 | O34: 401506 | S34: 20200416 | T34: 대용 | AA34: M000000000
A35: 20251231 | D35: 한아름은행 | E35: 490114 | F35: TIGER 레버리지 | H35: 종목170 | K35: 주식 - 대용 | L35: KR7102110004 | M35: 종목ETF001 | N35: 37600 | O35: 401506 | S35: 20200416 | T35: 대용 | AA35: M000000000
A36: 20251231 | D36: 한아름은행 | E36: 490114 | F36: TIGER 레버리지 | H36: 증권금융 | K36: 주식 - 대차담보 | L36: KR7102110004 | M36: 종목ETF001 | N36: 200000 | O36: 401506 | S36: 20251229 | T36: 대차담보 | AA36: M000000000
A37: 20251231 | D37: 한아름은행 | E37: 490114 | F37: TIGER 레버리지 | H37: 한국예탁결제원 | K37: 주식 - 대차담보 | L37: KR7105560007 | M37: 종목090 | N37: 5900 | O37: 17010 | S37: 20200323 | T37: 대차담보 | AA37: M000000000
A38: 20251231 | D38: 한아름은행 | E38: 490114 | F38: TIGER 레버리지 | H38: SK증권 | K38: 주식 - 대용 | L38: KR7316140003 | M38: 종목177 | N38: 7750 | O38: 35070 | S38: 20200831 | T38: 대용 | AA38: M000000000
N39: 7100498294 | O39: 7103108364
A40: 합계: | N40: 14200996588 | O40: 14206216728
A43: Page : | B43: 2 of 2 | J43: Screen No. 6307 | P43: Date. | R43: 46037.641 | U43: Printed By. | Y43: 엄재빈

Sheet 채권명세
A1: 종목코드 | B1: 표준코드 | C1: 종목명 | D1: 종목통화 | E1: 펀드통화 | F1: 종류 | G1: 코스콤대분류 | H1: 발행률 | I1: 할인률 | J1: 할증률 | K1: 시장률 | L1: 반영률 | M1: 매입률 | N1: 액면 | O1: 대용/대차/선도매도 | P1: 발행일 | Q1: 만기일 | R1: 매입일 | S1: 취득원가(종목통화) | T1: 장부가평가액(종목통화) | U1: 시가평가금액(종목통화) | V1: 취득원가(펀드통화) | W1: 장부가평가액(펀드통화) | X1: 시가평가금액(펀드통화) | Y1: 상환손익 | Z1: 총경과/총일수 | AA1: 기경과이자 | AB1: 선수이자 | AC1: 선후급 | AD1: 경과/구간 | AE1: 미수이자 | AF1: 선납원천세 | AG1: 미지급원천세 | AH1: 예수원천세 | AI1: 대조원천세 | AJ1: 평가손익 | AK1: 단가 | AL1: 신용등급 | AM1: 미수입금 | AN1: 미지급금
A2: KR103502G990 | B2: KR103502G990 | C2: 국고채권01125-3909(19-6) | D2: KRW | E2: KRW | F2: 이표(확정) | G2: 국채 | H2: 1.125 | I2: 0 | J2: 0 | K2: 3.36 | L2: 3.36 | M2: 0 | N2: 7100000000 | O2: 7100000000 | P2: 20190910 | Q2: 20390910 | R2: 20251229 | S2: 5366076992 | T2: 5391842045 | U2: 5393607300 | V2: 5366076992 | W2: 5391842045 | X2: 5393607300 | Y2: 831697 | Z2: 2304/7305 | AA2: 24271408 | AB2: 0 | AC2: 후급 | AD2: 74/181 | AE2: 661948 | AF2: 0 | AG2: 0 | AH2: 0 | AI2: 101940 | AJ2: 1765255 | AK2: 7596.63 | AL2: 0

Sheet 국내주식명세
A1: Column1 | B1: Column2 | C1: Column3 | D1: Column4 | E1: Column5 | F1: Column6 | G1: Column7 | H1: Column8 | I1: Column9 | J1: Column10 | K1: Column11
A2: 종목 | B2: 종목명 | C2: 상품구분 | D2: 수량 | E2: 취득가액 | F2: 종가 | G2: 평가금액 | H2: 평가손익 | I2: 미수입금 | J2: 미지급금 | K2: 미지급주식납입금
A3: KR7001440007 | B3: 종목002 | C3: 거래소 | D3: 5880 | E3: 91764961 | F3: 22900 | G3: 134652000 | H3: 42887039 | K3: 0 | L3: =D3*F3 -> 134652000
A4: KR7002380004 | B4: 종목003 | C4: 거래소 | D4: 210 | E4: 63483000 | F4: 420500 | G4: 88305000 | H4: 24822000 | K4: 0 | L4: =D4*F4 -> 88305000
A5: KR7003230000 | B5: 종목004 | C5: 거래소 | D5: 210 | E5: 204090000 | F5: 1231000 | G5: 258510000 | H5: 54420000 | K5: 0 | L5: =D5*F5 -> 258510000
A6: KR7003240009 | B6: 종목005 | C6: 거래소 | D6: 35 | E6: 28063230 | F6: 762000 | G6: 26670000 | H6: -1393230 | K6: 0 | L6: =D6*F6 -> 26670000
A7: KR7003670007 | B7: 종목006 | C7: 거래소 | D7: 1855 | E7: 311085250 | F7: 187000 | G7: 346885000 | H7: 35799750 | K7: 0 | L7: =D7*F7 -> 346885000
A8: KR7004490009 | B8: 종목007 | C8: 거래소 | D8: 420 | E8: 28544400 | F8: 62800 | G8: 26376000 | H8: -2168400 | K8: 0 | L8: =D8*F8 -> 26376000
A9: KR7007660004 | B9: 종목008 | C9: 거래소 | D9: 2835 | E9: 402100300 | F9: 119200 | G9: 337932000 | H9: -64168300 | K9: 0 | L9: =D9*F9 -> 337932000
A10: KR7009150004 | B10: 종목009 | C10: 거래소 | D10: 2905 | E10: 492148503 | F10: 255000 | G10: 740775000 | H10: 248626497 | K10: 0 | L10: =D10*F10 -> 740775000
A11: KR7009540006 | B11: 종목010 | C11: 거래소 | D11: 2450 | E11: 727251001 | F11: 407000 | G11: 997150000 | H11: 269898999 | K11: 0 | L11: =D11*F11 -> 997150000
A12: KR7010130003 | B12: 종목011 | C12: 거래소 | D12: 350 | E12: 363583220 | F12: 1316000 | G12: 460600000 | H12: 97016780 | K12: 0 | L12: =D12*F12 -> 460600000
A13: KR7010950004 | B13: 종목012 | C13: 거래소 | D13: 2170 | E13: 139159001 | F13: 83000 | G13: 180110000 | H13: 40950999 | K13: 0 | L13: =D13*F13 -> 180110000
A14: KR7017800004 | B14: 종목013 | C14: 거래소 | D14: 1330 | E14: 86271401 | F14: 88300 | G14: 117439000 | H14: 31167599 | K14: 0 | L14: =D14*F14 -> 117439000
... A205: KR7361610009 | B205: 종목205 | C205: 거래소 | D205: 1960 | E205: 50836120 | F205: 25050 | G205: 49098000 | H205: -1738120 | K205: 0 | L205: =D205*F205 -> 49098000
A206: KR7450080007 | B206: 종목206 | C206: 거래소 | D206: 1330 | E206: 79251490 | F206: 52100 | G206: 69293000 | H206: -9958490 | K206: 0

Sheet 수익증권명세
A1: Column1 | B1: Column2 | C1: Column3 | D1: Column4 | E1: Column5 | F1: Column6 | G1: Column7 | H1: Column8 | I1: Column9 | J1: Column10 | K1: Column11 | L1: Column12 | M1: Column13
A2: 종목코드 | B2: 표준코드 | C2: 종목명 | D2: 상품구분 | E2: 발행기관 | F2: 매입일 | G2: 좌수 | H2: 대용/대차 | I2: 기준가격 | J2: 평가금액 | K2: 취득가액 | L2: 평가손익 | M2: 과세가격1 | N2: 과세평가금액1 | O2: 과세취득가액1 | P2: 과세평가손익1 | Q2: 비과세손익1 | R2: 과세가격2 | S2: 과세평가금액2 | T2: 과세취득가액2 | U2: 과세평가손익2 | V2: 비과세손익2 | W2: 미수입금 | X2: 미지급금 | Y2: 해외자산비과세가격 | Z2: 해외자산비과세평가금액 | AA2: 해외자산비과세취득가액 | AB2: 해외자산비과세평가손익
A3: KR7102110004 | B3: KR7102110004 | C3: 종목ETF001 | D3: 상장집합투자증권 | E3: 10211 | G3: 401506 | H3: 265600 | I3: 60930 | J3: 24463760580 | K3: 23417443577 | L3: 1046317003 | M3: 22562.36 | N3: 9058922914 | O3: 9029373579 | P3: 29549335 | Q3: 1016767668 | R3: 22562.36 | S3: 9058922914 | T3: 9029373579 | U3: 29549335 | V3: 1016767668 | W3: 8837106649 | X3: 4547096890 | Y3: 22562.36 | Z3: 9058922914 | AA3: 9029373579 | AB3: 29549335
J12: =H3/G3 -> 0.66150942

Sheet 선물명세
A1: Column1 | B1: Column2 | C1: Column3 | D1: Column4 | E1: Column5 | F1: Column6 | G1: Column7 | H1: Column8 | I1: Column9 | J1: Column10 | K1: Column11 | L1: Column12 | M1: Column13 | N1: Column14 | O1: Column15
A2: 매매처 | B2: 매매처명 | C2: 종목 | D2: 표준코드 | E2: 종목명 | F2: 포지션 | G2: 계약수 | H2: 정산가 | I2: 평가금액 | J2: 취득가액 | K2: 정산손익 | L2: 미수입금 | M2: 미지급금 | N2: 결산손익 | O2: 선물수수료
A3: 000012 | B3: 종목132 | C3: KR4A01630008 | D3: KR4A01630008 | E3: 선물2026년03월물 | F3: 선물매수 | G3: 182 | H3: 608 | I3: 27664000000 | J3: 26650965056 | K3: 1013034944 | L3: 120575000 | M3: 0 | N3: 0 | O3: 0
A4: 000021 | B4: 한화투자증권 | C4: KR4A01630008 | D4: KR4A01630008 | E4: 선물2026년03월물 | F4: 선물매수 | G4: 179 | H4: 608 | I4: 27208000000 | J4: 26296087500 | K4: 911912500 | L4: 118587500 | M4: 0 | N4: 0 | O4: 0
A5: 000025 | B5: SK증권 | C5: KR4A01630008 | D5: KR4A01630008 | E5: 선물2026년03월물 | F5: 선물매수 | G5: 179 | H5: 608 | I5: 27208000000 | J5: 26071238500 | K5: 1136761500 | L5: 118587500 | M5: 0 | N5: 0 | O5: 0
A6: 000046 | B6: iM증권 | C6: KR4A01630008 | D6: KR4A01630008 | E6: 선물2026년03월물 | F6: 선물매수 | G6: 165 | H6: 608 | I6: 25080000000 | J6: 24050546159 | K6: 1029453841 | L6: 109312500 | M6: 0 | N6: 0 | O6: 0
A7: 000050 | B7: 종목170 | C7: KR4A01630008 | D7: KR4A01630008 | E7: 선물2026년03월물 | F7: 선물매수 | G7: 178 | H7: 608 | I7: 27056000000 | J7: 26053215256 | K7: 1002784744 | L7: 117925000 | M7: 0 | N7: 0 | O7: 0

Sheet 보수분배내역
A1: 결산구분 | B1: 기준일 | C1: 펀드 | D1: 펀드명 | E1: 매매처명 | F1: 당일보수 | G1: 미지급보수
A2: 전기 | B2: 20240101 | C2: 490114 | D2: 한빛코스피레버리지증권상장지수투자신탁(주식-파생형) | E2: 교보증권 | F2: 0 | G2: -339022
A3: 전기 | B3: 20240101 | C3: 490114 | D3: 한빛코스피레버리지증권상장지수투자신탁(주식-파생형) | E3: 신한투자증권 | F3: 75 | G3: -22104426
A4: 전기 | B4: 20240101 | C4: 490114 | D4: 한빛코스피레버리지증권상장지수투자신탁(주식-파생형) | E4: 한국투자증권 | F4: 0 | G4: -2334579
A5: 전기 | B5: 20240101 | C5: 490114 | D5: 한빛코스피레버리지증권상장지수투자신탁(주식-파생형) | E5: 종목028 | F5: 0 | G5: -57940556
A6: 전기 | B6: 20240101 | C6: 490114 | D6: 한빛코스피레버리지증권상장지수투자신탁(주식-파생형) | E6: 유진투자증권 | F6: 51 | G6: 8888108
A7: 전기 | B7: 20240101 | C7: 490114 | D7: 한빛코스피레버리지증권상장지수투자신탁(주식-파생형) | E7: 메리츠증권 | F7: 58 | G7: 12570242 | J7: 행 레이블 | K7: 합계 : 당일보수
A8: 전기 | B8: 20240101 | C8: 490114 | D8: 한빛코스피레버리지증권상장지수투자신탁(주식-파생형) | E8: 종목132 | F8: 405 | G8: 11188202 | J8: BNK투자증권 | K8: 0
A9: 전기 | B9: 20240101 | C9: 490114 | D9: 한빛코스피레버리지증권상장지수투자신탁(주식-파생형) | E9: KB증권 | F9: 99 | G9: 10586187 | J9: DB금융투자 | K9: 13473
A10: 전기 | B10: 20240101 | C10: 490114 | D10: 한빛코스피레버리지증권상장지수투자신탁(주식-파생형) | E10: 한화투자증권 | F10: 0 | G10: -771017 | J10: iM증권 | K10: 32802
A11: 전기 | B11: 20240101 | C11: 490114 | D11: 한빛코스피레버리지증권상장지수투자신탁(주식-파생형) | E11: SK증권 | F11: 0 | G11: -17321879 | J11: KB증권 | K11: 32802
A12: 전기 | B12: 20240101 | C12: 490114 | D12: 한빛코스피레버리지증권상장지수투자신탁(주식-파생형) | E12: DB증권 | F12: 41 | G12: 2164452 | J12: 종목132 | K12: 160540
A13: 전기 | B13: 20240101 | C13: 490114 | D13: 한빛코스피레버리지증권상장지수투자신탁(주식-파생형) | E13: iM증권 | F13: 99 | G13: 49595918 | J13: SK증권 | K13: 0
A14: 전기 | B14: 20240101 | C14: 490114 | D14: 한빛코스피레버리지증권상장지수투자신탁(주식-파생형) | E14: 종목170 | F14: 10 | G14: -130199 | J14: 교보증권 | K14: 0
A15: 전기 | B15: 20240101 | C15: 490114 | D15: 한빛코스피레버리지증권상장지수투자신탁(주식-파생형) | E15: 리딩투자증권 | F15: 161 | G15: 24255437 | J15: 다올투자증권 | K15: 376
A16: 전기 | B16: 20240101 | C16: 490114 | D16: 한빛코스피레버리지증권상장지수투자신탁(주식-파생형) | E16: 하나증권 | F16: 161 | G16: -510561 | J16: 리딩투자증권 | K16: 53281
A17: 전기 | B17: 20240101 | C17: 490114 | D17: 한빛코스피레버리지증권상장지수투자신탁(주식-파생형) | E17: 아이비케이투자증권 | F17: 0 | G17: -183 | J17: 메리츠증권 | K17: 19149
A18: 전기 | B18: 20240101 | C18: 490114 | D18: 한빛코스피레버리지증권상장지수투자신탁(주식-파생형) | E18: 다올투자증권 | F18: 0 | G18: -1217 | J18: 종목028 | K18: 0
A19: 전기 | B19: 20240101 | C19: 490114 | D19: 한빛코스피레버리지증권상장지수투자신탁(주식-파생형) | E19: BNK투자증권 | F19: 0 | G19: -56 | J19: 신한투자증권 | K19: 24838
... A27: 전기 | B27: 20240102 | C27: 490114 | D27: 한빛코스피레버리지증권상장지수투자신탁(주식-파생형) | E27: 종목132 | F27: 408 | G27: 11188610 | J27: 총합계 | K27: 410665
A28: 전기 | B28: 20240102 | C28: 490114 | D28: 한빛코스피레버리지증권상장지수투자신탁(주식-파생형) | E28: KB증권 | F28: 100 | G28: 10586287
A29: 전기 | B29: 20240102 | C29: 490114 | D29: 한빛코스피레버리지증권상장지수투자신탁(주식-파생형) | E29: 한화투자증권 | F29: 0 | G29: -771017
A30: 전기 | B30: 20240102 | C30: 490114 | D30: 한빛코스피레버리지증권상장지수투자신탁(주식-파생형) | E30: SK증권 | F30: 0 | G30: -17321879
A31: 전기 | B31: 20240102 | C31: 490114 | D31: 한빛코스피레버리지증권상장지수투자신탁(주식-파생형) | E31: DB증권 | F31: 41 | G31: 2164493
A32: 전기 | B32: 20240102 | C32: 490114 | D32: 한빛코스피레버리지증권상장지수투자신탁(주식-파생형) | E32: iM증권 | F32: 100 | G32: 49596018
A33: 전기 | B33: 20240102 | C33: 490114 | D33: 한빛코스피레버리지증권상장지수투자신탁(주식-파생형) | E33: 종목170 | F33: 10 | G33: -130189
A34: 전기 | B34: 20240102 | C34: 490114 | D34: 한빛코스피레버리지증권상장지수투자신탁(주식-파생형) | E34: 리딩투자증권 | F34: 163 | G34: 24255600
A35: 전기 | B35: 20240102 | C35: 490114 | D35: 한빛코스피레버리지증권상장지수투자신탁(주식-파생형) | E35: 하나증권 | F35: 163 | G35: -510398
A36: 전기 | B36: 20240102 | C36: 490114 | D36: 한빛코스피레버리지증권상장지수투자신탁(주식-파생형) | E36: 아이비케이투자증권 | F36: 0 | G36: -183
A37: 전기 | B37: 20240102 | C37: 490114 | D37: 한빛코스피레버리지증권상장지수투자신탁(주식-파생형) | E37: 다올투자증권 | F37: 0 | G37: -1217
A38: 전기 | B38: 20240102 | C38: 490114 | D38: 한빛코스피레버리지증권상장지수투자신탁(주식-파생형) | E38: BNK투자증권 | F38: 0 | G38: -56
A39: 전기 | B39: 20240102 | C39: 490114 | D39: 한빛코스피레버리지증권상장지수투자신탁(주식-파생형) | E39: 엘에스증권 | F39: 0 | G39: -17686380
... A13890: 당기 | B13890: 20251231 | C13890: 490114 | D13890: 한빛코스피레버리지증권상장지수투자신탁(주식-파생형) | E13890: 엘에스증권 | F13890: 0 | G13890: -17693191

Sheet 일별자산내역
A1: 기준일 | B1: 예금 | C1: 예금미수이자 | D1: 콜론 | E1: 콜미수이자 | F1: 정기예금 | G1: 정기예금미수이자 | H1: REPO | I1: REPO미수이자 | J1: 채권 | K1: 채권미수이자 | L1: 외화예금 | M1: 외화정기예금 | N1: 외화예금미수이자 | O1: 외화채권 | P1: 외화채권미수이자
A2: 20250101 | B2: 2246153208 | C2: 6677642 | D2: 0 | E2: 0 | F2: 0 | G2: 0 | H2: 0 | I2: 0 | J2: 0 | K2: 0 | L2: 0 | M2: 0 | N2: 0 | O2: 0 | P2: 0
A3: 20250102 | B3: 2070075158 | C3: 299179 | D3: 0 | E3: 0 | F3: 0 | G3: 0 | H3: 0 | I3: 0 | J3: 0 | K3: 0 | L3: 0 | M3: 0 | N3: 0 | O3: 0 | P3: 0
A4: 20250103 | B4: 1920549798 | C4: 432302 | D4: 0 | E4: 0 | F4: 0 | G4: 0 | H4: 0 | I4: 0 | J4: 0 | K4: 0 | L4: 0 | M4: 0 | N4: 0 | O4: 0 | P4: 0
A5: 20250104 | B5: 1920549798 | C5: 565425 | D5: 0 | E5: 0 | F5: 0 | G5: 0 | H5: 0 | I5: 0 | J5: 0 | K5: 0 | L5: 0 | M5: 0 | N5: 0 | O5: 0 | P5: 0
A6: 20250105 | B6: 1920549798 | C6: 698548 | D6: 0 | E6: 0 | F6: 0 | G6: 0 | H6: 0 | I6: 0 | J6: 0 | K6: 0 | L6: 0 | M6: 0 | N6: 0 | O6: 0 | P6: 0
A7: 20250106 | B7: 2980106153 | C7: 905115 | D7: 0 | E7: 0 | F7: 0 | G7: 0 | H7: 0 | I7: 0 | J7: 0 | K7: 0 | L7: 0 | M7: 0 | N7: 0 | O7: 0 | P7: 0
A8: 20250107 | B8: 3834228990 | C8: 1170884 | D8: 0 | E8: 0 | F8: 0 | G8: 0 | H8: 0 | I8: 0 | J8: 0 | K8: 0 | L8: 0 | M8: 0 | N8: 0 | O8: 0 | P8: 0
A9: 20250108 | B9: 3944491069 | C9: 1444297 | D9: 0 | E9: 0 | F9: 0 | G9: 0 | H9: 0 | I9: 0 | J9: 0 | K9: 0 | L9: 0 | M9: 0 | N9: 0 | O9: 0 | P9: 0
A10: 20250109 | B10: 4249095783 | C10: 1738823 | D10: 0 | E10: 0 | F10: 0 | G10: 0 | H10: 0 | I10: 0 | J10: 0 | K10: 0 | L10: 0 | M10: 0 | N10: 0 | O10: 0 | P10: 0
A11: 20250110 | B11: 3259141963 | C11: 1964731 | D11: 0 | E11: 0 | F11: 0 | G11: 0 | H11: 0 | I11: 0 | J11: 0 | K11: 0 | L11: 0 | M11: 0 | N11: 0 | O11: 0 | P11: 0
A12: 20250111 | B12: 3259141963 | C12: 2190639 | D12: 0 | E12: 0 | F12: 0 | G12: 0 | H12: 0 | I12: 0 | J12: 0 | K12: 0 | L12: 0 | M12: 0 | N12: 0 | O12: 0 | P12: 0
A13: 20250112 | B13: 3259141963 | C13: 2416546 | D13: 0 | E13: 0 | F13: 0 | G13: 0 | H13: 0 | I13: 0 | J13: 0 | K13: 0 | L13: 0 | M13: 0 | N13: 0 | O13: 0 | P13: 0
... A366: 20251231 | B366: 7196301321 | C366: 6231172 | D366: 0 | E366: 0 | F366: 0 | G366: 0 | H366: 0 | I366: 0 | J366: 5368673944 | K366: 661948 | L366: 0 | M366: 0 | N366: 0 | O366: 0 | P366: 0

Sheet ETF보수 추가자료
A1: 분배기준일 | B1: 펀드코드 | C1: 펀드명 | D1: 판매사코드 | E1: 판매사명 | F1: 설정환매보수1 | G1: 설정환매보수2 | H1: 유동성기여보수 | I1: 보수합계 | J1: 지급기준일 | K1: 보수인출일
A2: 46022 | B2: 490114 | C2: TIGER 레버리지 | D2: 000001 | E2: 교보증권 | F2: 3 | G2: 0 | H2: 0 | I2: 3 | J2: 46022 | K2: 46031
A3: 46022 | B3: 490114 | C3: TIGER 레버리지 | D3: 000002 | E3: 신한투자증권 | F3: 2573 | G3: 0 | H3: 0 | I3: 2573 | J3: 46022 | K3: 46031
A4: 46022 | B4: 490114 | C4: TIGER 레버리지 | D4: 000003 | E4: 한국투자증권 | F4: 2056 | G4: 0 | H4: 0 | I4: 2056 | J4: 46022 | K4: 46031
A5: 46022 | B5: 490114 | C5: TIGER 레버리지 | D5: 000005 | E5: 종목028 | F5: 6938 | G5: 10463 | H5: 91830 | I5: 109231 | J5: 46022 | K5: 46031
A6: 46022 | B6: 490114 | C6: TIGER 레버리지 | D6: 000008 | E6: 유진투자증권 | F6: 535 | G6: 0 | H6: 0 | I6: 535 | J6: 46022 | K6: 46031
A7: 46022 | B7: 490114 | C7: TIGER 레버리지 | D7: 000010 | E7: 메리츠증권 | F7: 501 | G7: 0 | H7: 0 | I7: 501 | J7: 46022 | K7: 46031
A8: 46022 | B8: 490114 | C8: TIGER 레버리지 | D8: 000012 | E8: 종목132 | F8: 3575 | G8: 10466 | H8: 69046 | I8: 83087 | J8: 46022 | K8: 46031
A9: 46022 | B9: 490114 | C9: TIGER 레버리지 | D9: 000017 | E9: KB증권 | F9: 1213 | G9: 0 | H9: 0 | I9: 1213 | J9: 46022 | K9: 46031
A10: 46022 | B10: 490114 | C10: TIGER 레버리지 | D10: 000021 | E10: 한화투자증권 | F10: 80 | G10: 0 | H10: 0 | I10: 80 | J10: 46022 | K10: 46031
A11: 46022 | B11: 490114 | C11: TIGER 레버리지 | D11: 000025 | E11: SK증권 | F11: 57 | G11: 0 | H11: 0 | I11: 57 | J11: 46022 | K11: 46031
A12: 46022 | B12: 490114 | C12: TIGER 레버리지 | D12: 000031 | E12: DB증권 | F12: 47 | G12: 0 | H12: 0 | I12: 47 | J12: 46022 | K12: 46031
A13: 46022 | B13: 490114 | C13: TIGER 레버리지 | D13: 000042 | E13: 크레디트스위스증권 | F13: 0 | G13: 0 | H13: 0 | I13: 0 | J13: 46022 | K13: 46031
... A21: 46022 | B21: 490114 | C21: TIGER 레버리지 | D21: 000752 | E21: 엘에스증권 | F21: 919 | G21: 0 | H21: 0 | I21: 919 | J21: 46022 | K21: 46031
A27: 분배기준일 | B27: 펀드코드 | C27: 펀드명 | D27: 판매사코드 | E27: 판매사명 | F27: 설정환매보수1 | G27: 설정환매보수2 | H27: 유동성기여보수 | I27: 보수합계 | J27: 지급기준일 | K27: 보수인출일
A28: 45688 | B28: 490114 | C28: TIGER 레버리지 | D28: 000005 | E28: 종목028 | F28: 1139 | G28: 1139 | H28: 0 | I28: 2278 | J28: 45747 | K28: 45755
A29: 45716 | B29: 490114 | C29: TIGER 레버리지 | D29: 000005 | E29: 종목028 | F29: 2204 | G29: 0 | H29: 0 | I29: 2204 | J29: 45747 | K29: 45755
A30: 45747 | B30: 490114 | C30: TIGER 레버리지 | D30: 000005 | E30: 종목028 | F30: 3350 | G30: 0 | H30: 0 | I30: 3350 | J30: 45747 | K30: 45755
A31: 45777 | B31: 490114 | C31: TIGER 레버리지 | D31: 000005 | E31: 종목028 | F31: 1176 | G31: 0 | H31: 0 | I31: 1176 | J31: 45838 | K31: 45846
A32: 45808 | B32: 490114 | C32: TIGER 레버리지 | D32: 000005 | E32: 종목028 | F32: 2418 | G32: 0 | H32: 0 | I32: 2418 | J32: 45838 | K32: 45846
A33: 45838 | B33: 490114 | C33: TIGER 레버리지 | D33: 000005 | E33: 종목028 | F33: 3680 | G33: 0 | H33: 0 | I33: 3680 | J33: 45838 | K33: 45846
A34: 45869 | B34: 490114 | C34: TIGER 레버리지 | D34: 000005 | E34: 종목028 | F34: 1219 | G34: 0 | H34: 0 | I34: 1219 | J34: 45930 | K34: 45945
A35: 45900 | B35: 490114 | C35: TIGER 레버리지 | D35: 000005 | E35: 종목028 | F35: 2327 | G35: 0 | H35: 0 | I35: 2327 | J35: 45930 | K35: 45945
A36: 45930 | B36: 490114 | C36: TIGER 레버리지 | D36: 000005 | E36: 종목028 | F36: 3398 | G36: 0 | H36: 0 | I36: 3398 | J36: 45930 | K36: 45945
A37: 45961 | B37: 490114 | C37: TIGER 레버리지 | D37: 000005 | E37: 종목028 | F37: 1646 | G37: 3992 | H37: 0 | I37: 5638 | J37: 46022 | K37: 46031
A38: 45991 | B38: 490114 | C38: TIGER 레버리지 | D38: 000005 | E38: 종목028 | F38: 4252 | G38: 7755 | H38: 0 | I38: 12007 | J38: 46022 | K38: 46031
A39: 46022 | B39: 490114 | C39: TIGER 레버리지 | D39: 000005 | E39: 종목028 | F39: 6938 | G39: 10463 | H39: 91830 | I39: 109231 | J39: 46022 | K39: 46031
I40: =I30+I33+I36+I39 -> 119659

Sheet 일별순자산
A1: 일자 | B1: 펀드 | C1: 순자산총액-대변당잔
A2: 기준일 | B2: 좌수 | C2: 순자산
A3: 20220101 | B3: 1700000 | C3: 38739971923
A4: 20220102 | B4: 1700000 | C4: 38739934062
A5: 20220103 | B5: 1700000 | C5: 38964788228
A6: 20220104 | B6: 1700000 | C6: 38891344146
A7: 20220105 | B7: 1700000 | C7: 37848122067
A8: 20220106 | B8: 1700000 | C8: 37067149253
A9: 20220107 | B9: 1700000 | C9: 38017331341
A10: 20220108 | B10: 1700000 | C10: 38017291535
A11: 20220109 | B11: 1700000 | C11: 38017251730
A12: 20220110 | B12: 1700000 | C12: 37327902930
A13: 20220111 | B13: 1700000 | C13: 37620406203
A14: 20220112 | B14: 1700000 | C14: 38824919767
... A366: 20221230 | B366: 2900000 | C366: 35851945337
A367: 20221231 | B367: 2900000 | C367: 35852020455 | T367: 66217908754 | U367: =T367-S367 -> 66217908754
B368: =AVERAGE(B3:B367) -> 2602739.7

Sheet 설정해지내역
A1: Column1 | B1: Column2 | C1: Column3 | D1: Column4 | E1: Column5 | F1: Column6 | G1: Column7 | H1: Column8 | I1: Column9
A2: 기준일 | B2: 기초좌수 | C2: 추가설정 | D2: 추가설정금액 | E2: 일부해지 | F2: 일부해지금액 | G2: 기말좌수 | H2: 적용기준가 | I2: NAV
A3: 20250101 | B3: 3100000 | C3: 0 | D3: 0 | E3: 0 | F3: 0 | G3: 3100000 | H3: 13687.87 | I3: 42432382313
A4: 20250102 | B4: 3100000 | C4: 100000 | D4: 1368790041 | E4: 100000 | F4: 1368790041 | G4: 3100000 | H4: 13687.9 | I4: 42432491295
A5: 20250103 | B5: 3100000 | C5: 100000 | D5: 1362017594 | E5: 100000 | F5: 1362017594 | G5: 3100000 | H5: 13620.18 | I5: 42222545434
A6: 20250104 | B6: 3100000 | C6: 0 | D6: 0 | E6: 0 | F6: 0 | G6: 3100000 | H6: 14206.56 | I6: 44040329603
A7: 20250105 | B7: 3100000 | C7: 0 | D7: 0 | E7: 0 | F7: 0 | G7: 3100000 | H7: 14206.59 | I7: 44040414305
A8: 20250106 | B8: 3100000 | C8: 100000 | D8: 1420661261 | E8: 100000 | F8: 1420661261 | G8: 3100000 | H8: 14206.61 | I8: 44040499107
A9: 20250107 | B9: 3100000 | C9: 100000 | D9: 1477904356 | E9: 100000 | F9: 1477904356 | G9: 3100000 | H9: 14779.04 | I9: 45815035044
